Workbook

Sheet Read Me
A1: PROMPOLU — Niche analysis & viral content workbook
A2: Prepared 22 Oct 2026 · Sources: prompolu.com, TikTok @prompolu, 479 niche TikTok videos · Instagram posts could not be read
A4: Contents (click a name to jump)
A5: Sheet | B5: What it holds
A6: =HYPERLINK("#'Niche & Strategy'!A1","Niche & Strategy") -> Niche & Strategy | B6: Your niche, audiences, what I could and could not see, the one-paragraph strategy
A7: =HYPERLINK("#'My TikTok Videos'!A1","My TikTok Videos") -> My TikTok Videos | B7: Your 10 visible videos with stats, rates and live medians (filmed vs animated)
A8: =HYPERLINK("#'Niche Patterns'!A1","Niche Patterns") -> Niche Patterns | B8: What goes viral in the niche, with live statistics calculated from the dataset
A9: =HYPERLINK("#'Competitors'!A1","Competitors") -> Competitors | B9: Live account table (calculated from the dataset) plus the full competitor map
A10: =HYPERLINK("#'20 Ideas'!A1","20 Ideas") -> 20 Ideas | B10: The 20 TikTok/Reels ideas: hook, shots, caption, evidence, shoot session
A11: =HYPERLINK("#'Briefs'!A1","Briefs") -> Briefs | B11: Full viral brief for each idea: setup, hooks A/B, sound, caption, pinned comment, sequels, watch-outs
A12: =HYPERLINK("#'Shot Lists'!A1","Shot Lists") -> Shot Lists | B12: Every shot-by-shot table, one row per beat, filterable by idea
A13: =HYPERLINK("#'Strategy Ideas (25)'!A1","Strategy Ideas (25)") -> Strategy Ideas (25) | B13: The 25 ideas from the first strategy report, by pillar
A14: =HYPERLINK("#'Calendar'!A1","Calendar") -> Calendar | B14: Six-week posting calendar with status dropdown, plus shoot sessions
A15: =HYPERLINK("#'30-Day Plan'!A1","30-Day Plan") -> 30-Day Plan | B15: The 30-day plan from the strategy report, with fix-first and measurement lists
A16: =HYPERLINK("#'Results Tracker'!A1","Results Tracker") -> Results Tracker | B16: Fill in your results after 48h; formulas suggest what to do next
A17: =HYPERLINK("#'Rules & Checklists'!A1","Rules & Checklists") -> Rules & Checklists | B17: Rules for every video, production standard, posting checklist, review table
A18: =HYPERLINK("#'Study List'!A1","Study List") -> Study List | B18: Moroccan and international videos worth studying, with links
A19: =HYPERLINK("#'Niche Videos'!A1","Niche Videos") -> Niche Videos | B19: The 479-video dataset with stats and the flags used for the statistics
A20: =HYPERLINK("#'Data Notes'!A1","Data Notes") -> Data Notes | B20: Method, definitions, caveats and what is missing
A22: Colour legend
A23: Blue text | B23: A typed-in number you can change (your video stats, tracker inputs, thresholds).
A24: Black text | B24: A formula, or plain text. Formulas recalculate when the inputs or dataset change.
A25: Yellow fill | B25: A cell for you to fill in (Results Tracker, Calendar status).
A26: Niche Videos sheet | B26: Raw public data read on 22 Oct 2026; the numbers are not changeable inputs, so they are left in black.
A28: Scope of the research | B28: Prepared 22 Oct 2026 from: prompolu.com (all 15 pages), TikTok @prompolu (all 10 visible videos, with stats), and 479 niche videos from TikTok search pages.
A29: Companion files | B29: Companion to tiktok-reels-ideas.md (the 20 ideas) and prompolu-content-strategy.md (the research).
A31: An honest note first
A32: Virality | B32: Nobody can guarantee a video goes viral. TikTok doesn't publish how it ranks videos, and reach is lumpy: in your own account one video in ten passed 10K views, and in the 479-video niche sample the typical video got about 7K while a few got millions. What this playbook does is stack the odds: strong first second, short and clear content, something worth sharing or saving, and a reason to comment. Plan to post often, because the winners are hard to predict.
A33: How to read the briefs | B33: Yours = from your own TikTok results. Niche = from the 479-video sample. Untested = a bet. Darija lines are drafts, so adapt them. Spec numbers (kg, mm, finishes) come from prompolu.com; check them against the STRUGAL sheets before you publish.
A35: Related files in the repository
A36: prompolu-content-strategy.md | B36: Full niche analysis, competitor study, 25 ideas, 30-day plan
A37: tiktok-reels-ideas.md | B37: 20 shoot-ready ideas with hooks and shot lists
A38: viral-video-playbook.md | B38: Detailed viral brief for each of the 20 ideas
A39: data/niche-tiktok-videos.csv | B39: The 479-video dataset (third-party phone numbers redacted)

Sheet Niche & Strategy
A1: Niche, audiences and strategy
A2: Text from the strategy report, sections 0, 1 and 5
A4: What I could and could not see
A5: Source | B5: What I got | C5: Gap
A6: prompolu.com | B6: Full read of every page in the sitemap | C6: —
A7: TikTok @prompolu | B7: Profile stats; 10 of 12 videos with exact views, likes, shares, saves, caption, date, cover and frames from the top 3 | C7: 2 videos weren't listed publicly
A8: Instagram @prompolu | B8: Only the headline numbers: 151 followers, 7 following, 15 posts | C8: Instagram blocks logged-out visitors, so I could not see a single post, caption or view count. Nothing below about your Instagram content is data-based.
A9: Competitors | B9: 479 public TikTok videos (188 Moroccan) with exact stats | C9: No Instagram competitor data at all. The sample is what TikTok surfaces for niche searches, so it leans toward popular videos.
B11: If you export Instagram Insights (or screenshot your top 5 reels), I can run the same analysis there.
A13: Your niche
B14: B2B aluminium profile supply for window, door and kitchen fabricators, with an AR sales tool that gives your customers a way to sell.
B15: • You are the official STRUGAL distributor for Fès, Sefrou and the surrounding region (stores on Av. El Wafaa in Fès and Route d'El Menzel in Sefrou), 18+ years in business, delivery across Morocco.
B16: • You sell raw material, not finished windows: 11 sliding systems (S70P to S140RP Infinity), casement systems (S53RP+, S46) plus ALUDOORS doors, interior fit-out profiles (kitchens and dressings with integrated handles), and exterior lines (railings, roller shutters, pergolas, cladding).
B17: • Your customers are menuisiers. Their customers are homeowners who say "I can't picture it".
B18: • Your unfair advantage is the 3D/AR tool (pergola, railing, sliding bay, casement). It's white-labelled to each menuisier, needs no app, loads in about a second on 4G, and returns a complete WhatsApp quote request. I found no competitor in my sample showing anything like it.
B19: • Your voice on the site is plain, practical and workshop-friendly: "Quatre étapes, sans formalité inutile."
B20: Two audiences, one funnel.
B21: 1. Menuisiers (buyers). They care about stock, colours, specs, hardware tricks, delivery and not wasting time.
B22: 2. Homeowners (demand creators). If they ask their menuisier for STRUGAL, the menuisier comes to you. Most of the views in this niche come from this group.
B23: Your content should serve the first group and use the second as a pull-through. Views from homeowners who can't buy from you are nice but they don't pay the bills. Measure WhatsApp enquiries, not views.
A25: Strategy in one paragraph
B26: Own the "workshop's best friend" lane in Darija and French. Post real stock and real hands, with a person who knows the product, at a steady rhythm. Use the viral "one clever mechanism" format on your own STRUGAL systems. Use the 3D/AR tool as your signature series. Pull homeowners toward asking for STRUGAL by name. Put the hook in the first second as on-screen text, caption in Arabic or short French with 3–5 tags, and keep the phone number on the video.

Sheet My TikTok Videos
A1: Your TikTok videos (@prompolu)
A2: 10 of 12 videos were visible. Stats read from the public video pages on 22 Oct 2026. Blue = typed-in data; black = formula.
A4: Video ID | B4: Posted | C4: Type | D4: What it is | E4: Views | F4: Likes | G4: Comments | H4: Shares | I4: Saves | J4: Length (s) | K4: Like rate | L4: Share rate | M4: Save rate | N4: Caption as posted | O4: Music | P4: Notes from the report
A5: 7636091127908650247 | B5: 46146 | C5: Filmed | D5: Folding mosquito net in 3 colours (showroom) | E5: 2732 | F5: 38 | G5: 2 | H5: 25 | I5: 7 | J5: 41 | K5: =IFERROR(F5/E5,0) -> 0.013909224 | L5: =IFERROR(H5/E5,0) -> 0.0091508053 | M5: =IFERROR(I5/E5,0) -> 0.0025622255 | N5: moustiquaire plissé disponible en gris givré , blanc et quartz . #fesal #fes #maroc #moustiquaire #fenetre | O5: Original sound | P5: 25 shares on 2.7K views, a high share count for its reach.
A6: 7657562891347954952 | B6: 46204 | C6: Filmed | D6: Kitchen accessories in the showroom | E6: 2135 | F6: 44 | G6: 4 | H6: 11 | I6: 11 | J6: 84 | K6: =IFERROR(F6/E6,0) -> 0.020608899 | L6: =IFERROR(H6/E6,0) -> 0.0051522248 | M6: =IFERROR(I6/E6,0) -> 0.0051522248 | N6: Accessoires de cuisine #accessoires #aluminum #fes #construction | O6: Original sound
A7: 7671325847072034056 | B7: 46241 | C7: Filmed | D7: POV walk through the stock aisles, colour list on screen | E7: 8073 | F7: 79 | G7: 5 | H7: 14 | I7: 10 | J7: 22 | K7: =IFERROR(F7/E7,0) -> 0.0097857054 | L7: =IFERROR(H7/E7,0) -> 0.0017341756 | M7: =IFERROR(I7/E7,0) -> 0.0012386969 | N7: #fesal #aluminium #fyp #fenêtre #maroc | O7: Original sound | P7: 79 likes, 14 shares.
A8: 7672143043700477202 | B8: 46243 | C8: Filmed | D8: Truck piled with profile bars in a Fès street | E8: 14700 | F8: 127 | G8: 3 | H8: 20 | I8: 15 | J8: 16 | K8: =IFERROR(F8/E8,0) -> 0.0086394558 | L8: =IFERROR(H8/E8,0) -> 0.0013605442 | M8: =IFERROR(I8/E8,0) -> 0.0010204082 | N8: #fyp #fesal #aluminium #maroc #fes | O8: Original sound | P8: 127 likes, 20 shares. No talking, phone number on screen. Your best video.
A9: 7681711882801122578 | B9: 46269 | C9: Filmed | D9: Presenter at the counter: dust fix for the flat lock (verrou plat) | E9: 4546 | F9: 131 | G9: 11 | H9: 26 | I9: 23 | J9: 29 | K9: =IFERROR(F9/E9,0) -> 0.028816542 | L9: =IFERROR(H9/E9,0) -> 0.0057193137 | M9: =IFERROR(I9/E9,0) -> 0.0050593929 | N9: Solution contre poussière pour le verou plat .#fes #alumminium #fenetre #maroc #morocco | O9: Original sound | P9: Most saves (23), shares (26) and comments (11) of any of your videos. 131 likes.
A10: 7689881301532364040 | B10: 46291 | C10: Animated | D10: Profile render, 'Précision architecturale' | E10: 653 | F10: 21 | G10: 2 | H10: 11 | I10: 0 | J10: 8 | K10: =IFERROR(F10/E10,0) -> 0.032159265 | L10: =IFERROR(H10/E10,0) -> 0.016845329 | M10: =IFERROR(I10/E10,0) -> 0 | N10: Decouvrir les autres gammes dans notre siteweb en bio #strugal #aluminium #fes #viral | O10: Licensed: the world we knew (luxury) | P10: Licensed music.
A11: 7689923806797876498 | B11: 46291 | C11: Animated | D11: 'Hello!' brand animation | E11: 227 | F11: 8 | G11: 2 | H11: 0 | I11: 1 | J11: 15 | K11: =IFERROR(F11/E11,0) -> 0.035242291 | L11: =IFERROR(H11/E11,0) -> 0 | M11: =IFERROR(I11/E11,0) -> 0.0044052863 | N11: Retrouvez-nous sur notre site web #aluminium #fes #immobilier #strugal #prompolu | O11: Original sound
A12: 7690695193615617287 | B12: 46293 | C12: Animated | D12: P-logo animation | E12: 312 | F12: 12 | G12: 2 | H12: 9 | I12: 1 | J12: 17 | K12: =IFERROR(F12/E12,0) -> 0.038461538 | L12: =IFERROR(H12/E12,0) -> 0.028846154 | M12: =IFERROR(I12/E12,0) -> 0.0032051282 | N12: Retrouvez nous sur notre siteweb prompolu.com #strugal #aluminium #fes #maroc #ai | O12: Original sound | P12: Caption mentions #ai.
A13: 7698422583078751506 | B13: 46314 | C13: Animated | D13: Brand motion piece | E13: 324 | F13: 14 | G13: 1 | H13: 5 | I13: 0 | J13: 15 | K13: =IFERROR(F13/E13,0) -> 0.043209877 | L13: =IFERROR(H13/E13,0) -> 0.015432099 | M13: =IFERROR(I13/E13,0) -> 0 | N13: Les gammes STRUGAL sont disponibles, Laissez nous vous aidez à trouver le profil qui répond à vos besoins. retrouvez nous sur prompolu.com . #strugal #architecture #viral #aluminium #maroc | O13: Licensed: Velvet Poolside | P13: Licensed music. Only 3 days old.
A14: 7699069673593228562 | B14: 46316 | C14: Animated | D14: Brand motion piece, LANDSCAPE 1024×576 (only 1–3 days old) | E14: 147 | F14: 13 | G14: 1 | H14: 10 | I14: 1 | J14: 20 | K14: =IFERROR(F14/E14,0) -> 0.088435374 | L14: =IFERROR(H14/E14,0) -> 0.068027211 | M14: =IFERROR(I14/E14,0) -> 0.0068027211 | N14: Nouveau style, nouvelle perspective. Retrouvez nous sur notre siteweb www.prompolu.com #strugal #architecture #aluminium #maison #fes . | O14: Original sound | P14: Landscape 16:9. Only 1 day old.
A16: Summary (formulas)
A17: Total views | E17: =SUM(E5:E14) -> 33849
A18: Median views, all 10 | E18: =MEDIAN(E5:E14) -> 1394
A19: Average views, all 10 | E19: =AVERAGE(E5:E14) -> 3384.9
A20: Median views, 5 filmed (rows 5–9) | E20: =MEDIAN(E5:E9) -> 4546
A21: Median views, 5 animated (rows 10–14) | E21: =MEDIAN(E10:E14) -> 312
A22: Filmed ÷ animated (×) | E22: =IFERROR(E20/E21,0) -> 14.570513
A23: Videos above 10,000 views | E23: =COUNTIF(E5:E14,">10000") -> 1
A25: Profile snapshot (typed-in)
A26: Platform | B26: Followers | C26: Following | D26: Likes / posts
A27: TikTok @prompolu | B27: 386 | C27: 4 | D27: 739 likes · 12 videos
A28: Instagram @prompolu | B28: 151 | C28: 7 | D28: 15 posts (posts not readable)
A30: What stands out
D31: 1. Real footage beats brand graphics by about 14×. The five filmed videos have a median of 4,546 views. The five animated or brand-graphic videos have a median of 312. The last two are only 1–3 days old, but the three from 26–28 Sep have had 3+ weeks and are flat. Your audience came for the stock, the trucks and the person at the counter.
D32: 2. Your tip video is the quality signal. It has a third of the truck's views but more saves, shares and comments in absolute numbers. People save and send it. (Rates per view are misleading on your small videos, because their few viewers are mostly followers.) It's the format to build a series on.
D33: 3. Your two biggest videos have hashtag-only captions (#fyp #fesal #aluminium #maroc #fes and similar). The next three add a one-line description. The weak ones say "Retrouvez-nous sur notre site" with #strugal. (#strugal is on all 5 of your weakest videos and none of your top 5. The animated videos also share that tag, so treat it as a hint, not proof.)
D34: 4. The Oct 21 video is landscape (1024×576). On a phone it plays as a thin letterboxed strip. Re-export everything as 9:16.
D35: 5. Posting is sporadic: 10 videos in 5.5 months, with an 8-week gap in May–July. TikTok can't learn who to show you to at this pace.
D36: 6. Brand mismatch. Your top videos carry a "Fesal.aluminium" watermark, the site's footer links to instagram.com/fesal.aluminium and tiktok.com/@fesal.aluminium, but your accounts are @prompolu. TikTok returned an error for @fesal.aluminium and Instagram showed only a login wall for it, so I couldn't confirm either account exists. Check these links; if they're dead or someone else's, you're sending visitors to the wrong place.

Sheet Niche Patterns
A1: What goes viral in the niche
A2: Statistics below are live formulas over the 'Niche Videos' sheet. Medians use array formulas.
A4: Sample size
A5: Videos in the sample | B5: =COUNT('Niche Videos'!$F$2:$F$480) -> 479
A6: Moroccan-tagged videos | B6: =COUNTIF('Niche Videos'!$K$2:$K$480,"yes") -> 188
A7: Median views, all videos | B7: =MEDIAN('Niche Videos'!$F$2:$F$480) -> 7052
A8: Median views, Moroccan videos | B8: {=MEDIAN(IF('Niche Videos'!$K$2:$K$480="yes",'Niche Videos'!$F$2:$F$480))} -> 8810
A9: Median share rate (shares ÷ views), all | B9: =MEDIAN('Niche Videos'!$M$2:$M$480) -> 0.0022857143
A10: Median save rate (saves ÷ views), all | B10: =MEDIAN('Niche Videos'!$N$2:$N$480) -> 0.0028632785
A12: Caption effects (Moroccan videos only)
A13: Caption feature | B13: n with | C13: Median views, with | D13: n without | E13: Median views, without | F13: With ÷ without (×) | G13: Reading
A14: Arabic caption | B14: =COUNTIFS('Niche Videos'!$K$2:$K$480,"yes",'Niche Videos'!$O$2:$O$480,1) -> 85 | C14: {=IFERROR(MEDIAN(IF(('Niche Videos'!$K$2:$K$480="yes")*('Niche Videos'!$O$2:$O$480=1),'Niche Videos'!$F$2:$F$480)),"n/a")} -> 18200 | D14: =COUNTIFS('Niche Videos'!$K$2:$K$480,"yes",'Niche Videos'!$O$2:$O$480,0) -> 103 | E14: {=IFERROR(MEDIAN(IF(('Niche Videos'!$K$2:$K$480="yes")*('Niche Videos'!$O$2:$O$480=0),'Niche Videos'!$F$2:$F$480)),"n/a")} -> 4539 | F14: =IFERROR(C14/E14,"n/a") -> 4.0096938 | G14: About 4× the reach with Arabic (correlation, not proof)
A15: Hashtag-only caption (no text) | B15: =COUNTIFS('Niche Videos'!$K$2:$K$480,"yes",'Niche Videos'!$P$2:$P$480,1) -> 45 | C15: {=IFERROR(MEDIAN(IF(('Niche Videos'!$K$2:$K$480="yes")*('Niche Videos'!$P$2:$P$480=1),'Niche Videos'!$F$2:$F$480)),"n/a")} -> 16800 | D15: =COUNTIFS('Niche Videos'!$K$2:$K$480,"yes",'Niche Videos'!$P$2:$P$480,0) -> 143 | E15: {=IFERROR(MEDIAN(IF(('Niche Videos'!$K$2:$K$480="yes")*('Niche Videos'!$P$2:$P$480=0),'Niche Videos'!$F$2:$F$480)),"n/a")} -> 6833 | F15: =IFERROR(C15/E15,"n/a") -> 2.4586565 | G15: Short captions did better
A16: Phone number in the caption | B16: =COUNTIFS('Niche Videos'!$K$2:$K$480,"yes",'Niche Videos'!$Q$2:$Q$480,1) -> 53 | C16: {=IFERROR(MEDIAN(IF(('Niche Videos'!$K$2:$K$480="yes")*('Niche Videos'!$Q$2:$Q$480=1),'Niche Videos'!$F$2:$F$480)),"n/a")} -> 4768 | D16: =COUNTIFS('Niche Videos'!$K$2:$K$480,"yes",'Niche Videos'!$Q$2:$Q$480,0) -> 135 | E16: {=IFERROR(MEDIAN(IF(('Niche Videos'!$K$2:$K$480="yes")*('Niche Videos'!$Q$2:$Q$480=0),'Niche Videos'!$F$2:$F$480)),"n/a")} -> 13900 | F16: =IFERROR(C16/E16,"n/a") -> 0.34302158 | G16: Numbers in the caption did worse; put it on the video instead
A18: Topic effects (all videos whose caption mentions the topic; categories overlap)
A19: Topic | B19: n videos | C19: Median views | D19: Median share rate | E19: Median save rate | G19: Reading
A20: Kitchen / cuisine | B20: =COUNTIF('Niche Videos'!$R$2:$R$480,1) -> 80 | C20: {=IFERROR(MEDIAN(IF('Niche Videos'!$R$2:$R$480=1,'Niche Videos'!$F$2:$F$480)),"n/a")} -> 29950 | D20: {=IFERROR(MEDIAN(IF('Niche Videos'!$R$2:$R$480=1,'Niche Videos'!$M$2:$M$480)),"n/a")} -> 0.0039059666 | E20: {=IFERROR(MEDIAN(IF('Niche Videos'!$R$2:$R$480=1,'Niche Videos'!$N$2:$N$480)),"n/a")} -> 0.0032004814 | G20: Biggest category in Moroccan aluminium TikTok
A21: Mosquito net | B21: =COUNTIF('Niche Videos'!$S$2:$S$480,1) -> 6 | C21: {=IFERROR(MEDIAN(IF('Niche Videos'!$S$2:$S$480=1,'Niche Videos'!$F$2:$F$480)),"n/a")} -> 5974 | D21: {=IFERROR(MEDIAN(IF('Niche Videos'!$S$2:$S$480=1,'Niche Videos'!$M$2:$M$480)),"n/a")} -> 0.0045718405 | E21: {=IFERROR(MEDIAN(IF('Niche Videos'!$S$2:$S$480=1,'Niche Videos'!$N$2:$N$480)),"n/a")} -> 0.0040105352 | G21: Small sample; high share rate
A22: Sliding / coulissant | B22: =COUNTIF('Niche Videos'!$T$2:$T$480,1) -> 126 | C22: {=IFERROR(MEDIAN(IF('Niche Videos'!$T$2:$T$480=1,'Niche Videos'!$F$2:$F$480)),"n/a")} -> 10244 | D22: {=IFERROR(MEDIAN(IF('Niche Videos'!$T$2:$T$480=1,'Niche Videos'!$M$2:$M$480)),"n/a")} -> 0.0030095558 | E22: {=IFERROR(MEDIAN(IF('Niche Videos'!$T$2:$T$480=1,'Niche Videos'!$N$2:$N$480)),"n/a")} -> 0.0034306226
A23: Pergola / terrace | B23: =COUNTIF('Niche Videos'!$U$2:$U$480,1) -> 38 | C23: {=IFERROR(MEDIAN(IF('Niche Videos'!$U$2:$U$480=1,'Niche Videos'!$F$2:$F$480)),"n/a")} -> 2480.5 | D23: {=IFERROR(MEDIAN(IF('Niche Videos'!$U$2:$U$480=1,'Niche Videos'!$M$2:$M$480)),"n/a")} -> 0.0018542433 | E23: {=IFERROR(MEDIAN(IF('Niche Videos'!$U$2:$U$480=1,'Niche Videos'!$N$2:$N$480)),"n/a")} -> 0.002052779
A24: Railing / garde-corps | B24: =COUNTIF('Niche Videos'!$V$2:$V$480,1) -> 61 | C24: {=IFERROR(MEDIAN(IF('Niche Videos'!$V$2:$V$480=1,'Niche Videos'!$F$2:$F$480)),"n/a")} -> 2462 | D24: {=IFERROR(MEDIAN(IF('Niche Videos'!$V$2:$V$480=1,'Niche Videos'!$M$2:$M$480)),"n/a")} -> 0.002615193 | E24: {=IFERROR(MEDIAN(IF('Niche Videos'!$V$2:$V$480=1,'Niche Videos'!$N$2:$N$480)),"n/a")} -> 0.002983871
A25: Window / fenêtre | B25: =COUNTIF('Niche Videos'!$W$2:$W$480,1) -> 98 | C25: {=IFERROR(MEDIAN(IF('Niche Videos'!$W$2:$W$480=1,'Niche Videos'!$F$2:$F$480)),"n/a")} -> 2013 | D25: {=IFERROR(MEDIAN(IF('Niche Videos'!$W$2:$W$480=1,'Niche Videos'!$M$2:$M$480)),"n/a")} -> 0.0011998391 | E25: {=IFERROR(MEDIAN(IF('Niche Videos'!$W$2:$W$480=1,'Niche Videos'!$N$2:$N$480)),"n/a")} -> 0.0018068146 | G25: Windows alone are weak reach
A26: Door / porte | B26: =COUNTIF('Niche Videos'!$X$2:$X$480,1) -> 147 | C26: {=IFERROR(MEDIAN(IF('Niche Videos'!$X$2:$X$480=1,'Niche Videos'!$F$2:$F$480)),"n/a")} -> 14100 | D26: {=IFERROR(MEDIAN(IF('Niche Videos'!$X$2:$X$480=1,'Niche Videos'!$M$2:$M$480)),"n/a")} -> 0.0024376731 | E26: {=IFERROR(MEDIAN(IF('Niche Videos'!$X$2:$X$480=1,'Niche Videos'!$N$2:$N$480)),"n/a")} -> 0.0032137118
A27: Dressing / wardrobe | B27: =COUNTIF('Niche Videos'!$Y$2:$Y$480,1) -> 20 | C27: {=IFERROR(MEDIAN(IF('Niche Videos'!$Y$2:$Y$480=1,'Niche Videos'!$F$2:$F$480)),"n/a")} -> 7960 | D27: {=IFERROR(MEDIAN(IF('Niche Videos'!$Y$2:$Y$480=1,'Niche Videos'!$M$2:$M$480)),"n/a")} -> 0.0031978322 | E27: {=IFERROR(MEDIAN(IF('Niche Videos'!$Y$2:$Y$480=1,'Niche Videos'!$N$2:$N$480)),"n/a")} -> 0.0023680904
A28: Shower | B28: =COUNTIF('Niche Videos'!$Z$2:$Z$480,1) -> 9 | C28: {=IFERROR(MEDIAN(IF('Niche Videos'!$Z$2:$Z$480=1,'Niche Videos'!$F$2:$F$480)),"n/a")} -> 4692 | D28: {=IFERROR(MEDIAN(IF('Niche Videos'!$Z$2:$Z$480=1,'Niche Videos'!$M$2:$M$480)),"n/a")} -> 0.00088731145 | E28: {=IFERROR(MEDIAN(IF('Niche Videos'!$Z$2:$Z$480=1,'Niche Videos'!$N$2:$N$480)),"n/a")} -> 0.00099307159
A29: Accessories / hardware | B29: =COUNTIF('Niche Videos'!$AA$2:$AA$480,1) -> 9 | C29: {=IFERROR(MEDIAN(IF('Niche Videos'!$AA$2:$AA$480=1,'Niche Videos'!$F$2:$F$480)),"n/a")} -> 8317 | D29: {=IFERROR(MEDIAN(IF('Niche Videos'!$AA$2:$AA$480=1,'Niche Videos'!$M$2:$M$480)),"n/a")} -> 0.001363174 | E29: {=IFERROR(MEDIAN(IF('Niche Videos'!$AA$2:$AA$480=1,'Niche Videos'!$N$2:$N$480)),"n/a")} -> 0.0031261272
A30: Facade / vitrine | B30: =COUNTIF('Niche Videos'!$AB$2:$AB$480,1) -> 29 | C30: {=IFERROR(MEDIAN(IF('Niche Videos'!$AB$2:$AB$480=1,'Niche Videos'!$F$2:$F$480)),"n/a")} -> 4436 | D30: {=IFERROR(MEDIAN(IF('Niche Videos'!$AB$2:$AB$480=1,'Niche Videos'!$M$2:$M$480)),"n/a")} -> 0.0024888004 | E30: {=IFERROR(MEDIAN(IF('Niche Videos'!$AB$2:$AB$480=1,'Niche Videos'!$N$2:$N$480)),"n/a")} -> 0.0029906542
A31: Before / after | B31: =COUNTIF('Niche Videos'!$AC$2:$AC$480,1) -> 15 | C31: {=IFERROR(MEDIAN(IF('Niche Videos'!$AC$2:$AC$480=1,'Niche Videos'!$F$2:$F$480)),"n/a")} -> 1476 | D31: {=IFERROR(MEDIAN(IF('Niche Videos'!$AC$2:$AC$480=1,'Niche Videos'!$M$2:$M$480)),"n/a")} -> 0.001845586 | E31: {=IFERROR(MEDIAN(IF('Niche Videos'!$AC$2:$AC$480=1,'Niche Videos'!$N$2:$N$480)),"n/a")} -> 0.0026071429
A32: Price / prix / devis | B32: =COUNTIF('Niche Videos'!$AD$2:$AD$480,1) -> 30 | C32: {=IFERROR(MEDIAN(IF('Niche Videos'!$AD$2:$AD$480=1,'Niche Videos'!$F$2:$F$480)),"n/a")} -> 12250 | D32: {=IFERROR(MEDIAN(IF('Niche Videos'!$AD$2:$AD$480=1,'Niche Videos'!$M$2:$M$480)),"n/a")} -> 0.0023559633 | E32: {=IFERROR(MEDIAN(IF('Niche Videos'!$AD$2:$AD$480=1,'Niche Videos'!$N$2:$N$480)),"n/a")} -> 0.0038292861 | G32: High save rate: price content gets kept
A34: Length buckets (bounds in blue are editable)
A35: Bucket (seconds) | B35: From (≥) | C35: To (<) | D35: n, all | E35: Median views, all | F35: n, Moroccan | G35: Median views, Moroccan
A36: 0–10 | B36: 0 | C36: 10 | D36: =COUNTIFS('Niche Videos'!$E$2:$E$480,">="&B36,'Niche Videos'!$E$2:$E$480,"<"&C36) -> 35 | E36: {=IFERROR(MEDIAN(IF(('Niche Videos'!$E$2:$E$480>=B36)*('Niche Videos'!$E$2:$E$480<C36),'Niche Videos'!$F$2:$F$480)),"n/a")} -> 10500 | F36: =COUNTIFS('Niche Videos'!$E$2:$E$480,">="&B36,'Niche Videos'!$E$2:$E$480,"<"&C36,'Niche Videos'!$K$2:$K$480,"yes") -> 4 | G36: {=IFERROR(MEDIAN(IF(('Niche Videos'!$E$2:$E$480>=B36)*('Niche Videos'!$E$2:$E$480<C36)*('Niche Videos'!$K$2:$K$480="yes"),'Niche Videos'!$F$2:$F$480)),"n/a")} -> 914000
A37: 10–20 | B37: 10 | C37: 20 | D37: =COUNTIFS('Niche Videos'!$E$2:$E$480,">="&B37,'Niche Videos'!$E$2:$E$480,"<"&C37) -> 105 | E37: {=IFERROR(MEDIAN(IF(('Niche Videos'!$E$2:$E$480>=B37)*('Niche Videos'!$E$2:$E$480<C37),'Niche Videos'!$F$2:$F$480)),"n/a")} -> 7979 | F37: =COUNTIFS('Niche Videos'!$E$2:$E$480,">="&B37,'Niche Videos'!$E$2:$E$480,"<"&C37,'Niche Videos'!$K$2:$K$480,"yes") -> 33 | G37: {=IFERROR(MEDIAN(IF(('Niche Videos'!$E$2:$E$480>=B37)*('Niche Videos'!$E$2:$E$480<C37)*('Niche Videos'!$K$2:$K$480="yes"),'Niche Videos'!$F$2:$F$480)),"n/a")} -> 7468
A38: 20–35 | B38: 20 | C38: 35 | D38: =COUNTIFS('Niche Videos'!$E$2:$E$480,">="&B38,'Niche Videos'!$E$2:$E$480,"<"&C38) -> 144 | E38: {=IFERROR(MEDIAN(IF(('Niche Videos'!$E$2:$E$480>=B38)*('Niche Videos'!$E$2:$E$480<C38),'Niche Videos'!$F$2:$F$480)),"n/a")} -> 3855.5 | F38: =COUNTIFS('Niche Videos'!$E$2:$E$480,">="&B38,'Niche Videos'!$E$2:$E$480,"<"&C38,'Niche Videos'!$K$2:$K$480,"yes") -> 62 | G38: {=IFERROR(MEDIAN(IF(('Niche Videos'!$E$2:$E$480>=B38)*('Niche Videos'!$E$2:$E$480<C38)*('Niche Videos'!$K$2:$K$480="yes"),'Niche Videos'!$F$2:$F$480)),"n/a")} -> 4487.5
A39: 35–60 | B39: 35 | C39: 60 | D39: =COUNTIFS('Niche Videos'!$E$2:$E$480,">="&B39,'Niche Videos'!$E$2:$E$480,"<"&C39) -> 104 | E39: {=IFERROR(MEDIAN(IF(('Niche Videos'!$E$2:$E$480>=B39)*('Niche Videos'!$E$2:$E$480<C39),'Niche Videos'!$F$2:$F$480)),"n/a")} -> 6955.5 | F39: =COUNTIFS('Niche Videos'!$E$2:$E$480,">="&B39,'Niche Videos'!$E$2:$E$480,"<"&C39,'Niche Videos'!$K$2:$K$480,"yes") -> 50 | G39: {=IFERROR(MEDIAN(IF(('Niche Videos'!$E$2:$E$480>=B39)*('Niche Videos'!$E$2:$E$480<C39)*('Niche Videos'!$K$2:$K$480="yes"),'Niche Videos'!$F$2:$F$480)),"n/a")} -> 7294
A40: 60 and over | B40: 60 | C40: 100000 | D40: =COUNTIFS('Niche Videos'!$E$2:$E$480,">="&B40,'Niche Videos'!$E$2:$E$480,"<"&C40) -> 91 | E40: {=IFERROR(MEDIAN(IF(('Niche Videos'!$E$2:$E$480>=B40)*('Niche Videos'!$E$2:$E$480<C40),'Niche Videos'!$F$2:$F$480)),"n/a")} -> 11000 | F40: =COUNTIFS('Niche Videos'!$E$2:$E$480,">="&B40,'Niche Videos'!$E$2:$E$480,"<"&C40,'Niche Videos'!$K$2:$K$480,"yes") -> 39 | G40: {=IFERROR(MEDIAN(IF(('Niche Videos'!$E$2:$E$480>=B40)*('Niche Videos'!$E$2:$E$480<C40)*('Niche Videos'!$K$2:$K$480="yes"),'Niche Videos'!$F$2:$F$480)),"n/a")} -> 15600
A41: Length is a weak signal: under 10 s and over 60 s did better than 20–35 s, but the Moroccan under-10 s group has only a few videos. Hook strength matters more than length.
A43: The big winners (typed from the report)
A44: Who | B44: Views | G44: What
A45: @chinawindowsdoors (206K followers) | B45: 9.0M | G45: 18s: "Easy to install, waterproof, and able to block space" (a folding/sliding door demo)
A46: @proalumad (602K, Moroccan kitchens) | B46: 8.3M | G46: 7 seconds, silent kitchen reveal, Arabic hashtags only
A47: @proalumad | B47: 5.9M | G47: 11s, same format
A48: @windowhome1 (209K) | B48: 3.0M ×2 | G48: 14s: sliding door with no floor track
A49: @siddiquealuminumandglass (12K followers) | B49: 1.8M | G49: 16s: telescopic sliding door
A50: @alu.mamoune (18K followers, Moroccan) | B50: 1.7M | G50: 51s kitchen
A51: @aluminooo (75K, Moroccan) | B51: 839K | G51: 23s shower cabin system, WhatsApp number in caption
A53: Seven patterns (from the report)
A54: 1. Small accounts go big. Accounts with 12K to 18K followers hit 1.7M to 1.8M, and some under 500 followers hit 150K. Follower count isn't the barrier.
A55: 2. A clever mechanism in under 20 seconds. "No drilling", "no track", "disappears into the wall", "telescopic". Each shows one surprising mechanism and nothing else.
A56: 3. Kitchens dominate Moroccan aluminium TikTok. Captions mentioning kitchens have a median of ~30K views (n=80). Doors ~14K, sliding systems ~10K, windows ~2K, pergolas ~2.5K, railings ~2.5K. (Categories overlap and the sample is search-biased.)
A57: 4. Arabic captions get about 4× the reach in Morocco: median 18.2K (n=85) vs 4.5K (n=103) for non-Arabic. Your 10 videos are all French or hashtag-only.
A58: 5. Less caption is better: hashtag-only captions have a median of 16.8K vs 6.8K. Captions that put a phone number in the text do worse (4.8K vs 13.9K). (Your own winners put the number on the video, not in the caption.)
A59: 6. Price and cost content gets saved. Captions mentioning price/prix/devis: median 12K and one of the highest save rates (0.38% of views, n=30, all niche videos).
A60: 7. City tags in the top quartile: #casablanca, #rabat, #bouznika, #mohammedia, plus Arabic category tags like #مطابخ_حديثة_المنيوم.
A61: Length is a weak signal: under 10s and over 60s both did better than the 20–35s middle, but the sample is small. Hook strength matters more than length.
A62: Hashtags in the top quartile of Moroccan videos (static count from my analysis)
A63: Hashtag | B63: Videos in top quartile
A64: #aluminium | B64: 17
A65: #cuisine | B65: 17
A66: #cuisinealuminium | B66: 11
A67: #casablanca | B67: 10
A68: #maroc | B68: 9
A69: #مطابخ_حديثة_المنيوم | B69: 8
A70: #مطابخ_حديثة | B70: 8
A71: #aluminum | B71: 7
A72: #proalumad | B72: 6
A73: #proalum | B73: 5
A74: #rabat | B74: 5
A75: #الدار_البيضاء | B75: 5
... A85: #mohammedia | B85: 3
A86: Counted on the top quarter (47 videos) of the 188 Moroccan-tagged videos. #strugal does not appear among the top hashtags.

Sheet Competitors
A1: Competitor map
A2: Top table: live formulas over the 'Niche Videos' sheet (videos seen in the sample only). Below: the full competitor text from the report.
A4: Account | B4: Followers | C4: Segment | D4: Videos seen | E4: Median views | F4: Best video (views) | G4: Note
A5: @proalumad | B5: =IFERROR(INDEX('Niche Videos'!$C$2:$C$480,MATCH("proalumad",'Niche Videos'!$B$2:$B$480,0)),"n/a") -> 602200 | C5: Tier 1: kitchen fabricator | D5: =COUNTIF('Niche Videos'!$B$2:$B$480,"proalumad") -> 7 | E5: {=IFERROR(MEDIAN(IF('Niche Videos'!$B$2:$B$480="proalumad",'Niche Videos'!$F$2:$F$480)),"n/a")} -> 1300000 | F5: {=IFERROR(MAX(IF('Niche Videos'!$B$2:$B$480="proalumad",'Niche Videos'!$F$2:$F$480)),"n/a")} -> 8300000 | G5: Short silent reveals, Arabic hashtags, no spoken caption. A template for the format.
A6: @alu.mamoune | B6: =IFERROR(INDEX('Niche Videos'!$C$2:$C$480,MATCH("alu.mamoune",'Niche Videos'!$B$2:$B$480,0)),"n/a") -> 18100 | C6: Tier 1: kitchens | D6: =COUNTIF('Niche Videos'!$B$2:$B$480,"alu.mamoune") -> 4 | E6: {=IFERROR(MEDIAN(IF('Niche Videos'!$B$2:$B$480="alu.mamoune",'Niche Videos'!$F$2:$F$480)),"n/a")} -> 182200 | F6: {=IFERROR(MAX(IF('Niche Videos'!$B$2:$B$480="alu.mamoune",'Niche Videos'!$F$2:$F$480)),"n/a")} -> 1700000 | G6: 51-second kitchen reached 1.7M with 18K followers.
A7: @alocuisines | B7: =IFERROR(INDEX('Niche Videos'!$C$2:$C$480,MATCH("alocuisines",'Niche Videos'!$B$2:$B$480,0)),"n/a") -> 47400 | C7: Tier 1: kitchens | D7: =COUNTIF('Niche Videos'!$B$2:$B$480,"alocuisines") -> 5 | E7: {=IFERROR(MEDIAN(IF('Niche Videos'!$B$2:$B$480="alocuisines",'Niche Videos'!$F$2:$F$480)),"n/a")} -> 45700 | F7: {=IFERROR(MAX(IF('Niche Videos'!$B$2:$B$480="alocuisines",'Niche Videos'!$F$2:$F$480)),"n/a")} -> 446300
A8: @aluminium_oujaiou | B8: =IFERROR(INDEX('Niche Videos'!$C$2:$C$480,MATCH("aluminium_oujaiou",'Niche Videos'!$B$2:$B$480,0)),"n/a") -> 23700 | C8: Tier 1: kitchens and interior doors | D8: =COUNTIF('Niche Videos'!$B$2:$B$480,"aluminium_oujaiou") -> 3 | E8: {=IFERROR(MEDIAN(IF('Niche Videos'!$B$2:$B$480="aluminium_oujaiou",'Niche Videos'!$F$2:$F$480)),"n/a")} -> 140600 | F8: {=IFERROR(MAX(IF('Niche Videos'!$B$2:$B$480="aluminium_oujaiou",'Niche Videos'!$F$2:$F$480)),"n/a")} -> 204000
A9: @zaki.aluminiumpro | B9: =IFERROR(INDEX('Niche Videos'!$C$2:$C$480,MATCH("zaki.aluminiumpro",'Niche Videos'!$B$2:$B$480,0)),"n/a") -> 12900 | C9: Tier 1: Casablanca menuiserie | D9: =COUNTIF('Niche Videos'!$B$2:$B$480,"zaki.aluminiumpro") -> 14 | E9: {=IFERROR(MEDIAN(IF('Niche Videos'!$B$2:$B$480="zaki.aluminiumpro",'Niche Videos'!$F$2:$F$480)),"n/a")} -> 18450 | F9: {=IFERROR(MAX(IF('Niche Videos'!$B$2:$B$480="zaki.aluminiumpro",'Niche Videos'!$F$2:$F$480)),"n/a")} -> 161600
A10: @aluminooo | B10: =IFERROR(INDEX('Niche Videos'!$C$2:$C$480,MATCH("aluminooo",'Niche Videos'!$B$2:$B$480,0)),"n/a") -> 74500 | C10: Tier 1: shower cabins | D10: =COUNTIF('Niche Videos'!$B$2:$B$480,"aluminooo") -> 8 | E10: {=IFERROR(MEDIAN(IF('Niche Videos'!$B$2:$B$480="aluminooo",'Niche Videos'!$F$2:$F$480)),"n/a")} -> 5293 | F10: {=IFERROR(MAX(IF('Niche Videos'!$B$2:$B$480="aluminooo",'Niche Videos'!$F$2:$F$480)),"n/a")} -> 839000 | G10: WhatsApp number in the caption; best video 839K.
A11: @rm_accessoires1 | B11: =IFERROR(INDEX('Niche Videos'!$C$2:$C$480,MATCH("rm_accessoires1",'Niche Videos'!$B$2:$B$480,0)),"n/a") -> 2282 | C11: Tier 2: wholesale hardware | D11: =COUNTIF('Niche Videos'!$B$2:$B$480,"rm_accessoires1") -> 1 | E11: {=IFERROR(MEDIAN(IF('Niche Videos'!$B$2:$B$480="rm_accessoires1",'Niche Videos'!$F$2:$F$480)),"n/a")} -> 8317 | F11: {=IFERROR(MAX(IF('Niche Videos'!$B$2:$B$480="rm_accessoires1",'Niche Videos'!$F$2:$F$480)),"n/a")} -> 8317 | G11: Charnière 3D wholesale clip: 8.3K views for a tiny account.
A12: @skymaxmaroc.ma | B12: =IFERROR(INDEX('Niche Videos'!$C$2:$C$480,MATCH("skymaxmaroc.ma",'Niche Videos'!$B$2:$B$480,0)),"n/a") -> 3247 | C12: Tier 2: cladding supplier | D12: =COUNTIF('Niche Videos'!$B$2:$B$480,"skymaxmaroc.ma") -> 7 | E12: {=IFERROR(MEDIAN(IF('Niche Videos'!$B$2:$B$480="skymaxmaroc.ma",'Niche Videos'!$F$2:$F$480)),"n/a")} -> 1808 | F12: {=IFERROR(MAX(IF('Niche Videos'!$B$2:$B$480="skymaxmaroc.ma",'Niche Videos'!$F$2:$F$480)),"n/a")} -> 23700 | G12: Near-identical captions on 7 videos; repetition without variety does not scale.
A13: @markglassoffciel | B13: =IFERROR(INDEX('Niche Videos'!$C$2:$C$480,MATCH("markglassoffciel",'Niche Videos'!$B$2:$B$480,0)),"n/a") -> 12800 | C13: Tier 2: glass and aluminium | D13: =COUNTIF('Niche Videos'!$B$2:$B$480,"markglassoffciel") -> 16 | E13: {=IFERROR(MEDIAN(IF('Niche Videos'!$B$2:$B$480="markglassoffciel",'Niche Videos'!$F$2:$F$480)),"n/a")} -> 2134 | F13: {=IFERROR(MAX(IF('Niche Videos'!$B$2:$B$480="markglassoffciel",'Niche Videos'!$F$2:$F$480)),"n/a")} -> 52300 | G13: Same sales caption on its top videos.
A14: @pukapergola | B14: =IFERROR(INDEX('Niche Videos'!$C$2:$C$480,MATCH("pukapergola",'Niche Videos'!$B$2:$B$480,0)),"n/a") -> 18600 | C14: Tier 2: pergolas | D14: =COUNTIF('Niche Videos'!$B$2:$B$480,"pukapergola") -> 2 | E14: {=IFERROR(MEDIAN(IF('Niche Videos'!$B$2:$B$480="pukapergola",'Niche Videos'!$F$2:$F$480)),"n/a")} -> 10750 | F14: {=IFERROR(MAX(IF('Niche Videos'!$B$2:$B$480="pukapergola",'Niche Videos'!$F$2:$F$480)),"n/a")} -> 10900 | G14: 80-second videos pitching European-standard profiles, the same angle as your STRUGAL pitch.
A15: @rofof.fes | B15: =IFERROR(INDEX('Niche Videos'!$C$2:$C$480,MATCH("rofof.fes",'Niche Videos'!$B$2:$B$480,0)),"n/a") -> 328 | C15: Tier 3: local (Fès) | D15: =COUNTIF('Niche Videos'!$B$2:$B$480,"rofof.fes") -> 1 | E15: {=IFERROR(MEDIAN(IF('Niche Videos'!$B$2:$B$480="rofof.fes",'Niche Videos'!$F$2:$F$480)),"n/a")} -> 17300 | F15: {=IFERROR(MAX(IF('Niche Videos'!$B$2:$B$480="rofof.fes",'Niche Videos'!$F$2:$F$480)),"n/a")} -> 17300 | G15: 328 followers; a 10 s Arabic+French kitchen clip reached 17.3K.
A16: @rais48alum | B16: =IFERROR(INDEX('Niche Videos'!$C$2:$C$480,MATCH("rais48alum",'Niche Videos'!$B$2:$B$480,0)),"n/a") -> 2768 | C16: Tier 3: local (Oujda) | D16: =COUNTIF('Niche Videos'!$B$2:$B$480,"rais48alum") -> 3 | E16: {=IFERROR(MEDIAN(IF('Niche Videos'!$B$2:$B$480="rais48alum",'Niche Videos'!$F$2:$F$480)),"n/a")} -> 4874 | F16: {=IFERROR(MAX(IF('Niche Videos'!$B$2:$B$480="rais48alum",'Niche Videos'!$F$2:$F$480)),"n/a")} -> 5213
A17: @aluminiumziyou | B17: =IFERROR(INDEX('Niche Videos'!$C$2:$C$480,MATCH("aluminiumziyou",'Niche Videos'!$B$2:$B$480,0)),"n/a") -> 139 | C17: Tier 3: local (Fès) | D17: =COUNTIF('Niche Videos'!$B$2:$B$480,"aluminiumziyou") -> 1 | E17: {=IFERROR(MEDIAN(IF('Niche Videos'!$B$2:$B$480="aluminiumziyou",'Niche Videos'!$F$2:$F$480)),"n/a")} -> 3125 | F17: {=IFERROR(MAX(IF('Niche Videos'!$B$2:$B$480="aluminiumziyou",'Niche Videos'!$F$2:$F$480)),"n/a")} -> 3125 | G17: 139 followers.
A18: @chinawindowsdoors | B18: =IFERROR(INDEX('Niche Videos'!$C$2:$C$480,MATCH("chinawindowsdoors",'Niche Videos'!$B$2:$B$480,0)),"n/a") -> 206000 | C18: International | D18: =COUNTIF('Niche Videos'!$B$2:$B$480,"chinawindowsdoors") -> 5 | E18: {=IFERROR(MEDIAN(IF('Niche Videos'!$B$2:$B$480="chinawindowsdoors",'Niche Videos'!$F$2:$F$480)),"n/a")} -> 2000000 | F18: {=IFERROR(MAX(IF('Niche Videos'!$B$2:$B$480="chinawindowsdoors",'Niche Videos'!$F$2:$F$480)),"n/a")} -> 9000000 | G18: One mechanism, shot clean, under 20 s, English text overlay.
A19: @windowhome1 | B19: =IFERROR(INDEX('Niche Videos'!$C$2:$C$480,MATCH("windowhome1",'Niche Videos'!$B$2:$B$480,0)),"n/a") -> 208900 | C19: International | D19: =COUNTIF('Niche Videos'!$B$2:$B$480,"windowhome1") -> 2 | E19: {=IFERROR(MEDIAN(IF('Niche Videos'!$B$2:$B$480="windowhome1",'Niche Videos'!$F$2:$F$480)),"n/a")} -> 3000000 | F19: {=IFERROR(MAX(IF('Niche Videos'!$B$2:$B$480="windowhome1",'Niche Videos'!$F$2:$F$480)),"n/a")} -> 3000000 | G19: Sliding door with no floor track (3.0M twice).
A20: @omy.window.and.door0 | B20: =IFERROR(INDEX('Niche Videos'!$C$2:$C$480,MATCH("omy.window.and.door0",'Niche Videos'!$B$2:$B$480,0)),"n/a") -> 16400 | C20: International | D20: =COUNTIF('Niche Videos'!$B$2:$B$480,"omy.window.and.door0") -> 1 | E20: {=IFERROR(MEDIAN(IF('Niche Videos'!$B$2:$B$480="omy.window.and.door0",'Niche Videos'!$F$2:$F$480)),"n/a")} -> 3200000 | F20: {=IFERROR(MAX(IF('Niche Videos'!$B$2:$B$480="omy.window.and.door0",'Niche Videos'!$F$2:$F$480)),"n/a")} -> 3200000
A21: @siddiquealuminumandglass | B21: =IFERROR(INDEX('Niche Videos'!$C$2:$C$480,MATCH("siddiquealuminumandglass",'Niche Videos'!$B$2:$B$480,0)),"n/a") -> 12100 | C21: International | D21: =COUNTIF('Niche Videos'!$B$2:$B$480,"siddiquealuminumandglass") -> 4 | E21: {=IFERROR(MEDIAN(IF('Niche Videos'!$B$2:$B$480="siddiquealuminumandglass",'Niche Videos'!$F$2:$F$480)),"n/a")} -> 147450 | F21: {=IFERROR(MAX(IF('Niche Videos'!$B$2:$B$480="siddiquealuminumandglass",'Niche Videos'!$F$2:$F$480)),"n/a")} -> 1800000 | G21: Telescopic sliding door, 1.8M with 12K followers.
A23: Full competitor map (from the report)
A24: Tier 1: kitchen fabricators with huge reach (not your peers, but their format is a template)
A25: • @proalumad: 602K followers, median 1.3M views on the 7 videos I saw. Short silent reveals, Arabic hashtags, no spoken caption.
A26: • @alu.mamoune (18K), @alocuisines (47K), @aluminium_oujaiou (24K), @zaki.aluminiumpro (13K, median 18K, best 162K).
A27: • @aluminooo (75K): shower cabins with a WhatsApp number.
A28: Tier 2: suppliers, the closest to what you do
A29: Account | B29: Followers | C29: What they post | G29: Read
A30: @rm_accessoires1 | B30: 2.3K | C30: Wholesale hardware ("Charnière 3D… للبيع بالجملة"), 16s clip | G30: 8.3K views for a tiny account. Wholesale hardware demos do get seen.
A31: @skymaxmaroc.ma | B31: 3.2K | C31: WPC cladding supplier, near-identical captions on 7 videos | G31: Median 1.8K; the best one hit 23.7K. Repetition without variety doesn't scale.
A32: @markglassoffciel | B32: 12.8K | C32: Glass and aluminium; the same sales caption on its top videos | G32: Median 2.1K; a few reach ~50K
A33: @pukapergola | B33: 18.6K | C33: Bioclimatic pergolas, 80s videos pitching "profils certifiés normes européennes" | G33: ~10.7K each. Same "European standards" angle as your STRUGAL pitch.
A35: Tier 3: your actual local competitors (Fès / Meknès / Oujda)
A36: Almost empty. Only 14 of 479 videos mention Fès, Meknès, Taza, Oujda, Nador or nearby, and a few of those aren't aluminium at all. The notable ones: @rofof.fes (328 followers, a 10s Arabic+French kitchen clip at 17.3K), @rais48alum (Oujda, 2.8K followers, 2.7K–5.2K per video), @aluminiumziyou (139 followers). Nobody is the "profile supplier of the Fès region" on TikTok.
A37: International (borrow the visuals, not the language)
A38: • @chinawindowsdoors, @windowhome1, @omy.window.and.door0, @siddiquealuminumandglass all follow one formula: one mechanism, shot clean, under 20s, English text overlay. They hold the views record in the niche.
A39: The gaps nobody fills (in my sample)
A40: 1. Nobody pairs "official distributor" authority with real stock footage, a trust angle you already own.
A41: 2. Nobody shows technical know-how as entertainment (your dust-fix video proves the appetite).
A42: 3. Nobody has the AR/3D tool, or at least nobody is showing one.
A43: 4. Fès/Sefrou is open.
A44: 5. Nobody teaches the end customer to ask for a system by name ("ask your menuisier for S90RP").

Sheet 20 Ideas
A1: # | B1: Pillar | C1: Idea | D1: Title in the first ideas list | E1: Hook (FR / Darija) | F1: Shots (summary) | G1: Length | H1: Triggers | I1: Evidence basis | J1: Why | K1: Caption & tags | L1: CTA / safety | M1: Shoot session
A2: 1 | B2: Stock, trucks, colours | C2: "Ce camion part pour [ville]" | E2: Ce camion part pour Meknès ce matin / هاد الكاميو غادي لمكناس دابا | F2: (1) truck loaded with bars at the store, (2) it pulls away, (3) city name appears on screen. No talking. 10–16s. | G2: 12–15s | H2: Rewatch · Local · Real | I2: Yours (your best video, 14.7K views, 127 likes, 20 shares) | J2: Yours: the truck video is your best at 14.7K views. Make it a weekly series and change the city each time, so you reach local audiences and show "livraison partout au Maroc" without saying it. | K2: Livraison du jour 🚚 #aluminium #maroc #fes #meknes #نجارة_الألمنيوم | M2: Stock & trucks
A3: 2 | B3: Stock, trucks, colours | C3: "Même profil, 6 teintes" | E3: Même profil. 6 teintes. Laquelle choisit ton client ? / نفس البروفيل، 6 ألوان. أي لون غادي يختار الزبون؟ | F3: (1) walk down the aisle, (2) each colour labelled as it passes: noir, gris naturel, fauxbois, blanc 9010, gris platine, gris givré, (3) end on the same section in three colours side by side. 15–22s. | G3: 18–21s | H3: Comment · Rewatch · Real | I3: Yours (stock walk, 8K views) | J3: Yours: the stock walk got 8K. The side-by-side ending turns a passive tour into a choice people comment on. | K3: Quelle teinte pour ta menuiserie ? 👇 #aluminium #fes #maroc #menuiserie #strugal | M3: Stock & trucks
A4: 3 | B4: Stock, trucks, colours | C4: "Arrivage" | E4: Nouvel arrivage S88RP / وصلات السلعة الجديدة | F4: a delivery being unloaded or a fresh bundle opened. Natural sound only. 8–12s. | G4: 8–12s | H4: Rewatch · Real | I4: Yours/Niche (raw stock is what your audience watches; very short silent clips are @proalumad's format) | J4: Yours/Niche: raw stock footage is what your audience already watches. Very short silent clips are what the biggest Moroccan account (@proalumad) uses. | K4: Arrivage ✅ #aluminium #strugal #fes #maroc #نجارة_الألمنيوم | M4: Stock & trucks
A5: 4 | B5: Stock, trucks, colours | C5: Folding mosquito net in three colours | E5: Moustiquaire plissée : gris givré, blanc, quartz / الناموسية المطوية فـ 3 ألوان | F5: hands pull the net across a window, one colour after another. 10–15s. | G5: 12–15s | H5: Share · Real | I5: Yours (25 shares on 2.7K views, a high ratio) | J5: Yours: your May mosquito-net video had 25 shares on 2.7K views, which is a high share count for its reach, so people send it to someone who needs one. | K5: Moustiquaire plissée : 3 teintes disponibles #moustiquaire #fenetre #maroc #fes #aluminium | M5: Stock & trucks
A6: 5 | B6: Counter tips (your most-saved format) | C6: "L'astuce du comptoir" (series) | D6: "Une astuce de 20 secondes" (dust fix, part 2) | E6: Une astuce de 20 secondes qui évite les retours / حيلة د 20 ثانية كتحميك من المشاكل | F6: same counter, same camera as your Sept video. Hold the profile and part, show one fix, finish with a question: Et toi, tu fais comment ? 20–30s. | G6: 22–28s | H6: Save · Share · Comment | I6: Yours (the dust-fix video has your most saves 23, shares 26, comments 11) | J6: Yours: the dust-fix video has the most saves (23), shares (26) and comments (11) of anything you've posted. The fixed setup lets viewers recognise the series. Run it weekly and pick topics from real customer questions. | K6: a question. Tu fais comment, toi ? 👇 #aluminium #menuiserie #fes #maroc #نجارة_الألمنيوم | M6: Counter
A7: 6 | B7: Counter tips (your most-saved format) | C7: S70P vs S90RP in your hands | E7: Où est la rupture de pont thermique ? / فين كاينة قطعة العزل الحراري؟ | F7: two profiles side by side, finger on the thermal barrier, then the frame sizes (your site: S90 has a 90 mm frame). 20–30s. | G7: 22–25s | H7: Save · Comment · Rewatch | I7: Untested (your site describes exactly this demo) | J7: Yours/Untested: your site says handling profiles "apprend en deux minutes ce qu'un catalogue met une heure à expliquer". This is that, on camera. | K7: S70P ou S90RP ? 👇 #coulissant #aluminium #menuiserie #fes #maroc | M7: Counter
A8: 7 | B8: Counter tips (your most-saved format) | C8: Quiz: "Quel profil porte 400 kg ?" | E8: Lequel porte 400 kg par vantail ? / شمن بروفيل كيحمل 400 كيلو؟ | F8: four profile close-ups labelled S70P, S90RP, S88RP, S110P. Pause 2 seconds, reveal S110P. Pin the full list in a comment: S70P 80 kg, S90RP 160 kg, S88RP 200–300 kg, S110P 400 kg (from your site). | G8: 15s | H8: Comment · Rewatch | I8: Untested | J8: Untested: built-in comment bait with a checkable answer. Don't include the S125RP in the options, because your site flags its limits as needing validation. | K8: Ton avis ? 👇 #aluminium #coulissant #menuiserie #maroc #fes | M8: Counter
A9: 8 | B9: Counter tips (your most-saved format) | C9: "Pourquoi deux devis sont différents" | D9: "Pourquoi deux devis de profilés sont différents" | E9: Même profilé, deux prix. Pourquoi ? / علاش جوج devis د البروفيلي مختلفين فالثمن؟ | F9: four quick text beats, one per factor from your FAQ: référence, quantité, finition, destination. Film the presenter at the counter. 20s. | G9: 20s | H9: Save · Share | I9: Niche (price/devis captions: median 12K views, save rate 0.38%, n=30) | J9: Niche: captions about price/devis had a median of 12K views and a high save rate (0.38%, n=30). It needs no actual prices. | K9: Les 4 choses qui changent le prix #aluminium #devis #menuiserie #fes #maroc | M9: Counter
A10: 9 | B10: The 3D/AR tool | C10: "Il hésite ? Montre-lui chez lui" | E10: Ton client n'arrive pas à se projeter ? / الزبون ما قادرش يتخيل؟ شوف هاد الحل | F10: screen recording. Empty terrace, then a pergola appears at real size, rotates, changes colour. 15–25s. | G10: 20–25s | H10: Share · Rewatch · Comment | I10: Untested (nobody in the sample shows this) | J10: Untested, but it's the one thing no competitor in my sample shows, and your site gives the selling points (no app, loads in about a second on 4G). | K10: Voir sa pergola chez soi avant de signer 🤯 #pergola #pergolabioclimatique #maroc #fes #بيرغولا | L10: CTA: Menuisiers : demandez votre lien. It's for professional customers only, which makes it exclusive. | M10: Screen recording
A11: 10 | B11: The 3D/AR tool | C11: "Pergola configurée en 30 secondes" | D11: Pergola in 30 seconds | E11: Une pergola 4,20 × 6,00 m configurée en 30 secondes / بيرغولا فـ 30 ثانية | F11: screen recording with a visible timer: size, colour, blades, LED, then the WhatsApp quote request arriving. 30s. | G11: 30s | H11: Rewatch · Share | I11: Untested | J11: Untested: speed-run formats work as proof. The WhatsApp ending shows the benefit for the menuisier: a complete request with sizes and finish. | K11: Un devis complet en 30 secondes #pergola #aluminium #devis #maroc #fes | M11: Screen recording
A12: 11 | B12: The 3D/AR tool | C12: A menuisier and his client | E12: Comment ce menuisier convainc son client avant la signature / كيفاش هاد النجار كيقنع الزبون قبل ما يوقع | F12: ask a customer workshop to film themselves showing the tool to a client (their own logo and link). Tag them. 20–30s. | G12: 20–30s | H12: Share · Real | I12: Untested | J12: Untested: a customer's own video is more credible than yours, and they'll repost it. Start with 3 workshops. | K12: Montrer avant de vendre #menuisier #aluminium #maroc #fes #pergola | M12: Ask a favour (3 customer workshops)
A13: 12 | B13: "One clever mechanism" | C13: The window that disappears | E13: La fenêtre qui disparaît / الشباك لي كيتخبى فالحيط | F13: an S88RP with galandage: the leaf slides fully into the wall. No talking. 8–12s. | G13: 10–12s | H13: Rewatch · Share | I13: Niche (one surprising mechanism, under 20 seconds: 1.8M to 9M views for others) | J13: Niche: the biggest videos here show a single surprising mechanism in under 20 seconds (1.8M to 9M views). Your site lists galandage as an S88RP option. | K13: La fenêtre qui disparaît 👀 #fenetre #coulissant #galandage #maroc #نجارة_الألمنيوم | M13: Stock & trucks
A14: 13 | B14: "One clever mechanism" | C14: The thinnest frame (S86RP) | D14: The thinnest frame in the range | E14: 42 mm au centre. Le plus fin. / أنحف بروفيل | F14: close-up of the S86RP centre section against a bright view. 8–10s. | G14: 8–12s | H14: Rewatch · Share | I14: Niche (same format as #12), built on your own spec | J14: Niche: same format as #12, based on your own spec (42 mm at the centre). | K14: Le plus fin du catalogue #coulissant #aluminium #architecture #maroc #fes | M14: Stock & trucks
A15: 14 | B15: "One clever mechanism" | C15: "400 kg sur un seul vantail" | D15: "400 kg… pour de vrai ?" | E15: Un vantail de 400 kg ? / واش بصح كيحمل 400 كيلو؟ | F15: loads added in steps on a supervised mock-up, with a clean cut at the end. 15–20s. | G15: 17s | H15: Rewatch · Comment | I15: Untested | J15: Untested: spectacle plus a spec people remember. | K15: Un vantail de 400 kg 🤯 #coulissant #aluminium #maroc #fes #architecture | L15: Safety: use a rig, not real glass, and don't imply it's a certified test. The figure comes from your site, so check it against the STRUGAL sheet first. | M15: Try later (needs safe rig)
A16: 15 | B16: Kitchens and dressings | C16: Integrated handle, silent reveal | E16: La poignée qu'on ne voit pas / المقبض لي ما كيبانش | F16: a kitchen door opens by its integrated handle profile. No talking, no voiceover. 5–10s. | G16: 7s | H16: Rewatch · Share | I16: Niche (kitchen captions: median ~30K views; @proalumad's 7-second silent reveal hit 8.3M) | J16: Niche: kitchens have a median of ~30K views in this sample, and @proalumad's 7-second silent kitchen reveal reached 8.3M. Kitchen fabricators are your customers, so the people who watch are the people who buy. | K16: المقبض لي ما كيبانش #cuisinealuminium #مطابخ_حديثة_المنيوم #fes #maroc | M16: Kitchen / dressing
A17: 16 | B17: Kitchens and dressings | C17: One dressing, three finishes | E17: Bicolore, effet bois ou anodisé ? / أي تشطيب كتفضل؟ | F17: the same profile in three finishes, wipe or swipe between them. 10–15s. | G17: 13s | H17: Comment · Rewatch | I17: Niche/Untested | J17: Niche/Untested: your site names these finishes for the S90RP, and a "pick one" question drives comments. | K17: Ton choix ? #dressing #aluminium #maroc #fes #design | M17: Kitchen / dressing
A18: 17 | B18: Humour, trust and replies | C18: Skit: "un petit coulissant" | E18: Le client veut un « petit coulissant »… / بغيت غير coulissant صغير… | F18: the client holds out his hands, then a tape measure reads 4 metres. 15s, Darija, two people. | G18: 15s, Darija, French subtitles | H18: Share · Comment | I18: Untested. Try 2–3 skits and keep it only if it earns shares. | J18: Untested: relatable humour about the menuisier's daily life. Try it 2 or 3 times, then keep it only if it earns shares. | K18: Tous les menuisiers connaissent 😅 #menuisier #aluminium #maroc #humour #fes | M18: Try later
A19: 18 | B19: Humour, trust and replies | C19: "L'aluminium rouille ?" | E19: L'aluminium rouille ? / واش الألمنيوم كيصدا؟ | F19: answer in one sentence, then show why (your exterior page: it forms a thin protective oxide layer and doesn't rust). 15–20s. | G19: 15–20s | H19: Share · Save | I19: Untested (your exterior page already has the facts) | J19: Untested: your site already has the explanation. Myth-busting is easy to share with a customer who asked the same thing. | K19: Le mythe qui revient tout le temps #aluminium #menuiserie #maroc #fes #bricolage | M19: Try later
A20: 19 | B20: Humour, trust and replies | C20: "Touchez avant de commander" (Sefrou showroom) | E20: Le showroom où tu peux tout comparer en main / جرّب بيدك قبل ما تطلب | F20: walk through the Sefrou showroom, pick up two profiles, show opening hours (lundi–samedi, 9h–19h). 20–25s. | G20: 20–22s | H20: Local · Real | I20: Yours/Untested (your best videos are shop-floor footage) | J20: Yours/Untested: your top videos are shop-floor footage. This turns the showroom into the reason to visit. | K20: Le showroom STRUGAL de Sefrou #sefrou #strugal #aluminium #maroc #fes | M20: Counter
A21: 20 | B21: Humour, trust and replies | C21: Reply video to a menuisier's comment | D21: Reply to a menuisier's comment | E21: the commenter's question on screen as a video reply, then your answer. | F21: 15–30s at the counter, one question, one answer. | G21: 15–30s | H21: Comment · Local | I21: Niche (your comment counts are only 1–11) | J21: Niche: your comment counts are 1–11, so any reply you give is also a reason for them to comment again. These cost almost nothing to film. | K21: Réponse à @… #aluminium #menuiserie #fes #maroc | M21: Counter
A23: How to read the ideas (from the ideas file)
B24: Built from the research in prompolu-content-strategy.md: your 10 TikToks, 479 niche videos (188 Moroccan) and the specs on prompolu.com.
B25: How to read each card
B26: • Hook: the on-screen text for the first 1–2 seconds, in French and Darija. The Darija lines are drafts, so change them to how you actually speak.
B27: • Shots: what to film, beat by beat.
B28: • Why: the evidence. Yours = your own TikTok results. Niche = the 479-video sample. Untested = a reasonable bet with no data behind it.
B29: • Length is a target, not a rule. Everything is 9:16.

Sheet Briefs
A1: # | B1: Idea | C1: Pillar | D1: Length | E1: Triggers | F1: Evidence | G1: Why it can travel | H1: Setup | I1: Hooks (A/B/bank) | J1: Sound & edit | K1: Caption | L1: Tags | M1: Pinned comment | N1: Next episodes | O1: Watch-outs | P1: Win signal | Q1: Extra notes
A2: 1 | B2: "Ce camion part pour [ville]" | C2: Stock, trucks, colours | D2: 12–15s | E2: Rewatch · Local · Real | F2: Yours (your best video, 14.7K views, 127 likes, 20 shares) | G2: spectacle (a truck piled high with bars) plus a local reveal. It shows "livraison partout au Maroc" without saying it. | H2: Setup: film from behind at street level. Fix the phone (wall, tripod or a helper standing still). Morning light. Ask someone to tighten the straps on camera. Check: nothing in frame that identifies a customer. | I2: Hook A (statement): Ce camion part pour Meknès ce matin / هاد الكاميو غادي لمكناس دابا Hook B (curiosity): Devine où part ce camion 🚚, with the city hidden until 10s. People watch to the end and comment guesses. | J2: no cuts during the drive-away; it's more satisfying as one take. Use a different city each time. | K2: Livraison du jour 🚚 | L2: #aluminium #maroc #fes #meknes #نجارة_الألمنيوم | M2: On livre partout au Maroc. Dites-nous votre ville 👇 (the city comments are proof, and your next videos' destinations). | N2: (a) the truck arriving at the workshop, with the menuisier's permission; (b) loading in time-lapse (8×); (c) after 10 deliveries, a map video with pins; (d) "Livré à Taza / Oujda / Casablanca" to open new regions. | O2: blur faces and plates that aren't yours. Don't block the road for the shot. | P2: beats 14.7K, or shares above 0.15% of views.
A3: 2 | B3: "Même profil, 6 teintes" | C3: Stock, trucks, colours | D3: 18–21s | E3: Comment · Rewatch · Real | F3: Yours (stock walk, 8K views) | G3: a quick sequence people replay to catch every colour, plus a pick-one question. | H3: walk the aisle at a steady pace, phone at chest height in both hands (or a gimbal). Bright, even light. | I3: Hook A: Même profil. 6 teintes. / نفس البروفيل، 6 ألوان Hook B (Arabic first): أي لون كتختار لفيلا فاس؟ | J3: time each label to a footstep. Add "Teintes indicatives (écran)" in small text, which your own site says about screen colours. | K3: Quelle teinte pour ta menuiserie ? 👇 | L3: #aluminium #fes #maroc #menuiserie #strugal | M3: the colour list and Demandez le stock du jour sur WhatsApp. | N3: "Teinte du mois"; RAL 7016 vs 9016 on a real window (your site's AR examples use RAL 7016, 9006 and 9016); the same window in 3 colours. | O3: only list colours actually in stock. | P3: comment replies naming a number or colour, and shares above 0.2%.
A4: 3 | B4: "Arrivage" | C4: Stock, trucks, colours | D4: 8–12s | E4: Rewatch · Real | F4: Yours/Niche (raw stock is what your audience watches; very short silent clips are @proalumad's format) | G4: it's satisfying. The sound of straps and sliding bars is half of it. | H4: film only a real delivery. Hold the phone close to the strap and the bundle. Wind off, no music. | I4: Nouvel arrivage S88RP / وصلات السلعة الجديدة | K4: Arrivage ✅ | L4: #aluminium #strugal #fes #maroc #نجارة_الألمنيوم | M4: Quelle référence vous cherchez ? | N4: "Arrivage #2"; empty truck → full shelf in 15s; the oldest and newest profile in the store. | O4: announce only what's really in stock, or WhatsApp fills with disappointed messages. | P4: WhatsApp enquiries naming the reference.
A5: 4 | B5: Folding mosquito net in three colours | C5: Stock, trucks, colours | D5: 12–15s | E5: Share · Real | F5: Yours (25 shares on 2.7K views, a high ratio) | G5: people send it to someone who needs one. | H5: a real window in daylight; three net samples. | I5: Hook A: Elle se plie dans le coin 👀 / الناموسية كتتطوى فالركن Hook B: Fenêtre ouverte, moustiques dehors. | K5: Moustiquaire plissée : 3 teintes disponibles | L5: #moustiquaire #fenetre #maroc #fes #aluminium | M5: Tag quelqu'un qui en a besoin 👇 (this prompts the shares you already get). | N5: net on a French door; the 3 colours on 3 window colours; how it's fitted (only if you can show it simply). | O5: strongest from spring to summer. Re-post it in April. | P5: shares per 1,000 views above 5.
A6: 5 | B6: "L'astuce du comptoir" (series) | C6: Counter tips (your most-saved format) | D6: 22–28s | E6: Save · Share · Comment | F6: Yours (the dust-fix video has your most saves 23, shares 26, comments 11) | G6: it's useful to exactly the person you want to reach, and menuisiers send tricks to each other. | H6: the same counter, camera and outfit as the September video so viewers recognise it. A small tripod at eye level, warm light, a clean background. The series name is a small text tag in the corner, not a separate intro. | I6: Hook bank: Une erreur qui coûte un retour de chantier / غلطة كتكلف رجوع من الورش · Personne ne t'a montré ça · Une astuce de 20 secondes / حيلة د 20 ثانية | K6: a question. Tu fais comment, toi ? 👇 | L6: #aluminium #menuiserie #fes #maroc #نجارة_الألمنيوم | M6: the tip in one line (saveable). | N6: reply videos to the best comments (#20); "Partie 2"; a "wrong way / right way" split screen. | O6: every technical claim must be correct. If you aren't sure, ask STRUGAL or your most experienced fitter. | P6: saves ≥ shares, and menuisiers posting their own tricks in the comments. | Q6: Topic backlog: (the first five come from your site, so they're safe; the rest are yours to validate): 1. Dust fix for the flat lock, part 2 (your own). 2. What the letters mean: P, R, RP (your site explains them). 3. Maximum glazing per system (S70P 21 mm, S88 32 mm). 4. Leaf weight vs system choice. 5. How to write a quote request (reference, quantity, finish, city). 6. Where the thermal barrier sits and why it matters. 7. Your own workshop tricks: rollers, drainage, gaskets, silicone. Tell me which you want expanded.
A7: 6 | B7: S70P vs S90RP in your hands | C7: Counter tips (your most-saved format) | D7: 22–25s | E7: Save · Comment · Rewatch | F7: Untested (your site describes exactly this demo) | G7: "find the thermal barrier" is a small game viewers try to win. | H7: two corner samples on the counter, a pen, a camera looking straight down. | I7: Où est la barrette ? / فين كاينة قطعة العزل؟ | K7: S70P ou S90RP ? 👇 | L7: #coulissant #aluminium #menuiserie #fes #maroc | M7: a mini comparison table. | N7: S88RP vs S90RP (your FAQ covers it); S70R vs S70P ("jusqu'à 20% d'économies d'énergie" per your site). | O7: Uw and acoustic values depend on the glazing and configuration, so write "selon fiche technique" on screen. | P7: comments answering "lequel", saves.
A8: 7 | B8: Quiz: "Quel profil porte 400 kg ?" | C8: Counter tips (your most-saved format) | D8: 15s | E8: Comment · Rewatch | F8: Untested | H8: four close-ups on one background; a big countdown graphic. | I8: Lequel porte 400 kg ? / شمن بروفيل كيحمل 400 كيلو؟ | J8: end on the answer, then cut straight back to the four tiles so it loops and people rewatch to check. | K8: Ton avis ? 👇 | L8: #aluminium #coulissant #menuiserie #maroc #fes | M8: the full table: S70P 80 kg · S90RP 160 kg · S88RP 200–300 kg · S110P 400 kg. | N8: "Quel système pour 3,3 × 3,2 m ?" (S88: max 3300 × 3200 mm); "Quel vitrage max ?" (21 / 26 / 32 mm). | O8: keep the S125RP out of the options, because its limits come with a validation note on your site. Add "Valeurs max, voir fiche technique". | P8: a lot of comments, wrong answers included. Reply to those.
A9: 8 | B9: "Pourquoi deux devis sont différents" | C9: Counter tips (your most-saved format) | D9: 20s | E9: Save · Share | F9: Niche (price/devis captions: median 12K views, save rate 0.38%, n=30) | G9: it removes a frustration every menuisier has with suppliers. And it needs no prices. | I9: علاش جوج devis د البروفيلي مختلفين فالثمن؟ | K9: Les 4 choses qui changent le prix | L9: #aluminium #devis #menuiserie #fes #maroc | M9: Pinned comment (the save): a copy-paste WhatsApp template: Référence : … / Quantité (barres ou ml) : … / Finition : … / Ville : … | N9: "Barres ou mètres ?"; "Comment lire une référence STRUGAL"; "Compte pro : quand c'est utile". | O9: no prices unless you decide to publish them. | P9: saves above shares, and WhatsApp messages that follow your template.
A10: 9 | B10: "Il hésite ? Montre-lui chez lui" | C10: The 3D/AR tool | D10: 20–25s | E10: Share · Rewatch · Comment | F10: Untested (nobody in the sample shows this) | G10: the "magic" moment of a pergola appearing on a real terrace, and homeowners tag their menuisier. | H10: a real terrace in late-afternoon light. Two people: one holds the phone, the other films over the shoulder, so the viewer sees the screen and the real space. Test the link before filming (recent phone needed, and the tool must be working). | I10: Hook A (client): Avant de signer, il voit sa pergola chez lui Hook B (menuisier): Ton client hésite ? Montre-lui ça / الزبون كيتردد؟ خليه يشوف البيرغولا فالتيراس ديالو | K10: Voir sa pergola chez soi avant de signer 🤯 | L10: #pergola #pergolabioclimatique #maroc #fes #بيرغولا | M10: Réservé aux menuisiers partenaires. Écrivez-nous pour votre lien. | N10: Glass Line railing on a balcony; sliding bay S90RP, 3 leaves, 3,60 × 2,20 m; window S53RP+ tilt-and-turn (all taken from your site's examples). | O10: add "Outil de vente, pas un plan d'atelier. Teintes indicatives." (your site says so). The tool is for professional customers, so make the CTA for them. | P10: menuisiers asking for access, and homeowners tagging someone.
A11: 10 | B11: "Pergola configurée en 30 secondes" | C11: The 3D/AR tool | D11: 30s | E11: Rewatch · Share | F11: Untested | H11: a screen recording only. Add a timer overlay at the top. | I11: Hook A: Pergola configurée en 30 s ⏱️ / بيرغولا فـ 30 ثانية Hook B: Combien de temps pour faire un devis ? | J11: speed-ramp between steps, zoom into the buttons, a faint tick sound. Add a 3-second slow replay at the end, because people replay to see the steps. | K11: Un devis complet en 30 secondes | L11: #pergola #aluminium #devis #maroc #fes | M11: the steps as a list. | N11: railing in 20s; sliding bay in 25s. | O11: don't fake the speed. Film it in one real take. | P11: replays and shares from menuisiers. | Q11: A strong one: record the moment the tool warns when a leaf is too heavy for the system (your site says it does). A "fail" moment gets comments.
A12: 11 | B12: A menuisier and his client | C12: The 3D/AR tool | D12: 20–30s | E12: Share · Real | F12: Untested | G12: a customer's video is more credible than yours, and they'll share it to their own audience. | H12: recruit 3 customer workshops. Give each a one-page brief: 4 shots, text lines, their own logo and link. Get their written OK, and the client's OK for any face (or film hands only). | I12: كيفاش هاد النجار كيقنع الزبون قبل ما يوقع | K12: Montrer avant de vendre | L12: #menuisier #aluminium #maroc #fes #pergola | N12: a monthly "Menuisier du mois". | O12: keep it real. Film an actual meeting. If you re-enact it, write "reconstitution". Don't claim results (sales closed, etc.) you can't back. | P12: the workshops reposting it, and requests for links. | Q12: Instagram: use a Collab post so it appears on both accounts.
A13: 12 | B13: The window that disappears | C13: "One clever mechanism" | D13: 10–12s | E13: Rewatch · Share | F13: Niche (one surprising mechanism, under 20 seconds: 1.8M to 9M views for others) | H13: you need a real galandage S88RP, either a showroom demo or a customer's installation with permission. If you have neither, skip this idea until you do. A fixed tripod, a wide shot, a clean wall. | I13: Hook A: Où est la fenêtre ? / فين الشباك؟ Hook B: La fenêtre qui disparaît dans le mur | K13: La fenêtre qui disparaît 👀 | L13: #fenetre #coulissant #galandage #maroc #نجارة_الألمنيوم | M13: S88RP avec option galandage : vantail jusqu'à 200–300 kg, jusqu'à 3300 × 3200 mm (voir fiche). | N13: galandage vs classic sliding; "combien de place dans le mur ?" (verify the technical answer first). | O13: say "selon configuration" if the product is custom. | P13: completion and shares.
A14: 13 | B14: The thinnest frame (S86RP) | C14: "One clever mechanism" | D14: 8–12s | E14: Rewatch · Share | F14: Niche (same format as #12), built on your own spec | H14: a corner sample of the S86RP and a ruler; a bright window behind. | I14: 42 mm seulement / 42 ملم بس | K14: Le plus fin du catalogue | L14: #coulissant #aluminium #architecture #maroc #fes | N14: "Plus fin encore ? 25 mm" (the S140RP central mullion). | O14: do not compare 42 mm to the S90's 90 mm. The first is a central section and the second a frame width, so that would be misleading. Use the ruler and a finger. | P14: shares from architects and menuisiers.
A15: 14 | B15: "400 kg sur un seul vantail" | C15: "One clever mechanism" | D15: 17s | E15: Rewatch · Comment | F15: Untested | G15: a number people can picture. | I15: 400 kg = 8 sacs de ciment. Sur UN vantail. / 400 كيلو = 8 د السياك. فضلفة وحدة | K15: Un vantail de 400 kg 🤯 | L15: #coulissant #aluminium #maroc #fes #architecture | M15: S110P : 400 kg max/vantail, dimensions max 3200 × 3000 mm. | O15: this is the maximum allowed leaf weight, not a test result. Don't call it a certified test. Mind your back when lifting. | P15: comments asking about other systems, which feed the quiz (#7). | Q15: Version B (only if your technical lead and the supplier validate it): a load rig: Use a frame and sandbags, not glass, with protective gear and nobody beneath the load. Never exceed the limit.
A16: 15 | B16: Integrated handle, silent reveal | C16: Kitchens and dressings | D16: 7s | E16: Rewatch · Share | F16: Niche (kitchen captions: median ~30K views; @proalumad's 7-second silent reveal hit 8.3M) | G16: the biggest audience in Moroccan aluminium TikTok, and kitchen fabricators are your customers. | H16: a finished kitchen with an integrated-handle profile from your range (permission from the fabricator and the owner; no faces or address). Film at 120 fps for slow motion, with macro close-ups. | I16: the visual itself, plus 3 words. المقبض لي ما كيبانش | J16: silent or gentle ambient. | K16: المقبض لي ما كيبانش | L16: #cuisinealuminium #مطابخ_حديثة_المنيوم #fes #maroc | M16: Profil poignée intégrée disponible pour les menuisiers. Écrivez-nous. | N16: three finishes; the same kitchen with the lights on; tag the fabricator each time, because they will share it. | O16: make sure the profile really comes from you. | P16: menuisiers asking where to buy the profile.
A17: 16 | B17: One dressing, three finishes | C17: Kitchens and dressings | D17: 13s | E17: Comment · Rewatch | F17: Niche/Untested | H17: three identical door samples: bicolour, wood-effect and anodised (laqué is a fourth option on your site). | I17: أي تشطيب؟ 1 ولا 2 ولا 3؟ | K17: Ton choix ? | L17: #dressing #aluminium #maroc #fes #design | M17: Résultat demain 👀 | N17: Next episode (this is a two-parter): Vous avez voté : the winner revealed, as a reply video. A guaranteed second post. | P17: votes above 30 in the first day.
A18: 17 | B18: Skit: "un petit coulissant" | C18: Humour, trust and replies | D18: 15s, Darija, French subtitles | E18: Share · Comment | F18: Untested. Try 2–3 skits and keep it only if it earns shares. | H18: the counter, two staff, handheld close-up, a tape measure. One take, deadpan, with a half-second pause before each punchline. | K18: Tous les menuisiers connaissent 😅 | L18: #menuisier #aluminium #maroc #humour #fes | O18: keep it affectionate, never mocking a real customer. | P18: shares with "c'est exactement toi" comments. | Q18: Other skit angles: "Moins cher mais pareil"; the colour chosen on a screen vs the real one (your site notes screen colours are indicative).
A19: 18 | B19: "L'aluminium rouille ?" | C19: Humour, trust and replies | D19: 15–20s | E19: Share · Save | F19: Untested (your exterior page already has the facts) | I19: واش الألمنيوم كيصدا؟ | K19: Le mythe qui revient tout le temps | L19: #aluminium #menuiserie #maroc #fes #bricolage | O19: stay with claims your site makes. Don't add numbers for corrosion. | P19: comments from people who believed the myth. | Q19: Series: "3 mythes": (1) rouille, (2) "l'alu est froid" (the thermal break answers it), (3) another one from your FAQ.
A20: 19 | B20: "Touchez avant de commander" (Sefrou showroom) | C20: Humour, trust and replies | D20: 20–22s | E20: Local · Real | F20: Yours/Untested (your best videos are shop-floor footage) | K20: Le showroom STRUGAL de Sefrou | L20: #sefrou #strugal #aluminium #maroc #fes | M20: the Google Maps link and hours. | O20: your site says the two stores don't carry the same product families. The STRUGAL range is shown at Sefrou, so say that clearly. | P20: visits ("on m'a dit de venir voir").
A21: 20 | B21: Reply video to a menuisier's comment | C21: Humour, trust and replies | D21: 15–30s | E21: Comment · Local | F21: Niche (your comment counts are only 1–11) | H21: Process: pick one comment or DM. Use TikTok's "reply with video" so the question appears as a bubble. Add a question sticker in Instagram Stories and answer the best one as a Reel. | K21: Réponse à @… | L21: #aluminium #menuiserie #fes #maroc | O21: answer only what you're sure of; don't leave a question unanswered if you promised. | P21: the person you replied to comments back, and others add questions. | Q21: Five answers already on your site (start with these): 1. Faut-il un compte pro pour une première commande ? No. Describe the need and you get a quote. 2. Barres ou mètres ? Bars. Quote in linear metres or number of bars; the length decides the transport. 3. S90RP ou S88RP ? S90RP is for insulation and finishes (leaf up to 160 kg). S88RP is more versatile, with lift-and-slide and galandage (200–300 kg). 4. Quel système pour une grande baie ou une piscine ? The S125RP lift-and-slide (limits to be validated per configuration). 5. Quelle différence entre Fès et Sefrou ? The STRUGAL range is shown at Sefrou; same hours and conditions.
A23: How each brief is organised (from the playbook)
B24: Each brief has the same parts: why it can travel, setup, shot-by-shot, hook options (test A against B in different weeks), sound and edit, caption, pinned comment, next episodes, watch-outs and the win signal.

Sheet Shot Lists
A1: # | B1: Idea | C1: Table / version | D1: Time | E1: Shot / beat / step / line | F1: On-screen text / sound / notes
A2: 1 | B2: "Ce camion part pour [ville]" | C2: Shot by shot (12–15s) | D2: 0.0–1.5 | E2: The loaded truck from behind, bars sticking out. | F2: Hook text. Ambient engine.
A3: 1 | B3: "Ce camion part pour [ville]" | C3: Shot by shot (12–15s) | D3: 1.5–5 | E3: A hand tightens the strap or slaps the tailgate. | F3: —
A4: 1 | B4: "Ce camion part pour [ville]" | C4: Shot by shot (12–15s) | D4: 5–10 | E4: The truck pulls away. The camera does not move. | F4: —
A5: 1 | B5: "Ce camion part pour [ville]" | C5: Shot by shot (12–15s) | D5: 10–13 | E5: Destination reveal. | F5: "📍 Meknès"
A6: 1 | B6: "Ce camion part pour [ville]" | C6: Shot by shot (12–15s) | D6: 13–15 | E6: Empty street (the loop point). | F6: Phone number, small.
A7: 2 | B7: "Même profil, 6 teintes" | C7: Shot by shot (18–21s) | D7: 0–1.5 | E7: Close-up of black profiles. | F7: Hook text.
A8: 2 | B8: "Même profil, 6 teintes" | C8: Shot by shot (18–21s) | D8: 1.5–14 | E8: Walk past each colour, a hand touching each stack. Label pops on every colour, one per ~2s. | F8: noir · gris naturel · fauxbois · blanc 9010 · gris platine · gris givré
A9: 2 | B9: "Même profil, 6 teintes" | C9: Shot by shot (18–21s) | D9: 14–19 | E9: The same section in three colours side by side. | F9: "Ton choix ? 1 / 2 / 3"
A10: 2 | B10: "Même profil, 6 teintes" | C10: Shot by shot (18–21s) | D10: 19–21 | E10: Back to the black stack (the loop). | F10: —
A11: 3 | B11: "Arrivage" | C11: Shot by shot (8–12s) | D11: 0–1 | E11: Macro: a strap is cut. | F11: "Nouvel arrivage" · the snap
A12: 3 | B12: "Arrivage" | C12: Shot by shot (8–12s) | D12: 1–5 | E12: The bundle opens and profiles fan out. A hand pulls one bar. | F12: The glide sound
A13: 3 | B13: "Arrivage" | C13: Shot by shot (8–12s) | D13: 5–9 | E13: Wide: stacks on the shelf. | F13: —
... A46: 9 | B46: "Il hésite ? Montre-lui chez lui" | C46: Shot by shot (20–25s) | D46: 24–25 | E46: End card. | F46: Menuisiers : demandez votre lien
A47: 10 | B47: "Pergola configurée en 30 secondes" | C47: Shot by shot (30s) | D47: 0–2 | E47: Hook + timer starts at 0:00
A48: 10 | B48: "Pergola configurée en 30 secondes" | C48: Shot by shot (30s) | D48: 2–5 | E48: Choose the product
A49: 10 | B49: "Pergola configurée en 30 secondes" | C49: Shot by shot (30s) | D49: 5–9 | E49: Enter size (4,20 × 6,00 m)
A50: 10 | B50: "Pergola configurée en 30 secondes" | C50: Shot by shot (30s) | D50: 9–12 | E50: Pick the colour
A51: 10 | B51: "Pergola configurée en 30 secondes" | C51: Shot by shot (30s) | D51: 12–15 | E51: Blades
A52: 10 | B52: "Pergola configurée en 30 secondes" | C52: Shot by shot (30s) | D52: 15–18 | E52: LED
A53: 10 | B53: "Pergola configurée en 30 secondes" | C53: Shot by shot (30s) | D53: 18–23 | E53: View in AR
A54: 10 | B54: "Pergola configurée en 30 secondes" | C54: Shot by shot (30s) | D54: 23–27 | E54: Send
A55: 10 | B55: "Pergola configurée en 30 secondes" | C55: Shot by shot (30s) | D55: 27–30 | E55: Timer stops at 0:29; the WhatsApp message shows. Your site's example: 4,20 × 6,00 m, RAL 7016, 28 lames, LED
A56: 11 | B56: A menuisier and his client | C56: Shot by shot (20–30s) | D56: 0–2 | E56: The client looks at a brochure. | F56: Quand le client hésite…
A57: 11 | B57: A menuisier and his client | C57: Shot by shot (20–30s) | D57: 2–8 | E57: The menuisier hands him a phone. | F57: —
A58: 11 | B58: A menuisier and his client | C58: Shot by shot (20–30s) | D58: 8–15 | E58: The client sees the product at real size in his home. | F58: —
A59: 11 | B59: A menuisier and his client | C59: Shot by shot (20–30s) | D59: 15–22 | E59: The reaction. | F59: —
A60: 11 | B60: A menuisier and his client | C60: Shot by shot (20–30s) | D60: 22–28 | E60: The WhatsApp request arrives on the menuisier's phone. | F60: Menuisier : demandez le même outil
A61: 12 | B61: The window that disappears | C61: Shot by shot (10–12s). Start on the hidden state so the video loops | D61: 0–2 | E61: An empty wall. | F61: Où est la fenêtre ?
A62: 12 | B62: The window that disappears | C62: Shot by shot (10–12s). Start on the hidden state so the video loops | D62: 2–7 | E62: The leaf slides out, slowly and smoothly. | F62: The glide sound
A63: 12 | B63: The window that disappears | C63: Shot by shot (10–12s). Start on the hidden state so the video loops | D63: 7–10 | E63: It slides back into the wall. | F63: —
A64: 12 | B64: The window that disappears | C64: Shot by shot (10–12s). Start on the hidden state so the video loops | D64: 10–12 | E64: Hidden again (= the first frame). | F64: —
A65: 13 | B65: The thinnest frame (S86RP) | C65: Shot by shot (8–12s) | D65: 0–2 | E65: A ruler on the central section reads 42 mm. | F65: 42 mm
A66: 13 | B66: The thinnest frame (S86RP) | C66: Shot by shot (8–12s) | D66: 2–6 | E66: The leaf slides, and the thin line stands out against the light. | F66: —
A67: 13 | B67: The thinnest frame (S86RP) | C67: Shot by shot (8–12s) | D67: 6–10 | E67: Next to a finger, for scale. | F67: Le plus fin
... A72: 14 | B72: "400 kg sur un seul vantail" | C72: Version A (recommended, safe): the equivalence | D72: 14–17 | E72: End. | F72: Valeurs max, voir fiche technique
A73: 15 | B73: Integrated handle, silent reveal | C73: Shot by shot (7s) | D73: 0–1.5 | E73: A finger runs along the handle groove (3-word text: Poignée intégrée).
A74: 15 | B74: Integrated handle, silent reveal | C74: Shot by shot (7s) | D74: 1.5–3.5 | E74: The door opens to a lit interior.
A75: 15 | B75: Integrated handle, silent reveal | C75: Shot by shot (7s) | D75: 3.5–5.5 | E75: A second door in another finish.
A76: 15 | B76: Integrated handle, silent reveal | C76: Shot by shot (7s) | D76: 5.5–7 | E76: The door closes (the loop).
A77: 16 | B77: One dressing, three finishes | C77: Shot by shot (13s) | D77: 0–2 | E77: Three tiles. | F77: Bicolore, effet bois ou anodisé ?
A78: 16 | B78: One dressing, three finishes | C78: Shot by shot (13s) | D78: 2–10 | E78: Each finish for ~2.5s in close-up, light moving across. | F78: 1 · 2 · 3
A79: 16 | B79: One dressing, three finishes | C79: Shot by shot (13s) | D79: 10–13 | E79: Vote card. | F79: Vote 1 / 2 / 3 👇
A80: 17 | B80: Skit: "un petit coulissant" | C80: Script (15s, Darija, French subtitles) | D80: 0–3 | E80: Client: بغيت غير coulissant صغير (text: Le client : « un petit coulissant »)
A81: 17 | B81: Skit: "un petit coulissant" | C81: Script (15s, Darija, French subtitles) | D81: 3–6 | E81: Menuisier: شحال؟
A82: 17 | B82: Skit: "un petit coulissant" | C82: Script (15s, Darija, French subtitles) | D82: 6–9 | E82: Client opens his arms: غير 4 متر…
A83: 17 | B83: Skit: "un petit coulissant" | C83: Script (15s, Darija, French subtitles) | D83: 9–12 | E83: Menuisier measures, looks at the camera. A beat.
A84: 17 | B84: Skit: "un petit coulissant" | C84: Script (15s, Darija, French subtitles) | D84: 12–15 | E84: Menuisier: هادي ماشي نافذة… هادي S110P. (text: Le client qui dit « petit »)
A85: 18 | B85: "L'aluminium rouille ?" | C85: Script (15–20s) | D85: 0–2 | E85: L'aluminium rouille ? (a sample in hand)
A86: 18 | B86: "L'aluminium rouille ?" | C86: Script (15–20s) | D86: 2–4 | E86: Non.
A87: 18 | B87: "L'aluminium rouille ?" | C87: Script (15–20s) | D87: 4–9 | E87: It forms a thin protective oxide layer.
A88: 18 | B88: "L'aluminium rouille ?" | C88: Script (15–20s) | D88: 9–14 | E88: Surface treatment (thermolaquage or anodisation) protects it over time.
A89: 18 | B89: "L'aluminium rouille ?" | C89: Script (15–20s) | D89: 14–18 | E89: One caveat: aluminium conducts heat, which is why a thermal break matters on windows.
A90: 18 | B90: "L'aluminium rouille ?" | C90: Script (15–20s) | D90: 18–20 | E90: Partie 2 : c'est quoi la rupture de pont thermique ?
A91: 19 | B91: "Touchez avant de commander" (Sefrou showroom) | C91: Shot by shot (20–22s) | D91: 0–2 | E91: The showroom door opens. | F91: Touche avant de commander / جرّب بيدك قبل ما تطلب
A92: 19 | B92: "Touchez avant de commander" (Sefrou showroom) | C92: Shot by shot (20–22s) | D92: 2–6 | E92: A hand slides a leaf on a display system. | F92: —
A93: 19 | B93: "Touchez avant de commander" (Sefrou showroom) | C93: Shot by shot (20–22s) | D93: 6–11 | E93: Two profiles compared in hand. | F93: —
A94: 19 | B94: "Touchez avant de commander" (Sefrou showroom) | C94: Shot by shot (20–22s) | D94: 11–16 | E94: Colour swatches. | F94: —
A95: 19 | B95: "Touchez avant de commander" (Sefrou showroom) | C95: Shot by shot (20–22s) | D95: 16–20 | E95: Outside. | F95: Route d'El Menzel, Sefrou · Lun–Sam 9h–19h
A96: 19 | B96: "Touchez avant de commander" (Sefrou showroom) | C96: Shot by shot (20–22s) | D96: 20–22 | E96: Walk out. | F96: —
A97: 20 | B97: Reply video to a menuisier's comment | C97: Shot by shot (15–30s) | D97: 0–2 | E97: The comment bubble.
A98: 20 | B98: Reply video to a menuisier's comment | C98: Shot by shot (15–30s) | D98: 2–20 | E98: Your answer at the counter with one prop.
A99: 20 | B99: Reply video to a menuisier's comment | C99: Shot by shot (15–30s) | D99: 20–25 | E99: Une autre question ? Commente 👇

Sheet Strategy Ideas (25)
A1: # | B1: Pillar | C1: Idea | D1: Note | E1: Details
A2: 1 | B2: A. Proven for you: stock, trucks, colours (start here) | C2: "Ce camion part pour …" | D2: (the 14.7K format) | E2: Film: a loaded truck leaving, with the destination city as on-screen text. 10–16s, no talking, phone number overlaid. Hook text: "Ce camion part pour Meknès ce matin" / هاد الكاميو غادي لمكناس دابا Make it a weekly series with a new city every time. Each video targets a local audience (#meknes, #taza, #oujda) and shows the "delivery across Morocco" promise.
A3: 2 | B3: A. Proven for you: stock, trucks, colours (start here) | C3: "Toutes les teintes en stock" | D3: (the 8K format, upgraded) | E3: Film: a smooth walk down the aisle, with each colour appearing as an on-screen label (noir, gris naturel, fauxbois, blanc 9010, gris platine, gris givré). 15–22s. Upgrade: end with the same profile in three colours side by side. Hook: "Même profil, 6 teintes. Laquelle choisit ton client ?" / نفس البروفيل، 6 ألوان. أي واحد غادي يختار الكليان؟
A4: 3 | B4: A. Proven for you: stock, trucks, colours (start here) | C4: "Arrivage" | E4: Film: a delivery from STRUGAL being unloaded or a fresh bundle being opened. Satisfying, no talking. 8–12s. Hook: "Nouvel arrivage S88RP" / وصلنا S88RP
A5: 4 | B5: B. Proven for you: the counter tip series (most saves, shares and comments) | C5: "Le truc que tout menuisier devrait savoir" | E5: Film: the presenter at the counter holds one profile and one part, shows one fix, under 30s. Same camera, same set, every time, so the audience learns to recognise it. Hook: "Une astuce de 20 secondes qui évite les retours de chantier" / حيلة د 20 ثانية كتحميك من المشاكل فالورش Topics that fit your range (verify each): dust protection on the flat lock (follow-up to your best tip), where the thermal break sits, glazing thickness limits per system, wheel adjustment on a lift-and-slide, drainage at the bottom rail. Ask a question at the end ("Et toi, tu fais comment ?") to lift comments. Your comment counts are 1–11.
A6: 5 | B6: B. Proven for you: the counter tip series (most saves, shares and comments) | C6: "Comparer en main": S70P vs S90RP | E6: Film: hold two profiles side by side, point at the thermal barrier. Your site says "comparer en main… apprend en deux minutes ce qu'un catalogue met une heure à expliquer", so film exactly that. 20–30s. Hook: "Où est la rupture de pont thermique ?" / فين كاينة قطعة العزل الحراري؟
A7: 6 | B7: B. Proven for you: the counter tip series (most saves, shares and comments) | C7: Quiz: "Combien de kg ?" | E7: Film: a profile close-up, text "S70P, S90RP, S88RP, S110P: lequel porte 400 kg par vantail ?" Reveal at the end. Your site lists: S70P 80 kg, S86RP 140 kg, S90P/S90RP 160 kg, S88 200–300 kg, S110P 400 kg. Comment-bait with a built-in answer. Pin a comment with the full list. Hook: "Quel profil porte le plus lourd vantail ?" / شمن بروفيل كيحمل أتقل ضلفة؟
A8: 7 | B8: C. Your unique asset: the 3D/AR tool (nobody else shows this) | C8: "Il hésite ? Montre-lui chez lui" | E8: Screen-record on a phone: someone points the camera at a terrace, a pergola appears at 4.20 × 6.00 m, rotates, changes colour. 15–25s. A before/after split with the empty terrace works well. Hook: "Ton client n'arrive pas à se projeter ? Voilà la solution" / الكليان ما قادرش يتخيل؟ شوف هاد الحل CTA: "Menuisiers : demandez votre lien" (it's reserved for professional clients, which creates exclusivity).
A9: 8 | B9: C. Your unique asset: the 3D/AR tool (nobody else shows this) | C9: Speed-run: "Une pergola configurée en 30 secondes" | E9: Screen recording with a visible timer. Colour, size, blades, LED. End with the WhatsApp message arriving, which shows the full quote request landing.
A10: 9 | B10: C. Your unique asset: the 3D/AR tool (nobody else shows this) | C10: Menuisier case studies | E10: Invite 3 workshop customers to use their personal link and film themselves with a client. Post it, tag them. They'll repost to their own audience, which is also marketing for you.
A11: 10 | B11: D. The viral "one clever mechanism" format, on your systems | C11: "Disparaît dans le mur" | D11: (S88RP with galandage) | E11: 8–12s: the sliding leaf slides fully into the wall. No talking. This is the format that got 1.8M to 9M for others. Hook: "La fenêtre qui disparaît" / الشباك لي كيتخبى فالحيط
A12: 11 | B12: D. The viral "one clever mechanism" format, on your systems | C12: "Le plus fin du catalogue" | D12: (S86RP, 42 mm at the centre) | E12: Close-up of the thin sightline with a bright view behind. 8–10s.
A13: 12 | B13: D. The viral "one clever mechanism" format, on your systems | C13: "400 kg… pour de vrai ?" | D13: (S110P) | E13: Safe, supervised weight test on a mock-up. 15–20s. Check the system sheet and use proper safety. Spectacle plus spec.
A14: 13 | B14: D. The viral "one clever mechanism" format, on your systems | C14: "Meneau de 25 mm" | D14: (S140RP Infinity) | E14: The lift-and-slide on a big opening, the slim centre post. 10s.
A15: 14 | B15: E. Kitchens and dressings (the biggest audience on Moroccan TikTok) | C15: "Poignée intégrée" silent reveal | E15: 5–10s of a kitchen door opening with the integrated-handle profile. Copy @proalumad's rhythm: no talking, Arabic category hashtags. It's your agencement range, and kitchen fabricators are your customers, so the people who watch are also the people who buy. Tags: #مطابخ_حديثة_المنيوم #cuisinealuminium + city.
A16: 15 | B16: E. Kitchens and dressings (the biggest audience on Moroccan TikTok) | C16: Dressing on request | E16: One profile, three finishes (bicolour, wood effect, anodised). 10–15s.
A17: 16 | B17: F. Education that gets saved (also for Instagram carousels) | C17: Carousel: "Coulissant ou battant ? Le tableau en 6 lignes" | D17: (from your guide)
A18: 17 | B18: F. Education that gets saved (also for Instagram carousels) | C18: Carousel: "La rupture de pont thermique en 5 slides" | D18: with a cross-section showing the barrier
A19: 18 | B19: F. Education that gets saved (also for Instagram carousels) | C19: Carousel: "Les 11 coulissants STRUGAL en une image" | D19: , a cheat-sheet people screenshot. Poids max, vitrage, Uw, usage.
A20: 19 | B20: F. Education that gets saved (also for Instagram carousels) | C20: Carousel: "Comment commander en 4 étapes" | D20: (describe, quote, validate, pick up or delivery)
A21: 20 | B21: F. Education that gets saved (also for Instagram carousels) | C21: Myth-busting video/carousel | D21: "L'aluminium rouille ?" (no), "Pourquoi une rupture de pont thermique ?", "Barre ou mètre ?" All from your FAQ and exterior page.
A22: 21 | B22: G. Price and ordering (the format with the best save rate) | C22: "Ce qui fait varier le prix d'un profilé" | E22: Your FAQ names four things: reference, quantity, finish, destination. 4 slides or a 20s video, one factor per beat. Hook: "Pourquoi deux devis de profilés sont si différents" / علاش جوج د الأثمنة د البروفيلي مختلفين؟ Whether to publish actual prices is your call. The fallback above needs none.
A23: 22 | B23: H. Relatable and local (untested here; try 3–4 and keep what works) | C23: Menuisier skit | D23: "Le client veut un 'petit coulissant', il mesure 4 mètres." Darija humour, 15s.
A24: 23 | B24: H. Relatable and local (untested here; try 3–4 and keep what works) | C24: "Retrait en 5 minutes" | D24: a workshop owner arrives, loads up, leaves. Shows your speed.
A25: 24 | B25: H. Relatable and local (untested here; try 3–4 and keep what works) | C25: "Un matin à Sefrou" | D25: the showroom opening, light through the profiles. Soft brand content, but filmed rather than animated.
A26: 25 | B26: H. Relatable and local (untested here; try 3–4 and keep what works) | C26: Reply videos | D26: answer a comment on camera. They cost little and they signal activity.
A28: Notes from the report
B29: Introduction | C29: Ranked by how directly your own data or the niche data supports them. Hooks are drafts in French and Darija; adapt them to how you actually speak. Technical claims should be double-checked against STRUGAL's sheets before you film. Spec numbers below come from your own site.
B30: F. Education that gets saved (also for Instagram carousels) | C30: Instagram is not data-backed here (see section 0), but the same content works as saveable carousels, and your site already has the research:

Sheet Calendar
A1: Six-week posting calendar (starts Monday 26 Oct 2026)
A2: Four posts a week; one shoot session can produce 3–4 videos (table below). Pick a status for each row; idea name, pillar and shoot session come from the '20 Ideas' sheet.
A3: Posted: | B3: =COUNTIF(H5:H28,"Posted") -> 0 | C3: of | D3: =COUNTA(D5:D28) -> 24
A4: Week | B4: Date | C4: Day | D4: Idea # | E4: Idea | F4: Pillar | G4: Shoot session | H4: Status | I4: Posted URL | J4: Notes
A5: 1 | B5: 46321 | C5: =TEXT(B5,"dddd") -> Monday | D5: 1 | E5: =IFERROR(INDEX('20 Ideas'!$C$2:$C$21,MATCH(D5,'20 Ideas'!$A$2:$A$21,0)),"") -> "Ce camion part pour [ville]" | F5: =IFERROR(INDEX('20 Ideas'!$B$2:$B$21,MATCH(D5,'20 Ideas'!$A$2:$A$21,0)),"") -> Stock, trucks, colours | G5: =IFERROR(INDEX('20 Ideas'!$M$2:$M$21,MATCH(D5,'20 Ideas'!$A$2:$A$21,0)),"") -> Stock & trucks | H5: Planned
A6: 1 | B6: 46323 | C6: =TEXT(B6,"dddd") -> Wednesday | D6: 5 | E6: =IFERROR(INDEX('20 Ideas'!$C$2:$C$21,MATCH(D6,'20 Ideas'!$A$2:$A$21,0)),"") -> "L'astuce du comptoir" (series) | F6: =IFERROR(INDEX('20 Ideas'!$B$2:$B$21,MATCH(D6,'20 Ideas'!$A$2:$A$21,0)),"") -> Counter tips (your most-saved format) | G6: =IFERROR(INDEX('20 Ideas'!$M$2:$M$21,MATCH(D6,'20 Ideas'!$A$2:$A$21,0)),"") -> Counter | H6: Planned
A7: 1 | B7: 46325 | C7: =TEXT(B7,"dddd") -> Friday | D7: 2 | E7: =IFERROR(INDEX('20 Ideas'!$C$2:$C$21,MATCH(D7,'20 Ideas'!$A$2:$A$21,0)),"") -> "Même profil, 6 teintes" | F7: =IFERROR(INDEX('20 Ideas'!$B$2:$B$21,MATCH(D7,'20 Ideas'!$A$2:$A$21,0)),"") -> Stock, trucks, colours | G7: =IFERROR(INDEX('20 Ideas'!$M$2:$M$21,MATCH(D7,'20 Ideas'!$A$2:$A$21,0)),"") -> Stock & trucks | H7: Planned
A8: 1 | B8: 46327 | C8: =TEXT(B8,"dddd") -> Sunday | D8: 9 | E8: =IFERROR(INDEX('20 Ideas'!$C$2:$C$21,MATCH(D8,'20 Ideas'!$A$2:$A$21,0)),"") -> "Il hésite ? Montre-lui chez lui" | F8: =IFERROR(INDEX('20 Ideas'!$B$2:$B$21,MATCH(D8,'20 Ideas'!$A$2:$A$21,0)),"") -> The 3D/AR tool | G8: =IFERROR(INDEX('20 Ideas'!$M$2:$M$21,MATCH(D8,'20 Ideas'!$A$2:$A$21,0)),"") -> Screen recording | H8: Planned
A9: 2 | B9: 46328 | C9: =TEXT(B9,"dddd") -> Monday | D9: 1 | E9: =IFERROR(INDEX('20 Ideas'!$C$2:$C$21,MATCH(D9,'20 Ideas'!$A$2:$A$21,0)),"") -> "Ce camion part pour [ville]" | F9: =IFERROR(INDEX('20 Ideas'!$B$2:$B$21,MATCH(D9,'20 Ideas'!$A$2:$A$21,0)),"") -> Stock, trucks, colours | G9: =IFERROR(INDEX('20 Ideas'!$M$2:$M$21,MATCH(D9,'20 Ideas'!$A$2:$A$21,0)),"") -> Stock & trucks | H9: Planned | J9: New city
A10: 2 | B10: 46330 | C10: =TEXT(B10,"dddd") -> Wednesday | D10: 6 | E10: =IFERROR(INDEX('20 Ideas'!$C$2:$C$21,MATCH(D10,'20 Ideas'!$A$2:$A$21,0)),"") -> S70P vs S90RP in your hands | F10: =IFERROR(INDEX('20 Ideas'!$B$2:$B$21,MATCH(D10,'20 Ideas'!$A$2:$A$21,0)),"") -> Counter tips (your most-saved format) | G10: =IFERROR(INDEX('20 Ideas'!$M$2:$M$21,MATCH(D10,'20 Ideas'!$A$2:$A$21,0)),"") -> Counter | H10: Planned
A11: 2 | B11: 46332 | C11: =TEXT(B11,"dddd") -> Friday | D11: 12 | E11: =IFERROR(INDEX('20 Ideas'!$C$2:$C$21,MATCH(D11,'20 Ideas'!$A$2:$A$21,0)),"") -> The window that disappears | F11: =IFERROR(INDEX('20 Ideas'!$B$2:$B$21,MATCH(D11,'20 Ideas'!$A$2:$A$21,0)),"") -> "One clever mechanism" | G11: =IFERROR(INDEX('20 Ideas'!$M$2:$M$21,MATCH(D11,'20 Ideas'!$A$2:$A$21,0)),"") -> Stock & trucks | H11: Planned | J11: Needs a galandage sample or a customer installation. Swap in #4 if you have neither.
A12: 2 | B12: 46334 | C12: =TEXT(B12,"dddd") -> Sunday | D12: 15 | E12: =IFERROR(INDEX('20 Ideas'!$C$2:$C$21,MATCH(D12,'20 Ideas'!$A$2:$A$21,0)),"") -> Integrated handle, silent reveal | F12: =IFERROR(INDEX('20 Ideas'!$B$2:$B$21,MATCH(D12,'20 Ideas'!$A$2:$A$21,0)),"") -> Kitchens and dressings | G12: =IFERROR(INDEX('20 Ideas'!$M$2:$M$21,MATCH(D12,'20 Ideas'!$A$2:$A$21,0)),"") -> Kitchen / dressing | H12: Planned
A13: 3 | B13: 46335 | C13: =TEXT(B13,"dddd") -> Monday | D13: 7 | E13: =IFERROR(INDEX('20 Ideas'!$C$2:$C$21,MATCH(D13,'20 Ideas'!$A$2:$A$21,0)),"") -> Quiz: "Quel profil porte 400 kg ?" | F13: =IFERROR(INDEX('20 Ideas'!$B$2:$B$21,MATCH(D13,'20 Ideas'!$A$2:$A$21,0)),"") -> Counter tips (your most-saved format) | G13: =IFERROR(INDEX('20 Ideas'!$M$2:$M$21,MATCH(D13,'20 Ideas'!$A$2:$A$21,0)),"") -> Counter | H13: Planned
A14: 3 | B14: 46337 | C14: =TEXT(B14,"dddd") -> Wednesday | D14: 5 | E14: =IFERROR(INDEX('20 Ideas'!$C$2:$C$21,MATCH(D14,'20 Ideas'!$A$2:$A$21,0)),"") -> "L'astuce du comptoir" (series) | F14: =IFERROR(INDEX('20 Ideas'!$B$2:$B$21,MATCH(D14,'20 Ideas'!$A$2:$A$21,0)),"") -> Counter tips (your most-saved format) | G14: =IFERROR(INDEX('20 Ideas'!$M$2:$M$21,MATCH(D14,'20 Ideas'!$A$2:$A$21,0)),"") -> Counter | H14: Planned | J14: Tip #2
A15: 3 | B15: 46339 | C15: =TEXT(B15,"dddd") -> Friday | D15: 10 | E15: =IFERROR(INDEX('20 Ideas'!$C$2:$C$21,MATCH(D15,'20 Ideas'!$A$2:$A$21,0)),"") -> "Pergola configurée en 30 secondes" | F15: =IFERROR(INDEX('20 Ideas'!$B$2:$B$21,MATCH(D15,'20 Ideas'!$A$2:$A$21,0)),"") -> The 3D/AR tool | G15: =IFERROR(INDEX('20 Ideas'!$M$2:$M$21,MATCH(D15,'20 Ideas'!$A$2:$A$21,0)),"") -> Screen recording | H15: Planned
A16: 3 | B16: 46341 | C16: =TEXT(B16,"dddd") -> Sunday | D16: 3 | E16: =IFERROR(INDEX('20 Ideas'!$C$2:$C$21,MATCH(D16,'20 Ideas'!$A$2:$A$21,0)),"") -> "Arrivage" | F16: =IFERROR(INDEX('20 Ideas'!$B$2:$B$21,MATCH(D16,'20 Ideas'!$A$2:$A$21,0)),"") -> Stock, trucks, colours | G16: =IFERROR(INDEX('20 Ideas'!$M$2:$M$21,MATCH(D16,'20 Ideas'!$A$2:$A$21,0)),"") -> Stock & trucks | H16: Planned
A17: 4 | B17: 46342 | C17: =TEXT(B17,"dddd") -> Monday | D17: 1 | E17: =IFERROR(INDEX('20 Ideas'!$C$2:$C$21,MATCH(D17,'20 Ideas'!$A$2:$A$21,0)),"") -> "Ce camion part pour [ville]" | F17: =IFERROR(INDEX('20 Ideas'!$B$2:$B$21,MATCH(D17,'20 Ideas'!$A$2:$A$21,0)),"") -> Stock, trucks, colours | G17: =IFERROR(INDEX('20 Ideas'!$M$2:$M$21,MATCH(D17,'20 Ideas'!$A$2:$A$21,0)),"") -> Stock & trucks | H17: Planned | J17: New city
A18: 4 | B18: 46344 | C18: =TEXT(B18,"dddd") -> Wednesday | D18: 8 | E18: =IFERROR(INDEX('20 Ideas'!$C$2:$C$21,MATCH(D18,'20 Ideas'!$A$2:$A$21,0)),"") -> "Pourquoi deux devis sont différents" | F18: =IFERROR(INDEX('20 Ideas'!$B$2:$B$21,MATCH(D18,'20 Ideas'!$A$2:$A$21,0)),"") -> Counter tips (your most-saved format) | G18: =IFERROR(INDEX('20 Ideas'!$M$2:$M$21,MATCH(D18,'20 Ideas'!$A$2:$A$21,0)),"") -> Counter | H18: Planned
A19: 4 | B19: 46346 | C19: =TEXT(B19,"dddd") -> Friday | D19: 13 | E19: =IFERROR(INDEX('20 Ideas'!$C$2:$C$21,MATCH(D19,'20 Ideas'!$A$2:$A$21,0)),"") -> The thinnest frame (S86RP) | F19: =IFERROR(INDEX('20 Ideas'!$B$2:$B$21,MATCH(D19,'20 Ideas'!$A$2:$A$21,0)),"") -> "One clever mechanism" | G19: =IFERROR(INDEX('20 Ideas'!$M$2:$M$21,MATCH(D19,'20 Ideas'!$A$2:$A$21,0)),"") -> Stock & trucks | H19: Planned
A20: 4 | B20: 46348 | C20: =TEXT(B20,"dddd") -> Sunday | D20: 20 | E20: =IFERROR(INDEX('20 Ideas'!$C$2:$C$21,MATCH(D20,'20 Ideas'!$A$2:$A$21,0)),"") -> Reply video to a menuisier's comment | F20: =IFERROR(INDEX('20 Ideas'!$B$2:$B$21,MATCH(D20,'20 Ideas'!$A$2:$A$21,0)),"") -> Humour, trust and replies | G20: =IFERROR(INDEX('20 Ideas'!$M$2:$M$21,MATCH(D20,'20 Ideas'!$A$2:$A$21,0)),"") -> Counter | H20: Planned
A21: 5 | B21: 46349 | C21: =TEXT(B21,"dddd") -> Monday | D21: 11 | E21: =IFERROR(INDEX('20 Ideas'!$C$2:$C$21,MATCH(D21,'20 Ideas'!$A$2:$A$21,0)),"") -> A menuisier and his client | F21: =IFERROR(INDEX('20 Ideas'!$B$2:$B$21,MATCH(D21,'20 Ideas'!$A$2:$A$21,0)),"") -> The 3D/AR tool | G21: =IFERROR(INDEX('20 Ideas'!$M$2:$M$21,MATCH(D21,'20 Ideas'!$A$2:$A$21,0)),"") -> Ask a favour (3 customer workshops) | H21: Planned | J21: Needs 3 customer workshops and written permission
A22: 5 | B22: 46351 | C22: =TEXT(B22,"dddd") -> Wednesday | D22: 5 | E22: =IFERROR(INDEX('20 Ideas'!$C$2:$C$21,MATCH(D22,'20 Ideas'!$A$2:$A$21,0)),"") -> "L'astuce du comptoir" (series) | F22: =IFERROR(INDEX('20 Ideas'!$B$2:$B$21,MATCH(D22,'20 Ideas'!$A$2:$A$21,0)),"") -> Counter tips (your most-saved format) | G22: =IFERROR(INDEX('20 Ideas'!$M$2:$M$21,MATCH(D22,'20 Ideas'!$A$2:$A$21,0)),"") -> Counter | H22: Planned | J22: Tip #3
A23: 5 | B23: 46353 | C23: =TEXT(B23,"dddd") -> Friday | D23: 19 | E23: =IFERROR(INDEX('20 Ideas'!$C$2:$C$21,MATCH(D23,'20 Ideas'!$A$2:$A$21,0)),"") -> "Touchez avant de commander" (Sefrou showroom) | F23: =IFERROR(INDEX('20 Ideas'!$B$2:$B$21,MATCH(D23,'20 Ideas'!$A$2:$A$21,0)),"") -> Humour, trust and replies | G23: =IFERROR(INDEX('20 Ideas'!$M$2:$M$21,MATCH(D23,'20 Ideas'!$A$2:$A$21,0)),"") -> Counter | H23: Planned
A24: 5 | B24: 46355 | C24: =TEXT(B24,"dddd") -> Sunday | D24: 16 | E24: =IFERROR(INDEX('20 Ideas'!$C$2:$C$21,MATCH(D24,'20 Ideas'!$A$2:$A$21,0)),"") -> One dressing, three finishes | F24: =IFERROR(INDEX('20 Ideas'!$B$2:$B$21,MATCH(D24,'20 Ideas'!$A$2:$A$21,0)),"") -> Kitchens and dressings | G24: =IFERROR(INDEX('20 Ideas'!$M$2:$M$21,MATCH(D24,'20 Ideas'!$A$2:$A$21,0)),"") -> Kitchen / dressing | H24: Planned | J24: Results video the next day
A25: 6 | B25: 46356 | C25: =TEXT(B25,"dddd") -> Monday | D25: 1 | E25: =IFERROR(INDEX('20 Ideas'!$C$2:$C$21,MATCH(D25,'20 Ideas'!$A$2:$A$21,0)),"") -> "Ce camion part pour [ville]" | F25: =IFERROR(INDEX('20 Ideas'!$B$2:$B$21,MATCH(D25,'20 Ideas'!$A$2:$A$21,0)),"") -> Stock, trucks, colours | G25: =IFERROR(INDEX('20 Ideas'!$M$2:$M$21,MATCH(D25,'20 Ideas'!$A$2:$A$21,0)),"") -> Stock & trucks | H25: Planned | J25: New city
A26: 6 | B26: 46358 | C26: =TEXT(B26,"dddd") -> Wednesday | D26: 18 | E26: =IFERROR(INDEX('20 Ideas'!$C$2:$C$21,MATCH(D26,'20 Ideas'!$A$2:$A$21,0)),"") -> "L'aluminium rouille ?" | F26: =IFERROR(INDEX('20 Ideas'!$B$2:$B$21,MATCH(D26,'20 Ideas'!$A$2:$A$21,0)),"") -> Humour, trust and replies | G26: =IFERROR(INDEX('20 Ideas'!$M$2:$M$21,MATCH(D26,'20 Ideas'!$A$2:$A$21,0)),"") -> Try later | H26: Planned
A27: 6 | B27: 46360 | C27: =TEXT(B27,"dddd") -> Friday | D27: 17 | E27: =IFERROR(INDEX('20 Ideas'!$C$2:$C$21,MATCH(D27,'20 Ideas'!$A$2:$A$21,0)),"") -> Skit: "un petit coulissant" | F27: =IFERROR(INDEX('20 Ideas'!$B$2:$B$21,MATCH(D27,'20 Ideas'!$A$2:$A$21,0)),"") -> Humour, trust and replies | G27: =IFERROR(INDEX('20 Ideas'!$M$2:$M$21,MATCH(D27,'20 Ideas'!$A$2:$A$21,0)),"") -> Try later | H27: Planned
A28: 6 | B28: 46362 | C28: =TEXT(B28,"dddd") -> Sunday | D28: 4 | E28: =IFERROR(INDEX('20 Ideas'!$C$2:$C$21,MATCH(D28,'20 Ideas'!$A$2:$A$21,0)),"") -> Folding mosquito net in three colours | F28: =IFERROR(INDEX('20 Ideas'!$B$2:$B$21,MATCH(D28,'20 Ideas'!$A$2:$A$21,0)),"") -> Stock, trucks, colours | G28: =IFERROR(INDEX('20 Ideas'!$M$2:$M$21,MATCH(D28,'20 Ideas'!$A$2:$A$21,0)),"") -> Stock & trucks | H28: Planned | J28: Or #14 once a safe rig is validated
A30: Shoot sessions (from the 20-ideas file)
E31: Session | F31: Time | G31: Videos
E32: Stock & trucks | F32: Half a day | G32: #1 (3 cities' worth), #2, #3, #4, #12, #13
E33: Counter | F33: Half a day | G33: #5 (3 tips), #6, #7, #8, #19, #20
E34: Screen recording | F34: 1 hour | G34: #9, #10
E35: Kitchen/dressing | F35: 1 hour | G35: #15, #16
E36: Ask a favour | F36: When ready | G36: #11 with 3 customer workshops
E37: Try later | G37: #14 (needs a safe rig), #17, #18
A39: First four weeks
B40: Post 3–4 a week. Start with #1, #5, #2 and #9, because the first three come from your own best results and #9 is the only idea nobody else has. After four weeks, check which pillar had the best shares per 1,000 views and post more of that.
B41: The number that matters is WhatsApp enquiries that say they came from social, not views.

Sheet 30-Day Plan
A1: 30-day plan (from the strategy report, section 7)
A2: This is the first plan I gave you. The Calendar sheet has the later six-week version built from the 20 ideas.
A4: Rhythm: 4 videos a week (3 minimum), all 9:16, filmed, no more than one animated piece a week.
A5: Week | B5: Mon | C5: Wed | D5: Fri | E5: Sat/Sun
A6: 1 | B6: #1 truck to Meknès | C6: #4 dust-fix follow-up | D6: #2 colours in stock | E6: #14 handle-profile reveal
A7: 2 | B7: #1 truck (new city) | C7: #7 AR on a terrace | D7: #5 S70P vs S90RP | E7: #10 wall-sliding system
A8: 3 | B8: #6 kg quiz | C8: #4 tip #2 | D8: #1 truck (new city) | E8: #8 pergola speed-run
A9: 4 | B9: #9 menuisier case | C9: #21 price factors | D9: #12 weight test | E9: #3 arrivage
A11: Every video:
A12: • Hook in the first 1–2 seconds as on-screen text, in Darija or French.
A13: • Caption: one short line in Arabic or French plus 3–5 tags (city + category + one Arabic tag). Drop #viral and #fyp.
A14: • Phone number on the video, not in the caption.
A15: • Original sound (your top 3 used it).
A16: • Cross-post to Instagram Reels without the TikTok watermark; turn the tip and education videos into carousels.
A17: Fix first (this week):
A18: 1. Check the @fesal.aluminium links on prompolu.com and the "Fesal" watermark: point everything to @prompolu or decide on one brand.
A19: 2. Re-export the landscape video, or delete it.
A20: 3. Add a one-line question to your WhatsApp greeting ("Vous nous avez connus par… ?") so you can count enquiries from social.
A21: 4. Put the AR tool access request in your link-in-bio.
A22: What to measure:
... A25: • Which pillar (stock, tips, AR, mechanism, kitchen) gets the best share rate: double down after 4 weeks.

Sheet Results Tracker
A1: Results tracker
A2: Fill the yellow cells 48 hours after posting. The grey row is an EXAMPLE with made-up numbers: overwrite it.
A4: Assumptions (blue = editable)
A5: Your median views | D5: ='My TikTok Videos'!$E$18 -> 1394 | E5: From 'My TikTok Videos' (median of your 10 videos). Replace with a newer median when you have more posts.
A6: Sequel threshold (× your median) | D6: 3 | E6: Playbook rule: a video at 3× your median within 48 h earns a sequel within 3 days.
A7: Benchmark share rate | D7: 0.002 | E7: Niche sample: typical share rate is 0.2–0.4% of views (see 'Niche Patterns').
A8: Benchmark save rate | D8: 0.002 | E8: Niche sample: typical save rate is 0.2–0.4% of views.
A10: Date posted | B10: Idea # | C10: Idea | D10: Hook (A/B) | E10: Platform | F10: Views @48h | G10: Likes | H10: Comments | I10: Shares | J10: Saves | K10: WhatsApp enquiries | L10: Share rate | M10: Save rate | N10: Views vs median (×) | O10: Suggested next step
A11: 46321 | B11: 1 | C11: =IF(B11="","",IFERROR(INDEX('20 Ideas'!$C$2:$C$21,MATCH(B11,'20 Ideas'!$A$2:$A$21,0)),"")) -> "Ce camion part pour [ville]" | D11: A | E11: TikTok | F11: 5200 | G11: 90 | H11: 6 | I11: 28 | J11: 20 | K11: 3 | L11: =IF(F11="","",IFERROR(I11/F11,0)) -> 0.0053846154 | M11: =IF(F11="","",IFERROR(J11/F11,0)) -> 0.0038461538 | N11: =IF(F11="","",IFERROR(F11/$D$5,0)) -> 3.7302726 | O11: =IF(F11="","",IF(N11>=$D$6,"Make a sequel within 3 days",IF(AND(N11<1,M11>=$D$8),"Good idea, weak hook: re-post with a new first second",IF(AND(N11>=1,L11<$D$7),"Entertained but not useful: add a share prompt","Keep and watch")))) -> Make a sequel within 3 days
C12: =IF(B12="","",IFERROR(INDEX('20 Ideas'!$C$2:$C$21,MATCH(B12,'20 Ideas'!$A$2:$A$21,0)),"")) | L12: =IF(F12="","",IFERROR(I12/F12,0)) | M12: =IF(F12="","",IFERROR(J12/F12,0)) | N12: =IF(F12="","",IFERROR(F12/$D$5,0)) | O12: =IF(F12="","",IF(N12>=$D$6,"Make a sequel within 3 days",IF(AND(N12<1,M12>=$D$8),"Good idea, weak hook: re-post with a new first second",IF(AND(N12>=1,L12<$D$7),"Entertained but not useful: add a share prompt","Keep and watch"))))
C13: =IF(B13="","",IFERROR(INDEX('20 Ideas'!$C$2:$C$21,MATCH(B13,'20 Ideas'!$A$2:$A$21,0)),"")) | L13: =IF(F13="","",IFERROR(I13/F13,0)) | M13: =IF(F13="","",IFERROR(J13/F13,0)) | N13: =IF(F13="","",IFERROR(F13/$D$5,0)) | O13: =IF(F13="","",IF(N13>=$D$6,"Make a sequel within 3 days",IF(AND(N13<1,M13>=$D$8),"Good idea, weak hook: re-post with a new first second",IF(AND(N13>=1,L13<$D$7),"Entertained but not useful: add a share prompt","Keep and watch"))))
C14: =IF(B14="","",IFERROR(INDEX('20 Ideas'!$C$2:$C$21,MATCH(B14,'20 Ideas'!$A$2:$A$21,0)),"")) | L14: =IF(F14="","",IFERROR(I14/F14,0)) | M14: =IF(F14="","",IFERROR(J14/F14,0)) | N14: =IF(F14="","",IFERROR(F14/$D$5,0)) | O14: =IF(F14="","",IF(N14>=$D$6,"Make a sequel within 3 days",IF(AND(N14<1,M14>=$D$8),"Good idea, weak hook: re-post with a new first second",IF(AND(N14>=1,L14<$D$7),"Entertained but not useful: add a share prompt","Keep and watch"))))
C15: =IF(B15="","",IFERROR(INDEX('20 Ideas'!$C$2:$C$21,MATCH(B15,'20 Ideas'!$A$2:$A$21,0)),"")) | L15: =IF(F15="","",IFERROR(I15/F15,0)) | M15: =IF(F15="","",IFERROR(J15/F15,0)) | N15: =IF(F15="","",IFERROR(F15/$D$5,0)) | O15: =IF(F15="","",IF(N15>=$D$6,"Make a sequel within 3 days",IF(AND(N15<1,M15>=$D$8),"Good idea, weak hook: re-post with a new first second",IF(AND(N15>=1,L15<$D$7),"Entertained but not useful: add a share prompt","Keep and watch"))))
C16: =IF(B16="","",IFERROR(INDEX('20 Ideas'!$C$2:$C$21,MATCH(B16,'20 Ideas'!$A$2:$A$21,0)),"")) | L16: =IF(F16="","",IFERROR(I16/F16,0)) | M16: =IF(F16="","",IFERROR(J16/F16,0)) | N16: =IF(F16="","",IFERROR(F16/$D$5,0)) | O16: =IF(F16="","",IF(N16>=$D$6,"Make a sequel within 3 days",IF(AND(N16<1,M16>=$D$8),"Good idea, weak hook: re-post with a new first second",IF(AND(N16>=1,L16<$D$7),"Entertained but not useful: add a share prompt","Keep and watch"))))
C17: =IF(B17="","",IFERROR(INDEX('20 Ideas'!$C$2:$C$21,MATCH(B17,'20 Ideas'!$A$2:$A$21,0)),"")) | L17: =IF(F17="","",IFERROR(I17/F17,0)) | M17: =IF(F17="","",IFERROR(J17/F17,0)) | N17: =IF(F17="","",IFERROR(F17/$D$5,0)) | O17: =IF(F17="","",IF(N17>=$D$6,"Make a sequel within 3 days",IF(AND(N17<1,M17>=$D$8),"Good idea, weak hook: re-post with a new first second",IF(AND(N17>=1,L17<$D$7),"Entertained but not useful: add a share prompt","Keep and watch"))))
C18: =IF(B18="","",IFERROR(INDEX('20 Ideas'!$C$2:$C$21,MATCH(B18,'20 Ideas'!$A$2:$A$21,0)),"")) | L18: =IF(F18="","",IFERROR(I18/F18,0)) | M18: =IF(F18="","",IFERROR(J18/F18,0)) | N18: =IF(F18="","",IFERROR(F18/$D$5,0)) | O18: =IF(F18="","",IF(N18>=$D$6,"Make a sequel within 3 days",IF(AND(N18<1,M18>=$D$8),"Good idea, weak hook: re-post with a new first second",IF(AND(N18>=1,L18<$D$7),"Entertained but not useful: add a share prompt","Keep and watch"))))
C19: =IF(B19="","",IFERROR(INDEX('20 Ideas'!$C$2:$C$21,MATCH(B19,'20 Ideas'!$A$2:$A$21,0)),"")) | L19: =IF(F19="","",IFERROR(I19/F19,0)) | M19: =IF(F19="","",IFERROR(J19/F19,0)) | N19: =IF(F19="","",IFERROR(F19/$D$5,0)) | O19: =IF(F19="","",IF(N19>=$D$6,"Make a sequel within 3 days",IF(AND(N19<1,M19>=$D$8),"Good idea, weak hook: re-post with a new first second",IF(AND(N19>=1,L19<$D$7),"Entertained but not useful: add a share prompt","Keep and watch"))))
C20: =IF(B20="","",IFERROR(INDEX('20 Ideas'!$C$2:$C$21,MATCH(B20,'20 Ideas'!$A$2:$A$21,0)),"")) | L20: =IF(F20="","",IFERROR(I20/F20,0)) | M20: =IF(F20="","",IFERROR(J20/F20,0)) | N20: =IF(F20="","",IFERROR(F20/$D$5,0)) | O20: =IF(F20="","",IF(N20>=$D$6,"Make a sequel within 3 days",IF(AND(N20<1,M20>=$D$8),"Good idea, weak hook: re-post with a new first second",IF(AND(N20>=1,L20<$D$7),"Entertained but not useful: add a share prompt","Keep and watch"))))
C21: =IF(B21="","",IFERROR(INDEX('20 Ideas'!$C$2:$C$21,MATCH(B21,'20 Ideas'!$A$2:$A$21,0)),"")) | L21: =IF(F21="","",IFERROR(I21/F21,0)) | M21: =IF(F21="","",IFERROR(J21/F21,0)) | N21: =IF(F21="","",IFERROR(F21/$D$5,0)) | O21: =IF(F21="","",IF(N21>=$D$6,"Make a sequel within 3 days",IF(AND(N21<1,M21>=$D$8),"Good idea, weak hook: re-post with a new first second",IF(AND(N21>=1,L21<$D$7),"Entertained but not useful: add a share prompt","Keep and watch"))))
C22: =IF(B22="","",IFERROR(INDEX('20 Ideas'!$C$2:$C$21,MATCH(B22,'20 Ideas'!$A$2:$A$21,0)),"")) | L22: =IF(F22="","",IFERROR(I22/F22,0)) | M22: =IF(F22="","",IFERROR(J22/F22,0)) | N22: =IF(F22="","",IFERROR(F22/$D$5,0)) | O22: =IF(F22="","",IF(N22>=$D$6,"Make a sequel within 3 days",IF(AND(N22<1,M22>=$D$8),"Good idea, weak hook: re-post with a new first second",IF(AND(N22>=1,L22<$D$7),"Entertained but not useful: add a share prompt","Keep and watch"))))
C23: =IF(B23="","",IFERROR(INDEX('20 Ideas'!$C$2:$C$21,MATCH(B23,'20 Ideas'!$A$2:$A$21,0)),"")) | L23: =IF(F23="","",IFERROR(I23/F23,0)) | M23: =IF(F23="","",IFERROR(J23/F23,0)) | N23: =IF(F23="","",IFERROR(F23/$D$5,0)) | O23: =IF(F23="","",IF(N23>=$D$6,"Make a sequel within 3 days",IF(AND(N23<1,M23>=$D$8),"Good idea, weak hook: re-post with a new first second",IF(AND(N23>=1,L23<$D$7),"Entertained but not useful: add a share prompt","Keep and watch"))))
... C40: =IF(B40="","",IFERROR(INDEX('20 Ideas'!$C$2:$C$21,MATCH(B40,'20 Ideas'!$A$2:$A$21,0)),"")) | L40: =IF(F40="","",IFERROR(I40/F40,0)) | M40: =IF(F40="","",IFERROR(J40/F40,0)) | N40: =IF(F40="","",IFERROR(F40/$D$5,0)) | O40: =IF(F40="","",IF(N40>=$D$6,"Make a sequel within 3 days",IF(AND(N40<1,M40>=$D$8),"Good idea, weak hook: re-post with a new first second",IF(AND(N40>=1,L40<$D$7),"Entertained but not useful: add a share prompt","Keep and watch"))))
A42: Rules that need your judgement (not automated): comments with questions → answer with a reply video (idea #20) the same week; under your median twice in a row → retire that format for a month; WhatsApp enquiries from social is the real score.

Sheet Rules & Checklists
A1: Rules, standards and checklists
A2: From the playbook (Part 1, Part 4, Part 5), the ideas file and the strategy report. ☐ cells have a ☐/✅ dropdown.
A4: 1.1 What your data says to stop doing
A5: Habit | B5: Evidence
A6: Opening on a logo, a "Hello!" or a blank screen | B6: Your five animated videos had a median of 312 views (filmed: 4,546). Their cover frames were mostly a logo, "Hello!", or a near-blank canvas.
A7: Landscape video | B7: Your 21 Oct video is 1024×576. On a phone it plays as a thin strip.
A8: Captions like "Retrouvez-nous sur notre site" | B8: Your two biggest videos had hashtag-only captions. The weak ones used this line.
A9: A phone number in the caption | B9: Niche captions with a number: median 4.8K views vs 13.9K without (correlation). Put the number on the video, as your winners did.
A10: Long gaps | B10: 8 weeks without posting in May–July.
A13: 1.2 The seven viral triggers (each video should hit at least two)
B14: 1. Instant hook: the first frame already shows something interesting, with a few words of text. No greeting, no logo, no "aujourd'hui je vais vous montrer".
B15: 2. Rewatch: a loop (last frame matches the first), a quick sequence people replay to catch, or a quiz where they check the answer.
B16: 3. Share: something a viewer sends to a specific person ("envoie ça à ton menuisier").
B17: 4. Save: a cheat sheet or a template people want to keep.
B18: 5. Comment: a binary choice, a question with a checkable answer, or a "what city next?".
B19: 6. Local: a city name, Darija, a familiar street. In your niche, Arabic captions had about 4× the median reach in Morocco (correlation).
B20: 7. Real: filmed with real hands, real stock, real trucks. This is what your audience already watches.
B21: TikTok doesn't confirm how it weighs these, but watch time, shares, saves and comments are generally treated as the strongest signals.
A23: 1.3 Production standard
B24: • Vertical 1080×1920, 30 fps. Use 60–120 fps only for slow-motion shots.
B25: • Lock focus and exposure (tap and hold) before recording, clean the lens, and use daylight.
B26: • Steady: a small tripod, or elbows tucked into your body. No digital zoom.
B27: • Shot length: 1–3 seconds for mechanism clips, 3–5 for explainers. Cut on movement.
B28: • Text: 7 words or fewer, large, in the middle of the frame. Avoid the top and bottom edges (the app covers them). One font, high contrast.
B29: • Burned-in subtitles for anything with speech. Many people scroll muted, and TikTok's data for your videos showed no auto-generated captions.
B30: • Sound: original sound or ambient. Record close to the action. Your top 3 used original sound. (Your two licensed-music videos were also animated, so I can't separate the effects.)
B31: • Phone number on the video, small, in the upper third.
B32: • Cover frame: a product shot, not a logo.
B33: • Keep the edited file from your editing app (no TikTok watermark) so you can upload the same file to Reels.
A35: 1.4 Posting checklist (every video)
B36: 1. Caption: one short line (Arabic or French) with a question when it fits, plus 3–5 tags: a city, a category and one Arabic tag. Drop #viral and #fyp.
B37: 2. Pinned comment with something useful (a list, a template, a question).
B38: 3. First hour: reply to every comment. Turn good questions into reply videos (idea #20).
B39: 4. Reels: same file, hook text in the middle of the frame, product cover, location tag (Fès or Sefrou), caption that ends with a question. Share to Stories. For partner videos, try the Instagram Collab post. (No Instagram data was available, so these are general practice.)
B40: 5. WhatsApp: add a one-line question to your greeting ("Vous nous avez connus par… ?") so you can count enquiries that came from social. That number matters more than views.
A42: 1.5 Benchmarks from the niche sample
B43: • Typical share rate: 0.2–0.4% of views. Typical save rate: 0.2–0.4%.
B44: • Your own median: 1,394 views. A video at 3× your median within 48 hours is a signal to make a sequel (see Part 4).
A46: Rules for every video
B47: 1. Hook text in the first second. Your captions currently say "Retrouvez-nous sur notre site", which gives people no reason to watch.
B48: 2. Phone number on the video, not in the caption (your winners did this; niche captions with numbers did worse).
B49: 3. Caption: one short line (Arabic or French) plus 3–5 tags: a city, a category and one Arabic tag. Drop #viral and #fyp.
B50: 4. Original sound. Your top 3 all used it.
B51: 5. Film it, don't animate it. Your filmed videos have a median of 4,546 views, against 312 for the animated ones.
A53: Reels versions (nothing below is based on Instagram data, because I couldn't read any)
B54: • Export a clean file without the TikTok watermark.
B55: • Keep the hook text in the middle of the frame, away from the top and bottom edges where the Reels interface covers it.
B56: • Pick a cover frame that shows the product.
B57: • Tag the location (Fès or Sefrou).
B58: • End with a question in the caption, because Reels tend to spread by sends and saves.
A60: Part 4: How to learn from the results
B61: After 48 hours, compare each video to your own median (1,394 views) and to the niche rates (shares and saves 0.2–0.4%).
A62: What you see | B62: What to do
A63: 3× your median | B63: Make a sequel within 3 days, with the same hook structure and a new subject.
A64: Low views, high saves | B64: The idea is good but the hook is weak. Re-post with a new first second.
A65: High views, low shares | B65: It entertained but wasn't useful. Add a share prompt ("envoie à ton menuisier").
A66: Comments with questions | B66: Answer with a reply video (#20) the same week.
A67: Under your median, twice in a row | B67: Retire that format for a month.
A68: WhatsApp enquiries from social | B68: This is the real score. Count them every week.
B70: After four weeks, rank the pillars by shares per 1,000 views and plan the next month around the top two.
A72: Part 5: What to check before you film
A73: ☐ | B73: Prop and product on hand: galandage S88RP (#12), integrated-handle kitchen (#15), S86RP sample (#13), S110P sample (#14), mosquito net samples (#4).
A74: ☐ | B74: The AR link is working on a recent phone (#9, #10).
A75: ☐ | B75: Written permission for any customer, workshop, face or address (#11, #15).
A76: ☐ | B76: Every spec cross-checked against STRUGAL sheets.
A77: ☐ | B77: 9:16 export, hook in the first frame, phone number on screen, no logo intro.
A79: Fix first (this week):
B80: 1. Check the @fesal.aluminium links on prompolu.com and the "Fesal" watermark: point everything to @prompolu or decide on one brand.
B81: 2. Re-export the landscape video, or delete it.
B82: 3. Add a one-line question to your WhatsApp greeting ("Vous nous avez connus par… ?") so you can count enquiries from social.
B83: 4. Put the AR tool access request in your link-in-bio.
A85: What to measure:
B86: • WhatsApp enquiries that say they came from TikTok/Instagram: the real number.
B87: • 3-second hold rate and shares per 1,000 views in TikTok Analytics.
B88: • Which pillar (stock, tips, AR, mechanism, kitchen) gets the best share rate: double down after 4 weeks.

Sheet Study List
A1: Group | B1: Views | C1: Length (s) | D1: Account | E1: Followers | F1: Video link
A2: Moroccan videos | B2: 8300000 | C2: 7 | D2: @proalumad | E2: 602200 | F2: https://www.tiktok.com/@proalumad/video/7075315096817306885
A3: Moroccan videos | B3: 5900000 | C3: 11 | D3: @proalumad | E3: 602200 | F3: https://www.tiktok.com/@proalumad/video/7288013328054488326
A4: Moroccan videos | B4: 1800000 | C4: 5 | D4: @proalumad | E4: 602300 | F4: https://www.tiktok.com/@proalumad/video/7591110042548538645
A5: Moroccan videos | B5: 1700000 | C5: 51 | D5: @alu.mamoune | E5: 18100 | F5: https://www.tiktok.com/@alu.mamoune/video/7323879084658887942
A6: Moroccan videos | B6: 1300000 | C6: 18 | D6: @proalumad | E6: 602200 | F6: https://www.tiktok.com/@proalumad/video/7541352573593324808
A7: Moroccan videos | B7: 1100000 | C7: 66 | D7: @tamarisstores2009 | E7: 46900 | F7: https://www.tiktok.com/@tamarisstores2009/video/7340389793223724294
A8: Moroccan videos | B8: 839000 | C8: 23 | D8: @aluminooo | E8: 74500 | F8: https://www.tiktok.com/@aluminooo/video/7602743628905057557
A9: Moroccan videos | B9: 446300 | C9: 32 | D9: @alocuisines | E9: 47400 | F9: https://www.tiktok.com/@alocuisines/video/7288763769570839813
A10: Moroccan videos | B10: 418000 | C10: 52 | D10: @oussamahirche | E10: 25400 | F10: https://www.tiktok.com/@oussamahirche/video/7655816058258853141
A11: Moroccan videos | B11: 355700 | C11: 13 | D11: @proalumad | E11: 602300 | F11: https://www.tiktok.com/@proalumad/video/7639412122660769045
A12: Moroccan videos | B12: 293400 | C12: 20 | D12: @alu.mamoune | E12: 18100 | F12: https://www.tiktok.com/@alu.mamoune/video/7555038195470093586
A13: International videos | B13: 9000000 | C13: 18 | D13: @chinawindowsdoors | E13: 206000 | F13: https://www.tiktok.com/@chinawindowsdoors/video/7434373688859921672
... A18: International videos | B18: 2500000 | C18: 12 | D18: @chinawindowsdoors | E18: 206000 | F18: https://www.tiktok.com/@chinawindowsdoors/video/7436946128278424850

Sheet Niche Videos
A1: Video URL | B1: Account | C1: Followers | D1: Posted | E1: Length (s) | F1: Views | G1: Likes | H1: Comments | I1: Shares | J1: Saves | K1: Moroccan? | L1: Caption (160 chars, phones redacted) | M1: Share rate | N1: Save rate | O1: Flag: Arabic caption | P1: Flag: hashtag-only | Q1: Flag: phone in caption | R1: Flag: Kitchen / cuisine | S1: Flag: Mosquito net | T1: Flag: Sliding / coulissant | U1: Flag: Pergola / terrace | V1: Flag: Railing / garde-corps | W1: Flag: Window / fenêtre | X1: Flag: Door / porte | Y1: Flag: Dressing / wardrobe | Z1: Flag: Shower | AA1: Flag: Accessories / hardware | AB1: Flag: Facade / vitrine | AC1: Flag: Before / after | AD1: Flag: Price / prix / devis
A2: https://www.tiktok.com/@chinawindowsdoors/video/7434373688859921672 | B2: chinawindowsdoors | C2: 206000 | D2: 45603 | E2: 18 | F2: 9000000 | G2: 105500 | H2: 2676 | I2: 45200 | J2: 25886 | K2: no | L2: Easy to install, waterproof,and able to block space. #slidingdoor #slidingdoors #foldingdoor #door #aluminium #alloy #interiordesign #install #tottme #tottmetal | M2: =IFERROR(I2/F2,0) -> 0.0050222222 | N2: =IFERROR(J2/F2,0) -> 0.0028762222 | O2: 0 | P2: 0 | Q2: 0 | R2: 0 | S2: 0 | T2: 1 | U2: 0 | V2: 0 | W2: 0 | X2: 1 | Y2: 0 | Z2: 0 | AA2: 0 | AB2: 0 | AC2: 0 | AD2: 0
A3: https://www.tiktok.com/@proalumad/video/7075315096817306885 | B3: proalumad | C3: 602200 | D3: 44635 | E3: 7 | F3: 8300000 | G3: 89600 | H3: 764 | I3: 11200 | J3: 4841 | K3: yes | L3: #cuisinealuminium #fpyシ #bouznika #مطابخ_حديثة_المنيوم #marocaine🇲🇦 #casablanca #proalum #rabat #proalumad | M3: =IFERROR(I3/F3,0) -> 0.0013493976 | N3: =IFERROR(J3/F3,0) -> 0.00058325301 | O3: 1 | P3: 1 | Q3: 0 | R3: 1 | S3: 0 | T3: 0 | U3: 0 | V3: 0 | W3: 0 | X3: 0 | Y3: 0 | Z3: 0 | AA3: 0 | AB3: 0 | AC3: 0 | AD3: 1
A4: https://www.tiktok.com/@proalumad/video/7288013328054488326 | B4: proalumad | C4: 602200 | D4: 45208 | E4: 11 | F4: 5900000 | G4: 126000 | H4: 919 | I4: 14800 | J4: 19442 | K4: yes | L4: #مطابخ_حديثة_المنيوم #foryoupage #الدار_البيضاء #cuisinealuminium #المغرب🇲🇦تونس🇹🇳الجزائر🇩🇿 #aluminium #rabat #casablanca #proalumad #proalum #mohammedia | M4: =IFERROR(I4/F4,0) -> 0.0025084746 | N4: =IFERROR(J4/F4,0) -> 0.0032952542 | O4: 1 | P4: 1 | Q4: 0 | R4: 1 | S4: 0 | T4: 0 | U4: 0 | V4: 0 | W4: 0 | X4: 0 | Y4: 0 | Z4: 0 | AA4: 0 | AB4: 0 | AC4: 0 | AD4: 1
A5: https://www.tiktok.com/@omy.window.and.door0/video/7488288149555334446 | B5: omy.window.and.door0 | C5: 16400 | D5: 45748 | E5: 11 | F5: 3200000 | G5: 98800 | H5: 1495 | I5: 16700 | J5: 10558 | K5: no | L5: China doors and windows yuantou factory#window#Aluminium window#Doors and windows yuantou factory | M5: =IFERROR(I5/F5,0) -> 0.00521875 | N5: =IFERROR(J5/F5,0) -> 0.003299375 | O5: 0 | P5: 0 | Q5: 0 | R5: 0 | S5: 0 | T5: 0 | U5: 0 | V5: 0 | W5: 1 | X5: 1 | Y5: 0 | Z5: 0 | AA5: 0 | AB5: 0 | AC5: 0 | AD5: 0
A6: https://www.tiktok.com/@windowhome1/video/7347574448490319147 | B6: windowhome1 | C6: 208900 | D6: 45369 | E6: 14 | F6: 3000000 | G6: 41600 | H6: 566 | I6: 23500 | J6: 11527 | K6: no | L6: The latest design of the sliding door system PT door has no ground track design and has sliding and flat opening functions.#aluminium #door #ptdoors | M6: =IFERROR(I6/F6,0) -> 0.0078333333 | N6: =IFERROR(J6/F6,0) -> 0.0038423333 | O6: 0 | P6: 0 | Q6: 0 | R6: 0 | S6: 0 | T6: 1 | U6: 0 | V6: 0 | W6: 0 | X6: 1 | Y6: 0 | Z6: 0 | AA6: 0 | AB6: 0 | AC6: 0 | AD6: 0
A7: https://www.tiktok.com/@windowhome1/video/7360507063526608170 | B7: windowhome1 | C7: 208900 | D7: 45404 | E7: 14 | F7: 3000000 | G7: 45100 | H7: 455 | I7: 30500 | J7: 11657 | K7: no | L7: The latest designed sliding door system PT door PD door has no floor rail design and has sliding and flat opening functions.#aluminium #doors | M7: =IFERROR(I7/F7,0) -> 0.010166667 | N7: =IFERROR(J7/F7,0) -> 0.0038856667 | O7: 0 | P7: 0 | Q7: 0 | R7: 0 | S7: 0 | T7: 1 | U7: 0 | V7: 0 | W7: 0 | X7: 1 | Y7: 0 | Z7: 0 | AA7: 0 | AB7: 0 | AC7: 0 | AD7: 0
A8: https://www.tiktok.com/@blinds2go.official/video/7651300960135957782 | B8: blinds2go.official | C8: 171800 | D8: 46187 | E8: 50 | F8: 2500000 | G8: 1784 | H8: 28 | I8: 237 | J8: 757 | K8: no | L8: Sliding doors just got a little smarter 🏡 These no drill blinds are made specifically for aluminium sliding doors, sticking directly to the glass and moving sea | M8: =IFERROR(I8/F8,0) -> 9.48e-05 | N8: =IFERROR(J8/F8,0) -> 0.0003028 | O8: 0 | P8: 0 | Q8: 0 | R8: 1 | S8: 0 | T8: 1 | U8: 0 | V8: 0 | W8: 0 | X8: 1 | Y8: 0 | Z8: 0 | AA8: 0 | AB8: 0 | AC8: 0 | AD8: 0
A9: https://www.tiktok.com/@chinawindowsdoors/video/7436946128278424850 | B9: chinawindowsdoors | C9: 206000 | D9: 45610 | E9: 12 | F9: 2500000 | G9: 35000 | H9: 1306 | I9: 10600 | J9: 7170 | K9: no | L9: No need to drill holes,keep warm in winter and insulated in summer.#slidingdoor #slidingdoors #foldingdoor #door #aluminium #alloy #interiordesign #install #tot | M9: =IFERROR(I9/F9,0) -> 0.00424 | N9: =IFERROR(J9/F9,0) -> 0.002868 | O9: 0 | P9: 0 | Q9: 0 | R9: 0 | S9: 0 | T9: 1 | U9: 0 | V9: 0 | W9: 0 | X9: 1 | Y9: 0 | Z9: 0 | AA9: 0 | AB9: 0 | AC9: 0 | AD9: 0
A10: https://www.tiktok.com/@chinawindowsdoors/video/7456647456017616135 | B10: chinawindowsdoors | C10: 206000 | D10: 45663 | E10: 15 | F10: 2000000 | G10: 27500 | H10: 407 | I10: 12900 | J10: 15169 | K10: no | L10: Easy to install,no track required.#slidingdoor #slidingdoors #door #aluminium #alloy #interiordesign #install #home #tottme #tottmetal | M10: =IFERROR(I10/F10,0) -> 0.00645 | N10: =IFERROR(J10/F10,0) -> 0.0075845 | O10: 0 | P10: 0 | Q10: 0 | R10: 0 | S10: 0 | T10: 1 | U10: 0 | V10: 0 | W10: 0 | X10: 1 | Y10: 0 | Z10: 0 | AA10: 0 | AB10: 0 | AC10: 0 | AD10: 0
A11: https://www.tiktok.com/@proalumad/video/7591110042548538645 | B11: proalumad | C11: 602300 | D11: 46025 | E11: 5 | F11: 1800000 | G11: 12600 | H11: 90 | I11: 7527 | J11: 5283 | K11: yes | L11: #mohammedia #proalumad #cuisinealuminium #rabat #aluminium | M11: =IFERROR(I11/F11,0) -> 0.0041816667 | N11: =IFERROR(J11/F11,0) -> 0.002935 | O11: 0 | P11: 1 | Q11: 0 | R11: 1 | S11: 0 | T11: 0 | U11: 0 | V11: 0 | W11: 0 | X11: 0 | Y11: 0 | Z11: 0 | AA11: 0 | AB11: 0 | AC11: 0 | AD11: 1
A12: https://www.tiktok.com/@siddiquealuminumandglass/video/7676841474662714644 | B12: siddiquealuminumandglass | C12: 12100 | D12: 46256 | E12: 16 | F12: 1800000 | G12: 30900 | H12: 191 | I12: 8461 | J12: 9882 | K12: no | L12: Telescope sliding door Aluminum telescope sliding door#creatersearchingsight #siddiquealuminiumandglassexperts #telescopsliding #telescop | M12: =IFERROR(I12/F12,0) -> 0.0047005556 | N12: =IFERROR(J12/F12,0) -> 0.00549 | O12: 0 | P12: 0 | Q12: 0 | R12: 0 | S12: 0 | T12: 1 | U12: 0 | V12: 0 | W12: 0 | X12: 1 | Y12: 0 | Z12: 0 | AA12: 0 | AB12: 0 | AC12: 0 | AD12: 0
A13: https://www.tiktok.com/@alu.mamoune/video/7323879084658887942 | B13: alu.mamoune | C13: 18100 | D13: 45305 | E13: 51 | F13: 1700000 | G13: 17100 | H13: 409 | I13: 6699 | J13: 2577 | K13: yes | L13: #cuisine #cuisniemaroccaine #cuisinemdfmaroc #cuisinetiktok #cuisinealuminium #مطابخ_حديثة_المنيوم #مطابخ_حديثة | M13: =IFERROR(I13/F13,0) -> 0.0039405882 | N13: =IFERROR(J13/F13,0) -> 0.0015158824 | O13: 1 | P13: 1 | Q13: 0 | R13: 1 | S13: 0 | T13: 0 | U13: 0 | V13: 0 | W13: 0 | X13: 0 | Y13: 0 | Z13: 0 | AA13: 0 | AB13: 0 | AC13: 0 | AD13: 0
... A218: https://www.tiktok.com/@marvel.kigali.gorin/video/7687232188114390280 | B218: marvel.kigali.gorin | C218: 9172 | D218: 46284 | E218: 168 | F218: 9575 | G218: 317 | H218: 7 | I218: 75 | J218: 87 | K218: no | L218: Brand new aluminium factory in Kigali Freezone that can sell aluminium profile to carry 350kg glass! Privacy protection wall! Children protection foldable doors | M218: =IFERROR(I218/F218,0) -> 0.0078328982 | N218: =IFERROR(J218/F218,0) -> 0.0090861619 | O218: 0 | P218: 0 | Q218: 0 | R218: 0 | S218: 0 | T218: 0 | U218: 0 | V218: 0 | W218: 0 | X218: 1 | Y218: 0 | Z218: 0 | AA218: 0 | AB218: 0 | AC218: 0 | AD218: 0
A219: https://www.tiktok.com/@aluminium.safii/video/7697962171405307154 | B219: aluminium.safii | C219: 1081 | D219: 46313 | E219: 29 | F219: 9499 | G219: 165 | H219: 2 | I219: 79 | J219: 32 | K219: no | M219: =IFERROR(I219/F219,0) -> 0.0083166649 | N219: =IFERROR(J219/F219,0) -> 0.0033687757 | O219: 0 | P219: 1 | Q219: 0 | R219: 0 | S219: 0 | T219: 0 | U219: 0 | V219: 0 | W219: 0 | X219: 0 | Y219: 0 | Z219: 0 | AA219: 0 | AB219: 0 | AC219: 0 | AD219: 0
A220: https://www.tiktok.com/@sahara.intelligence/video/7449839690498297120 | B220: sahara.intelligence | C220: 49400 | D220: 45644 | E220: 135 | F220: 9303 | G220: 92 | H220: 2 | I220: 12 | J220: 16 | K220: yes | L220: Vers une harmonisation des façades de cafés à Casablanca#rabat#maroc#casablanca#harmonie #cafe#facade#restauration#image#decor#demande#wali#ordre#urbanisation#l | M220: =IFERROR(I220/F220,0) -> 0.0012899065 | N220: =IFERROR(J220/F220,0) -> 0.0017198753 | O220: 0 | P220: 0 | Q220: 0 | R220: 0 | S220: 0 | T220: 0 | U220: 0 | V220: 0 | W220: 0 | X220: 0 | Y220: 0 | Z220: 0 | AA220: 0 | AB220: 1 | AC220: 0 | AD220: 0
A221: https://www.tiktok.com/@kajobaashraf/video/7698475710784015636 | B221: kajobaashraf | C221: 547900 | D221: 46314 | E221: 110 | F221: 8943 | G221: 442 | H221: 15 | I221: 1 | J221: 41 | K221: no | L221: #fyp #foryou #foryoupage #ugandatiktok #aluminum @kajobaashraf | M221: =IFERROR(I221/F221,0) -> 0.0001118193 | N221: =IFERROR(J221/F221,0) -> 0.0045845913 | O221: 0 | P221: 0 | Q221: 0 | R221: 0 | S221: 0 | T221: 0 | U221: 0 | V221: 0 | W221: 0 | X221: 0 | Y221: 0 | Z221: 0 | AA221: 0 | AB221: 0 | AC221: 0 | AD221: 0
A222: https://www.tiktok.com/@designodoorslimited/video/7679527151703461152 | B222: designodoorslimited | C222: 7262 | D222: 46263 | E222: 83 | F222: 8713 | G222: 107 | H222: 2 | I222: 86 | J222: 86 | K222: no | L222: ##aluminium #sliding #installation #renovation #construction | M222: =IFERROR(I222/F222,0) -> 0.0098703087 | N222: =IFERROR(J222/F222,0) -> 0.0098703087 | O222: 0 | P222: 1 | Q222: 0 | R222: 0 | S222: 0 | T222: 1 | U222: 0 | V222: 0 | W222: 0 | X222: 0 | Y222: 0 | Z222: 0 | AA222: 0 | AB222: 0 | AC222: 0 | AD222: 0
A223: https://www.tiktok.com/@aluminium.style/video/7666501459814501639 | B223: aluminium.style | C223: 1147 | D223: 46228 | E223: 20 | F223: 8424 | G223: 447 | H223: 4 | I223: 12 | J223: 38 | K223: no | L223: ❌❌✅nouveau chantier 💯💯🇹🇳#menuiserie #aluminum #doors #tunisia🇹🇳 #libya🇱🇾 | M223: =IFERROR(I223/F223,0) -> 0.0014245014 | N223: =IFERROR(J223/F223,0) -> 0.0045109212 | O223: 0 | P223: 0 | Q223: 0 | R223: 0 | S223: 0 | T223: 0 | U223: 0 | V223: 0 | W223: 0 | X223: 1 | Y223: 0 | Z223: 0 | AA223: 0 | AB223: 0 | AC223: 0 | AD223: 0
A224: https://www.tiktok.com/@rm_accessoires1/video/7613524695069003028 | B224: rm_accessoires1 | C224: 2282 | D224: 46085 | E224: 16 | F224: 8317 | G224: 130 | H224: 6 | I224: 17 | J224: 26 | K224: yes | L224: Charnière 3D (RM Accessoires) مفصلات بجودة احترافية للبيع بالجملة ، الاختيار الأول للحرفيين في المغرب لضمان إتقان وسهولة في التركيب #RM_Accessoires #Aluminium_ | M224: =IFERROR(I224/F224,0) -> 0.0020440063 | N224: =IFERROR(J224/F224,0) -> 0.0031261272 | O224: 1 | P224: 0 | Q224: 0 | R224: 0 | S224: 0 | T224: 0 | U224: 0 | V224: 0 | W224: 0 | X224: 0 | Y224: 0 | Z224: 0 | AA224: 1 | AB224: 0 | AC224: 0 | AD224: 0
A225: https://www.tiktok.com/@estudiolfarq/video/7582289176230432020 | B225: estudiolfarq | C225: 96700 | D225: 46001 | E225: 13 | F225: 8310 | G225: 125 | H225: 2 | I225: 4 | J225: 10 | K225: yes | L225: Casa Moderna Life House - Casa Blanca, Marrocos 🇲🇦 By Estúdio LF Arquitetura . . #arquitetura #casasdeluxo #casasluxuosas #fachadasmodernas #imoveisdeluxo | M225: =IFERROR(I225/F225,0) -> 0.00048134777 | N225: =IFERROR(J225/F225,0) -> 0.0012033694 | O225: 0 | P225: 0 | Q225: 0 | R225: 0 | S225: 0 | T225: 0 | U225: 0 | V225: 0 | W225: 0 | X225: 0 | Y225: 0 | Z225: 0 | AA225: 0 | AB225: 0 | AC225: 0 | AD225: 0
A226: https://www.tiktok.com/@lamenagere.paris/video/7659831064415735073 | B226: lamenagere.paris | C226: 9134 | D226: 46210 | E226: 28 | F226: 8237 | G226: 164 | H226: 12 | I226: 54 | J226: 120 | K226: no | L226: ✔️ Cette magnifique porte vitrée coulissante est idéale pour séparer un couloir d'un salon, d'une cuisine ou de toilettes. Elle convient également parfaitement | M226: =IFERROR(I226/F226,0) -> 0.0065557849 | N226: =IFERROR(J226/F226,0) -> 0.014568411 | O226: 0 | P226: 0 | Q226: 1 | R226: 1 | S226: 0 | T226: 1 | U226: 1 | V226: 0 | W226: 0 | X226: 1 | Y226: 0 | Z226: 0 | AA226: 0 | AB226: 0 | AC226: 0 | AD226: 1
A227: https://www.tiktok.com/@changyuanalu/video/7198069285124672769 | B227: changyuanalu | C227: 50 | D227: 44966 | E227: 47 | F227: 8198 | G227: 76 | H227: 3 | I227: 39 | J227: 15 | K227: no | L227: aluminium profile anodizing #aluminium #aluminiumprofile #aluminum #manufacturing #China #foshanbuildingmaterials #anodizing @ #factory #powdercoated | M227: =IFERROR(I227/F227,0) -> 0.0047572579 | N227: =IFERROR(J227/F227,0) -> 0.0018297146 | O227: 0 | P227: 0 | Q227: 0 | R227: 0 | S227: 0 | T227: 0 | U227: 0 | V227: 0 | W227: 0 | X227: 0 | Y227: 0 | Z227: 0 | AA227: 0 | AB227: 0 | AC227: 0 | AD227: 0
A228: https://www.tiktok.com/@khaledhadjkali/video/7575947445595639058 | B228: khaledhadjkali | C228: 14900 | D228: 45984 | E228: 39 | F228: 8080 | G228: 129 | H228: 8 | I228: 11 | J228: 10 | K228: no | L228: Une baie vitrée Tpr blanc coulissant trois rails pour plus d’informations. N’hésitez pas à nous appeler sur 07 97 603, 903, localisation Kn Alu bouzareah Alger | M228: =IFERROR(I228/F228,0) -> 0.0013613861 | N228: =IFERROR(J228/F228,0) -> 0.0012376238 | O228: 1 | P228: 0 | Q228: 0 | R228: 0 | S228: 0 | T228: 1 | U228: 0 | V228: 0 | W228: 1 | X228: 0 | Y228: 0 | Z228: 0 | AA228: 0 | AB228: 0 | AC228: 0 | AD228: 0
A229: https://www.tiktok.com/@aydiscount/video/7647225695323737347 | B229: aydiscount | C229: 345 | D229: 46176 | E229: 8 | F229: 8030 | G229: 50 | H229: 4 | I229: 21 | J229: 40 | K229: no | L229: 🔥 GARDE-CORPS EN VERRE 270€/ml🔥 Apportez une touche moderne et élégante à votre terrasse, balcon ou escalier avec nos garde-corps en verre haute qualité. ✔️ Des | M229: =IFERROR(I229/F229,0) -> 0.002615193 | N229: =IFERROR(J229/F229,0) -> 0.00498132 | O229: 0 | P229: 0 | Q229: 0 | R229: 0 | S229: 0 | T229: 0 | U229: 1 | V229: 1 | W229: 0 | X229: 0 | Y229: 0 | Z229: 0 | AA229: 0 | AB229: 0 | AC229: 0 | AD229: 1
A230: https://www.tiktok.com/@aluminum.profile0/video/7580610861778291976 | B230: aluminum.profile0 | C230: 29800 | D230: 45997 | E230: 9 | F230: 8022 | G230: 139 | H230: 16 | I230: 20 | J230: 35 | K230: no | L230: Where to buy aluminum profile? Absolutely Foshan China. We have customers from many different countries. See if there is your country below. We focus on aluminu | M230: =IFERROR(I230/F230,0) -> 0.0024931439 | N230: =IFERROR(J230/F230,0) -> 0.0043630017 | O230: 0 | P230: 0 | Q230: 0 | R230: 1 | S230: 0 | T230: 0 | U230: 0 | V230: 0 | W230: 0 | X230: 0 | Y230: 1 | Z230: 0 | AA230: 0 | AB230: 0 | AC230: 0 | AD230: 0
A231: https://www.tiktok.com/@nassimtaamourt/video/7697690722576747828 | B231: nassimtaamourt | C231: 21500 | D231: 46312 | E231: 19 | F231: 7979 | G231: 142 | H231: 2 | I231: 4 | J231: 14 | K231: no | M231: =IFERROR(I231/F231,0) -> 0.00050131595 | N231: =IFERROR(J231/F231,0) -> 0.0017546058 | O231: 0 | P231: 1 | Q231: 0 | R231: 0 | S231: 0 | T231: 0 | U231: 0 | V231: 0 | W231: 0 | X231: 0 | Y231: 0 | Z231: 0 | AA231: 0 | AB231: 0 | AC231: 0 | AD231: 0
A232: https://www.tiktok.com/@zaki.aluminiumpro/video/7474376416902008069 | B232: zaki.aluminiumpro | C232: 12900 | D232: 45710 | E232: 61 | F232: 7898 | G232: 102 | H232: 9 | I232: 41 | J232: 19 | K232: yes | L232: #meniuserie #aluminium #casablanca #morocco🇲🇦 #redcity #cusine #balcon #dicoration #placards #casablanca #maroc🇲🇦 | M232: =IFERROR(I232/F232,0) -> 0.0051911876 | N232: =IFERROR(J232/F232,0) -> 0.0024056723 | O232: 0 | P232: 1 | Q232: 0 | R232: 0 | S232: 0 | T232: 0 | U232: 0 | V232: 0 | W232: 0 | X232: 0 | Y232: 1 | Z232: 0 | AA232: 0 | AB232: 0 | AC232: 0 | AD232: 0
A233: https://www.tiktok.com/@atouleee.national/video/7508765260036279574 | B233: atouleee.national | C233: 68300 | D233: 45803 | E233: 56 | F233: 7876 | G233: 106 | H233: 4 | I233: 21 | J233: 26 | K233: no | L233: Baie vitrée à 6 vantaux coulissants sur 3 rails, avec ouverture en angle, offrant une vue panoramique exceptionnelle et une ventilation naturelle optimale. Dime | M233: =IFERROR(I233/F233,0) -> 0.0026663281 | N233: =IFERROR(J233/F233,0) -> 0.0033011681 | O233: 0 | P233: 0 | Q233: 0 | R233: 0 | S233: 0 | T233: 1 | U233: 0 | V233: 0 | W233: 0 | X233: 0 | Y233: 0 | Z233: 0 | AA233: 0 | AB233: 0 | AC233: 0 | AD233: 0
A234: https://www.tiktok.com/@sidali90k/video/7653861823326031124 | B234: sidali90k | C234: 4381 | D234: 46194 | E234: 65 | F234: 7543 | G234: 117 | H234: 17 | I234: 9 | J234: 24 | K234: no | L234: #aluminium #شعب_الصيني_ماله_حل😂😂 #dressing #outillage #menuiserie | M234: =IFERROR(I234/F234,0) -> 0.0011931592 | N234: =IFERROR(J234/F234,0) -> 0.0031817579 | O234: 1 | P234: 1 | Q234: 0 | R234: 0 | S234: 0 | T234: 0 | U234: 0 | V234: 0 | W234: 0 | X234: 0 | Y234: 1 | Z234: 0 | AA234: 0 | AB234: 0 | AC234: 0 | AD234: 0
A235: https://www.tiktok.com/@mirrorsdesign/video/7554371290291866887 | B235: mirrorsdesign | C235: 752 | D235: 45926 | E235: 14 | F235: 7468 | G235: 80 | H235: 4 | I235: 13 | J235: 24 | K235: yes | L235: #Cuisine #CuisineElegante #CuisineDesign #CuisineModerne #CuisineMarocaine #KitchenDesign #KitchenInspiration #HomeDecor #DecoMaison #CuisineEnAluminium #Modern | M235: =IFERROR(I235/F235,0) -> 0.0017407606 | N235: =IFERROR(J235/F235,0) -> 0.0032137118 | O235: 1 | P235: 1 | Q235: 0 | R235: 1 | S235: 0 | T235: 0 | U235: 0 | V235: 0 | W235: 1 | X235: 1 | Y235: 0 | Z235: 0 | AA235: 0 | AB235: 0 | AC235: 0 | AD235: 0
A236: https://www.tiktok.com/@joubijalusystem/video/7653596542900636960 | B236: joubijalusystem | C236: 9764 | D236: 46193 | E236: 48 | F236: 7426 | G236: 424 | H236: 2 | I236: 67 | J236: 26 | K236: yes | L236: #ألمنيوم #ديكور_مغربي #explore #aluminum #marocaine🇲🇦 | M236: =IFERROR(I236/F236,0) -> 0.0090223539 | N236: =IFERROR(J236/F236,0) -> 0.003501212 | O236: 1 | P236: 1 | Q236: 0 | R236: 0 | S236: 0 | T236: 0 | U236: 0 | V236: 0 | W236: 0 | X236: 0 | Y236: 0 | Z236: 0 | AA236: 0 | AB236: 0 | AC236: 0 | AD236: 0
A237: https://www.tiktok.com/@menuiserielembour/video/7042302615966813446 | B237: menuiserielembour | C237: 4090 | D237: 44546 | E237: 97 | F237: 7354 | G237: 240 | H237: 8 | I237: 33 | J237: 10 | K237: no | L237: Porte coulissante bois et fer pour baie vitrée 77 054 12 84. | M237: =IFERROR(I237/F237,0) -> 0.0044873538 | N237: =IFERROR(J237/F237,0) -> 0.0013598042 | O237: 0 | P237: 0 | Q237: 0 | R237: 0 | S237: 0 | T237: 1 | U237: 0 | V237: 0 | W237: 0 | X237: 1 | Y237: 0 | Z237: 0 | AA237: 0 | AB237: 0 | AC237: 0 | AD237: 0
A238: https://www.tiktok.com/@aluminooo/video/7606474003909250325 | B238: aluminooo | C238: 74500 | D238: 46066 | E238: 26 | F238: 7245 | G238: 58 | H238: 0 | I238: 15 | J238: 19 | K238: yes | L238: Cabine de douche, système fixe, fixation profil Aluminium, original salle de bain Disponible au Maroc 🇲🇦 contacte sur WhatsApp [tel] ##salledebain##maroc##c | M238: =IFERROR(I238/F238,0) -> 0.0020703934 | N238: =IFERROR(J238/F238,0) -> 0.0026224983 | O238: 0 | P238: 0 | Q238: 1 | R238: 0 | S238: 0 | T238: 0 | U238: 0 | V238: 0 | W238: 0 | X238: 0 | Y238: 0 | Z238: 1 | AA238: 0 | AB238: 0 | AC238: 0 | AD238: 0
A239: https://www.tiktok.com/@zaki.aluminiumpro/video/7689989589875969332 | B239: zaki.aluminiumpro | C239: 12900 | D239: 46291 | E239: 35 | F239: 7162 | G239: 355 | H239: 4 | I239: 31 | J239: 15 | K239: yes | L239: #placards #aluminium #😍🤎 #cuisine #maroco🇲🇦algeria🇩🇿tunisia🇹🇳 | M239: =IFERROR(I239/F239,0) -> 0.0043283999 | N239: =IFERROR(J239/F239,0) -> 0.002094387 | O239: 0 | P239: 1 | Q239: 0 | R239: 1 | S239: 0 | T239: 0 | U239: 0 | V239: 0 | W239: 0 | X239: 0 | Y239: 1 | Z239: 0 | AA239: 0 | AB239: 0 | AC239: 0 | AD239: 0
A240: https://www.tiktok.com/@alocuisines/video/7237812478875421957 | B240: alocuisines | C240: 47400 | D240: 45073 | E240: 514 | F240: 7159 | G240: 45 | H240: 1 | I240: 7 | J240: 3 | K240: yes | L240: جديد المطابخ العصرية في المغرب مطبخ إم دي إف مع الالومنيوم الصح و العمل MDF et Aluminium #cuisines #Équipées #cuisinesequipees #cuisineséquipées #cuisinemaiso | M240: =IFERROR(I240/F240,0) -> 0.00097779019 | N240: =IFERROR(J240/F240,0) -> 0.00041905294 | O240: 1 | P240: 0 | Q240: 0 | R240: 1 | S240: 0 | T240: 0 | U240: 0 | V240: 0 | W240: 0 | X240: 0 | Y240: 0 | Z240: 0 | AA240: 0 | AB240: 0 | AC240: 0 | AD240: 0
A241: https://www.tiktok.com/@snay3i_bdarija/video/7297664548385918213 | B241: snay3i_bdarija | C241: 673 | D241: 45234 | E241: 32 | F241: 7052 | G241: 616 | H241: 114 | I241: 263 | J241: 13 | K241: yes | L241: الألمينوم الزجاج mdf مرحبا بكم تمن جد مناسب وجودة عالية [tel] مرحبا بكم🦈 #aluminum #aluminum #المغرب #الجزائر #تونس🇹🇳 #المغرب🇲🇦تونس🇹🇳الجزائر🇩🇿 #مراكش #marrake | M241: =IFERROR(I241/F241,0) -> 0.037294385 | N241: =IFERROR(J241/F241,0) -> 0.0018434487 | O241: 1 | P241: 0 | Q241: 1 | R241: 0 | S241: 0 | T241: 0 | U241: 0 | V241: 0 | W241: 0 | X241: 0 | Y241: 0 | Z241: 0 | AA241: 0 | AB241: 0 | AC241: 0 | AD241: 0
A242: https://www.tiktok.com/@ideal_aluminium_senegal1/video/7637541022217686292 | B242: ideal_aluminium_senegal1 | C242: 27500 | D242: 46150 | E242: 14 | F242: 7038 | G242: 164 | H242: 9 | I242: 14 | J242: 29 | K242: no | L242: Baie vitrée Coulissante pour vos Salon #ideal_aluminium_senegal | M242: =IFERROR(I242/F242,0) -> 0.0019892015 | N242: =IFERROR(J242/F242,0) -> 0.0041204888 | O242: 0 | P242: 0 | Q242: 0 | R242: 0 | S242: 0 | T242: 1 | U242: 0 | V242: 0 | W242: 0 | X242: 0 | Y242: 0 | Z242: 0 | AA242: 0 | AB242: 0 | AC242: 0 | AD242: 0
A243: https://www.tiktok.com/@novabuildinga/video/7198829318548622597 | B243: novabuildinga | C243: 2250 | D243: 44968 | E243: 16 | F243: 6833 | G243: 68 | H243: 0 | I243: 23 | J243: 11 | K243: yes | L243: cuisine moderne Aluminium 🤌🖤 #verretrempé #aluminium #cuisinealuminium #architecturedesign #decoration #trempé #verre #aluminumwiretree #marocaine🇲🇦 #maroc #arc | M243: =IFERROR(I243/F243,0) -> 0.0033660179 | N243: =IFERROR(J243/F243,0) -> 0.0016098346 | O243: 0 | P243: 0 | Q243: 0 | R243: 1 | S243: 0 | T243: 0 | U243: 0 | V243: 0 | W243: 0 | X243: 0 | Y243: 1 | Z243: 0 | AA243: 0 | AB243: 0 | AC243: 0 | AD243: 0
... A289: https://www.tiktok.com/@arqfree.constructora/video/7597473891086322965 | B289: arqfree.constructora | C289: 267900 | D289: 46042 | E289: 26 | F289: 3409 | G289: 93 | H289: 2 | I289: 14 | J289: 11 | K289: no | L289: ✨🏡 AGAR Residence (615m²): Marruecos ya tiene su casa ícono. Arquitectura posmoderna con fachada escultural y detalles que se sienten lujo real. 🌍 Diseñado por | M289: =IFERROR(I289/F289,0) -> 0.0041067762 | N289: =IFERROR(J289/F289,0) -> 0.0032267527 | O289: 0 | P289: 0 | Q289: 0 | R289: 0 | S289: 0 | T289: 0 | U289: 0 | V289: 0 | W289: 0 | X289: 0 | Y289: 0 | Z289: 0 | AA289: 0 | AB289: 0 | AC289: 0 | AD289: 0
A290: https://www.tiktok.com/@najat.dou/video/7667188152544546056 | B290: najat.dou | C290: 1800 | D290: 46230 | E290: 18 | F290: 3375 | G290: 109 | H290: 5 | I290: 5 | J290: 7 | K290: no | M290: =IFERROR(I290/F290,0) -> 0.0014814815 | N290: =IFERROR(J290/F290,0) -> 0.0020740741 | O290: 0 | P290: 1 | Q290: 0 | R290: 0 | S290: 0 | T290: 0 | U290: 0 | V290: 0 | W290: 0 | X290: 0 | Y290: 0 | Z290: 0 | AA290: 0 | AB290: 0 | AC290: 0 | AD290: 0
A291: https://www.tiktok.com/@ora.glass.and.alu/video/7625508559731657991 | B291: ora.glass.and.alu | C291: 1769 | D291: 46118 | E291: 19 | F291: 3338 | G291: 29 | H291: 1 | I291: 5 | J291: 1 | K291: no | L291: we do make aluminium sliding doors high quality aluminium sliding doors prices range from K1,500,000....from different sizes #luxurylife #Malawi #aluminium #sli | M291: =IFERROR(I291/F291,0) -> 0.0014979029 | N291: =IFERROR(J291/F291,0) -> 0.00029958059 | O291: 0 | P291: 0 | Q291: 0 | R291: 0 | S291: 0 | T291: 1 | U291: 0 | V291: 0 | W291: 0 | X291: 1 | Y291: 0 | Z291: 0 | AA291: 0 | AB291: 0 | AC291: 0 | AD291: 1
A292: https://www.tiktok.com/@groupmaisondelux/video/7244276126569286917 | B292: groupmaisondelux | C292: 14000 | D292: 45090 | E292: 58 | F292: 3267 | G292: 18 | H292: 0 | I292: 10 | J292: 4 | K292: no | L292: baie vitrée coulissante 2 rails 4 vantaux by #Group_Maison_DeLux #algeria🇩🇿 #algerienne #alger #Oran #annaba #Constantine #mila #homedesign #homedecor #archit | M292: =IFERROR(I292/F292,0) -> 0.0030609122 | N292: =IFERROR(J292/F292,0) -> 0.0012243649 | O292: 0 | P292: 0 | Q292: 0 | R292: 0 | S292: 0 | T292: 1 | U292: 0 | V292: 0 | W292: 0 | X292: 1 | Y292: 0 | Z292: 0 | AA292: 0 | AB292: 0 | AC292: 0 | AD292: 0
A293: https://www.tiktok.com/@alugabon/video/7549276688790654214 | B293: alugabon | C293: 12500 | D293: 45912 | E293: 61 | F293: 3251 | G293: 63 | H293: 6 | I293: 6 | J293: 6 | K293: no | L293: porte coulissante#DIY #baievitrée #AvantApres #videoviral #vu | M293: =IFERROR(I293/F293,0) -> 0.001845586 | N293: =IFERROR(J293/F293,0) -> 0.001845586 | O293: 0 | P293: 0 | Q293: 0 | R293: 0 | S293: 0 | T293: 1 | U293: 0 | V293: 0 | W293: 0 | X293: 1 | Y293: 0 | Z293: 0 | AA293: 0 | AB293: 0 | AC293: 1 | AD293: 0
A294: https://www.tiktok.com/@elazri.service1/video/7615375482791398663 | B294: elazri.service1 | C294: 945 | D294: 46090 | E294: 24 | F294: 3229 | G294: 34 | H294: 2 | I294: 7 | J294: 11 | K294: yes | L294: Donnez à votre espace un style moderne avec l’effet béton. Finition élégante, résistante et tendance pour murs et façades. 📍 Travail professionnel – Résultat ga | M294: =IFERROR(I294/F294,0) -> 0.0021678538 | N294: =IFERROR(J294/F294,0) -> 0.0034066274 | O294: 0 | P294: 0 | Q294: 0 | R294: 0 | S294: 0 | T294: 0 | U294: 0 | V294: 0 | W294: 0 | X294: 0 | Y294: 0 | Z294: 0 | AA294: 0 | AB294: 1 | AC294: 0 | AD294: 0
A295: https://www.tiktok.com/@golden.hand.aluminium/video/7606095799399058708 | B295: golden.hand.aluminium | C295: 4067 | D295: 46065 | E295: 18 | F295: 3214 | G295: 84 | H295: 10 | I295: 2 | J295: 4 | K295: no | L295: golden Hand Aluminium 🪟 🎥 شوفو مليح هاد grand baie vitrée coulissant 3 rail الكبيرة 👌 مشـي غير حجم… المهم هو النوعية لي راها داخلة فيها 👇 كاين لي يديرها رخيصة… | M295: =IFERROR(I295/F295,0) -> 0.00062227754 | N295: =IFERROR(J295/F295,0) -> 0.0012445551 | O295: 1 | P295: 0 | Q295: 0 | R295: 0 | S295: 0 | T295: 1 | U295: 0 | V295: 0 | W295: 0 | X295: 1 | Y295: 0 | Z295: 0 | AA295: 0 | AB295: 0 | AC295: 0 | AD295: 0
A296: https://www.tiktok.com/@tm_aluminium/video/7666909588154928405 | B296: tm_aluminium | C296: 3887 | D296: 46229 | E296: 59 | F296: 3213 | G296: 110 | H296: 3 | I296: 12 | J296: 8 | K296: yes | L296: ##TMAluminium #aluminium #menuiseriealuminium #agadir #maroc | M296: =IFERROR(I296/F296,0) -> 0.0037348273 | N296: =IFERROR(J296/F296,0) -> 0.0024898848 | O296: 0 | P296: 1 | Q296: 0 | R296: 0 | S296: 0 | T296: 0 | U296: 0 | V296: 0 | W296: 0 | X296: 0 | Y296: 0 | Z296: 0 | AA296: 0 | AB296: 0 | AC296: 0 | AD296: 0
A297: https://www.tiktok.com/@greenbaie.porte.f/video/7252711317927234842 | B297: greenbaie.porte.f | C297: 45 | D297: 45113 | E297: 63 | F297: 3186 | G297: 13 | H297: 0 | I297: 6 | J297: 5 | K297: no | L297: #baievitree #aluminum #devisgratuit #menuiserie #pourtoi #coulissant | M297: =IFERROR(I297/F297,0) -> 0.0018832392 | N297: =IFERROR(J297/F297,0) -> 0.001569366 | O297: 0 | P297: 1 | Q297: 0 | R297: 0 | S297: 0 | T297: 1 | U297: 0 | V297: 0 | W297: 0 | X297: 0 | Y297: 0 | Z297: 0 | AA297: 0 | AB297: 0 | AC297: 0 | AD297: 1
A298: https://www.tiktok.com/@zaki.aluminiumpro/video/7495852845179161861 | B298: zaki.aluminiumpro | C298: 12900 | D298: 45768 | E298: 32 | F298: 3183 | G298: 78 | H298: 7 | I298: 8 | J298: 7 | K298: yes | L298: #menuiserie #aluminium #casablanca #morocco🇲🇦 #redcity #cusine #balcon #placards #maroc🇲🇦 | M298: =IFERROR(I298/F298,0) -> 0.0025133522 | N298: =IFERROR(J298/F298,0) -> 0.0021991832 | O298: 0 | P298: 1 | Q298: 0 | R298: 0 | S298: 0 | T298: 0 | U298: 0 | V298: 0 | W298: 0 | X298: 0 | Y298: 1 | Z298: 0 | AA298: 0 | AB298: 0 | AC298: 0 | AD298: 0
A299: https://www.tiktok.com/@balustradealu/video/7696917555516067105 | B299: balustradealu | C299: 3396 | D299: 46310 | E299: 73 | F299: 3174 | G299: 31 | H299: 2 | I299: 13 | J299: 19 | K299: no | L299: Merci énormément grâce a nos réseaux sociaux vous nous donner la force et merci de votre confiance 🙏 Veuillez visiter notre site internet: www.balustradealu.f | M299: =IFERROR(I299/F299,0) -> 0.0040957782 | N299: =IFERROR(J299/F299,0) -> 0.0059861374 | O299: 0 | P299: 0 | Q299: 1 | R299: 0 | S299: 0 | T299: 0 | U299: 0 | V299: 1 | W299: 0 | X299: 0 | Y299: 0 | Z299: 0 | AA299: 0 | AB299: 0 | AC299: 0 | AD299: 1
A300: https://www.tiktok.com/@kamelkamel1597/video/7361491865608277281 | B300: kamelkamel1597 | C300: 55 | D300: 45406 | E300: 44 | F300: 3147 | G300: 20 | H300: 0 | I300: 4 | J300: 4 | K300: no | L300: #toustypesdefermetures | M300: =IFERROR(I300/F300,0) -> 0.0012710518 | N300: =IFERROR(J300/F300,0) -> 0.0012710518 | O300: 0 | P300: 1 | Q300: 0 | R300: 0 | S300: 0 | T300: 0 | U300: 0 | V300: 0 | W300: 0 | X300: 0 | Y300: 0 | Z300: 0 | AA300: 0 | AB300: 0 | AC300: 0 | AD300: 0
A301: https://www.tiktok.com/@aluminiumziyou/video/7697031365933665556 | B301: aluminiumziyou | C301: 139 | D301: 46310 | E301: 29 | F301: 3125 | G301: 82 | H301: 0 | I301: 8 | J301: 7 | K301: yes | L301: #alumunium #aluminium #fes #maroc | M301: =IFERROR(I301/F301,0) -> 0.00256 | N301: =IFERROR(J301/F301,0) -> 0.00224 | O301: 0 | P301: 1 | Q301: 0 | R301: 0 | S301: 0 | T301: 0 | U301: 0 | V301: 0 | W301: 0 | X301: 0 | Y301: 0 | Z301: 0 | AA301: 0 | AB301: 0 | AC301: 0 | AD301: 0
A302: https://www.tiktok.com/@aluminum_profile_factory/video/7675650420643056927 | B302: aluminum_profile_factory | C302: 22200 | D302: 46253 | E302: 18 | F302: 2926 | G302: 58 | H302: 0 | I302: 1 | J302: 2 | K302: no | L302: 👉We provide custom extruded aluminum profiles for the construction and machinery industries. 🏭#aluminumOEM #aluminumODM #aluminumfactory #aluminumprofile #alumi | M302: =IFERROR(I302/F302,0) -> 0.0003417635 | N302: =IFERROR(J302/F302,0) -> 0.000683527 | O302: 0 | P302: 0 | Q302: 0 | R302: 0 | S302: 0 | T302: 0 | U302: 0 | V302: 0 | W302: 1 | X302: 1 | Y302: 0 | Z302: 0 | AA302: 0 | AB302: 0 | AC302: 0 | AD302: 0
... A337: https://www.tiktok.com/@mo7tarif_tpr_algerie/video/7698747914188819733 | B337: mo7tarif_tpr_algerie | C337: 23900 | D337: 46315 | E337: 78 | F337: 1800 | G337: 152 | H337: 10 | I337: 0 | J337: 3 | K337: no | L337: Menuiserie aluminium TPR. #المحترف #tpr | M337: =IFERROR(I337/F337,0) -> 0 | N337: =IFERROR(J337/F337,0) -> 0.0016666667 | O337: 1 | P337: 0 | Q337: 0 | R337: 0 | S337: 0 | T337: 0 | U337: 0 | V337: 0 | W337: 0 | X337: 0 | Y337: 0 | Z337: 0 | AA337: 0 | AB337: 0 | AC337: 0 | AD337: 0
A338: https://www.tiktok.com/@nassimtaamourt/video/7697644058310708486 | B338: nassimtaamourt | C338: 21500 | D338: 46312 | E338: 50 | F338: 1764 | G338: 72 | H338: 2 | I338: 0 | J338: 1 | K338: no | M338: =IFERROR(I338/F338,0) -> 0 | N338: =IFERROR(J338/F338,0) -> 0.00056689342 | O338: 0 | P338: 1 | Q338: 0 | R338: 0 | S338: 0 | T338: 0 | U338: 0 | V338: 0 | W338: 0 | X338: 0 | Y338: 0 | Z338: 0 | AA338: 0 | AB338: 0 | AC338: 0 | AD338: 0
A339: https://www.tiktok.com/@skymaxmaroc.ma/video/7603331941487725831 | B339: skymaxmaroc.ma | C339: 3247 | D339: 46058 | E339: 31 | F339: 1761 | G339: 15 | H339: 0 | I339: 3 | J339: 6 | K339: yes | L339: BARDAGE COMPOSITE Habillage façade bardage composite wpc maroc disponible chez nous. SKYMAX MAROC votre fournisseur de matériaux d'habillage et revêtement au | M339: =IFERROR(I339/F339,0) -> 0.0017035775 | N339: =IFERROR(J339/F339,0) -> 0.003407155 | O339: 0 | P339: 0 | Q339: 0 | R339: 0 | S339: 0 | T339: 0 | U339: 0 | V339: 0 | W339: 0 | X339: 0 | Y339: 0 | Z339: 0 | AA339: 0 | AB339: 1 | AC339: 0 | AD339: 0
A340: https://www.tiktok.com/@kajobaashraf/video/7698974302858792212 | B340: kajobaashraf | C340: 547900 | D340: 46316 | E340: 48 | F340: 1724 | G340: 103 | H340: 3 | I340: 1 | J340: 9 | K340: no | L340: #fyp #foryou #foryoupage #ugandatiktok #aluminium @kajobaashraf | M340: =IFERROR(I340/F340,0) -> 0.0005800464 | N340: =IFERROR(J340/F340,0) -> 0.0052204176 | O340: 0 | P340: 0 | Q340: 0 | R340: 0 | S340: 0 | T340: 0 | U340: 0 | V340: 0 | W340: 0 | X340: 0 | Y340: 0 | Z340: 0 | AA340: 0 | AB340: 0 | AC340: 0 | AD340: 0
A341: https://www.tiktok.com/@r__i__d__o__3.0/video/7698428672142806324 | B341: r__i__d__o__3.0 | C341: 7888 | D341: 46314 | E341: 53 | F341: 1683 | G341: 188 | H341: 15 | I341: 0 | J341: 18 | K341: no | L341: Master la Menuiserie Aluminium | M341: =IFERROR(I341/F341,0) -> 0 | N341: =IFERROR(J341/F341,0) -> 0.010695187 | O341: 0 | P341: 0 | Q341: 0 | R341: 0 | S341: 0 | T341: 0 | U341: 0 | V341: 0 | W341: 0 | X341: 0 | Y341: 0 | Z341: 0 | AA341: 0 | AB341: 0 | AC341: 0 | AD341: 0
A342: https://www.tiktok.com/@zghaluminium_sg/video/7698655034355027218 | B342: zghaluminium_sg | C342: 3419 | D342: 46315 | E342: 55 | F342: 1669 | G342: 13 | H342: 0 | I342: 8 | J342: 10 | K342: no | L342: Our aluminium sliding doors are one of the most affordable ways to maximise space, especially in areas where a traditional swing door would take up too much roo | M342: =IFERROR(I342/F342,0) -> 0.0047932894 | N342: =IFERROR(J342/F342,0) -> 0.0059916117 | O342: 0 | P342: 0 | Q342: 0 | R342: 0 | S342: 0 | T342: 1 | U342: 0 | V342: 0 | W342: 0 | X342: 1 | Y342: 0 | Z342: 0 | AA342: 0 | AB342: 0 | AC342: 0 | AD342: 0
A343: https://www.tiktok.com/@intersolar57/video/7606122391126887683 | B343: intersolar57 | C343: 85 | D343: 46065 | E343: 60 | F343: 1661 | G343: 5 | H343: 0 | I343: 0 | J343: 4 | K343: no | L343: Motorisation d’un volet roulant d’une baie vitrée coulissante. Mon client avait une manœuvre par treuil, et malgré ça, il éprouvait des difficultés à manœuvrer | M343: =IFERROR(I343/F343,0) -> 0 | N343: =IFERROR(J343/F343,0) -> 0.0024081878 | O343: 0 | P343: 0 | Q343: 0 | R343: 0 | S343: 0 | T343: 1 | U343: 0 | V343: 0 | W343: 0 | X343: 0 | Y343: 0 | Z343: 0 | AA343: 0 | AB343: 0 | AC343: 0 | AD343: 0
A344: https://www.tiktok.com/@imad10430/video/7698418359502654738 | B344: imad10430 | C344: 2578 | D344: 46314 | E344: 9 | F344: 1658 | G344: 103 | H344: 0 | I344: 2 | J344: 1 | K344: no | L344: #creatorsearchinsights #aluminiummenuiserie #الشعب_الصيني_ماله_حل😂 @Chawki Kl | M344: =IFERROR(I344/F344,0) -> 0.0012062726 | N344: =IFERROR(J344/F344,0) -> 0.00060313631 | O344: 1 | P344: 0 | Q344: 0 | R344: 0 | S344: 0 | T344: 0 | U344: 0 | V344: 0 | W344: 0 | X344: 0 | Y344: 0 | Z344: 0 | AA344: 0 | AB344: 0 | AC344: 0 | AD344: 0
A345: https://www.tiktok.com/@glanium.engineering/video/7699131060633734401 | B345: glanium.engineering | C345: 120000 | D345: 46316 | E345: 66 | F345: 1652 | G345: 71 | H345: 1 | I345: 2 | J345: 2 | K345: no | L345: In China aluminium windows and doors. Premium. World class quality. | M345: =IFERROR(I345/F345,0) -> 0.0012106538 | N345: =IFERROR(J345/F345,0) -> 0.0012106538 | O345: 0 | P345: 0 | Q345: 0 | R345: 0 | S345: 0 | T345: 0 | U345: 0 | V345: 0 | W345: 1 | X345: 1 | Y345: 0 | Z345: 0 | AA345: 0 | AB345: 0 | AC345: 0 | AD345: 0
A346: https://www.tiktok.com/@hicham.el.jaaouan/video/7630447461441670420 | B346: hicham.el.jaaouan | C346: 4609 | D346: 46131 | E346: 30 | F346: 1646 | G346: 32 | H346: 3 | I346: 1 | J346: 2 | K346: yes | L346: حجر تازة لتزيين الواجهات بااحجر الطبيعي #الرخام_المغربي #تزيين_المنازل #حجر_طبيعي #ديكور_مغربي #حرف_تقليدي | M346: =IFERROR(I346/F346,0) -> 0.00060753341 | N346: =IFERROR(J346/F346,0) -> 0.0012150668 | O346: 1 | P346: 0 | Q346: 0 | R346: 0 | S346: 0 | T346: 0 | U346: 0 | V346: 0 | W346: 0 | X346: 0 | Y346: 0 | Z346: 0 | AA346: 0 | AB346: 0 | AC346: 0 | AD346: 0
A347: https://www.tiktok.com/@successmanagementafrica/video/7635646009275616532 | B347: successmanagementafrica | C347: 3787 | D347: 46145 | E347: 25 | F347: 1632 | G347: 31 | H347: 0 | I347: 0 | J347: 2 | K347: no | L347: Élégance et modernité avec nos baies coulissantes en alu. Gagnez en espace et profitez d'une vue panoramique. Disponible en plusieurs coloris (Noir, Gris Anthra | M347: =IFERROR(I347/F347,0) -> 0 | N347: =IFERROR(J347/F347,0) -> 0.0012254902 | O347: 0 | P347: 0 | Q347: 0 | R347: 0 | S347: 0 | T347: 1 | U347: 0 | V347: 0 | W347: 0 | X347: 0 | Y347: 0 | Z347: 0 | AA347: 0 | AB347: 0 | AC347: 0 | AD347: 0
A348: https://www.tiktok.com/@couvertinealuminium/video/7624547665119841553 | B348: couvertinealuminium | C348: 226 | D348: 46115 | E348: 56 | F348: 1624 | G348: 28 | H348: 2 | I348: 21 | J348: 16 | K348: yes | L348: Découvrez le processus complet de fabrication d’une couvertine en aluminium au Maroc 🇲🇦 De la matière brute jusqu’au produit fini, chaque étape est réalisée ave | M348: =IFERROR(I348/F348,0) -> 0.012931034 | N348: =IFERROR(J348/F348,0) -> 0.0098522167 | O348: 0 | P348: 0 | Q348: 0 | R348: 0 | S348: 0 | T348: 0 | U348: 0 | V348: 0 | W348: 0 | X348: 0 | Y348: 0 | Z348: 0 | AA348: 0 | AB348: 0 | AC348: 1 | AD348: 0
A349: https://www.tiktok.com/@halisgroupe.offic/video/7627097652462636308 | B349: halisgroupe.offic | C349: 129 | D349: 46122 | E349: 25 | F349: 1618 | G349: 30 | H349: 0 | I349: 1 | J349: 5 | K349: no | L349: Baie vitrée coulissante Grand Mbao, cite Baobab 2 33 872 91 07 77 240 73 86 www.halisgroupe.com halis@halisgroupe.com #baievitrée #baievitréecoulissante #bai | M349: =IFERROR(I349/F349,0) -> 0.00061804697 | N349: =IFERROR(J349/F349,0) -> 0.0030902349 | O349: 0 | P349: 0 | Q349: 1 | R349: 0 | S349: 0 | T349: 1 | U349: 0 | V349: 0 | W349: 0 | X349: 0 | Y349: 0 | Z349: 0 | AA349: 0 | AB349: 0 | AC349: 0 | AD349: 0
A350: https://www.tiktok.com/@alugabon/video/7652452048587296017 | B350: alugabon | C350: 12500 | D350: 46190 | E350: 90 | F350: 1608 | G350: 80 | H350: 16 | I350: 11 | J350: 9 | K350: no | L350: N’hésitez pas de nous contacter pour tous vos projets de construction@Coach Simplice Mve ASSEKO #vues #libreville_gabon🇬🇦 #windowstyle #diy #aluminium | M350: =IFERROR(I350/F350,0) -> 0.006840796 | N350: =IFERROR(J350/F350,0) -> 0.0055970149 | O350: 0 | P350: 0 | Q350: 0 | R350: 0 | S350: 0 | T350: 0 | U350: 0 | V350: 0 | W350: 1 | X350: 0 | Y350: 0 | Z350: 0 | AA350: 0 | AB350: 0 | AC350: 0 | AD350: 0
... A368: https://www.tiktok.com/@soufianeyasser455/video/7697254592366562581 | B368: soufianeyasser455 | C368: 179 | D368: 46311 | E368: 109 | F368: 1265 | G368: 58 | H368: 8 | I368: 1 | J368: 3 | K368: yes | L368: ⚙️ الدقة فكل قَطعة، والجودة فكل تفصيلة ✨ خدمة متقونة بآلات احترافية 👌 Aluminium • Inox • MDF • Verre 🖤 #الألمنيوم #الديكور_العصري #casablanca #maroco🇲🇦algeria🇩🇿 | M368: =IFERROR(I368/F368,0) -> 0.00079051383 | N368: =IFERROR(J368/F368,0) -> 0.0023715415 | O368: 1 | P368: 0 | Q368: 0 | R368: 0 | S368: 0 | T368: 0 | U368: 0 | V368: 0 | W368: 0 | X368: 0 | Y368: 0 | Z368: 0 | AA368: 0 | AB368: 0 | AC368: 0 | AD368: 0
A369: https://www.tiktok.com/@nassimtaamourt/video/7697599925487471878 | B369: nassimtaamourt | C369: 21500 | D369: 46312 | E369: 24 | F369: 1253 | G369: 61 | H369: 3 | I369: 2 | J369: 1 | K369: no | M369: =IFERROR(I369/F369,0) -> 0.0015961692 | N369: =IFERROR(J369/F369,0) -> 0.0007980846 | O369: 0 | P369: 1 | Q369: 0 | R369: 0 | S369: 0 | T369: 0 | U369: 0 | V369: 0 | W369: 0 | X369: 0 | Y369: 0 | Z369: 0 | AA369: 0 | AB369: 0 | AC369: 0 | AD369: 0
A370: https://www.tiktok.com/@68designcreation/video/7648295747573517570 | B370: 68designcreation | C370: 1023 | D370: 46179 | E370: 26 | F370: 1191 | G370: 28 | H370: 1 | I370: 3 | J370: 4 | K370: no | L370: Escalier suspendu avec garde-corps verre #gardecorpssurmesure #construction #escalier #gardecorps #designcreation | M370: =IFERROR(I370/F370,0) -> 0.0025188917 | N370: =IFERROR(J370/F370,0) -> 0.0033585223 | O370: 0 | P370: 0 | Q370: 0 | R370: 0 | S370: 0 | T370: 0 | U370: 0 | V370: 1 | W370: 0 | X370: 0 | Y370: 0 | Z370: 0 | AA370: 0 | AB370: 0 | AC370: 0 | AD370: 0
A371: https://www.tiktok.com/@markglassoffciel/video/7697225580839800065 | B371: markglassoffciel | C371: 12800 | D371: 46311 | E371: 29 | F371: 1172 | G371: 9 | H371: 0 | I371: 2 | J371: 1 | K371: yes | L371: MARK GLASS : L’expertise du verre et de l’aluminium au Maroc ! 📞 [tel] MARK GLASS, votre expert en verre et aluminium : pergolas, garde-corps, systèmes accordéo | M371: =IFERROR(I371/F371,0) -> 0.0017064846 | N371: =IFERROR(J371/F371,0) -> 0.00085324232 | O371: 0 | P371: 0 | Q371: 1 | R371: 0 | S371: 0 | T371: 0 | U371: 1 | V371: 1 | W371: 0 | X371: 0 | Y371: 0 | Z371: 0 | AA371: 0 | AB371: 0 | AC371: 0 | AD371: 0
A372: https://www.tiktok.com/@alugabon/video/7602751328804179201 | B372: alugabon | C372: 12500 | D372: 46056 | E372: 33 | F372: 1142 | G372: 41 | H372: 4 | I372: 2 | J372: 6 | K372: no | L372: Venez passer vos commandes des fenêtres#viral #baievitrée #flypシ #tiktokgabon🇬🇦tiktok #diy | M372: =IFERROR(I372/F372,0) -> 0.0017513135 | N372: =IFERROR(J372/F372,0) -> 0.0052539405 | O372: 0 | P372: 0 | Q372: 0 | R372: 0 | S372: 0 | T372: 1 | U372: 0 | V372: 0 | W372: 1 | X372: 0 | Y372: 0 | Z372: 0 | AA372: 0 | AB372: 0 | AC372: 0 | AD372: 0
A373: https://www.tiktok.com/@aluminium_marrakech_by_y/video/7183479459167653126 | B373: aluminium_marrakech_by_y | C373: 798 | D373: 44927 | E373: 40 | F373: 1127 | G373: 5 | H373: 0 | I373: 1 | J373: 1 | K373: yes | L373: #menuiseriealuminium #verre #verretrempé #mdf #magazin #decoration #marrakech #morocco #douchetrempé #cuisinealuminium #rideaux #stores #storesrideaux #mdf #cui | M373: =IFERROR(I373/F373,0) -> 0.00088731145 | N373: =IFERROR(J373/F373,0) -> 0.00088731145 | O373: 0 | P373: 1 | Q373: 0 | R373: 1 | S373: 0 | T373: 0 | U373: 0 | V373: 0 | W373: 0 | X373: 0 | Y373: 0 | Z373: 1 | AA373: 0 | AB373: 0 | AC373: 0 | AD373: 0
A374: https://www.tiktok.com/@alu_masterr/video/7661697675934321927 | B374: alu_masterr | C374: 564 | D374: 46215 | E374: 69 | F374: 1100 | G374: 57 | H374: 5 | I374: 5 | J374: 3 | K374: no | L374: Garde-corps D’escalier en Verre Trempé | M374: =IFERROR(I374/F374,0) -> 0.0045454545 | N374: =IFERROR(J374/F374,0) -> 0.0027272727 | O374: 0 | P374: 0 | Q374: 0 | R374: 0 | S374: 0 | T374: 0 | U374: 0 | V374: 1 | W374: 0 | X374: 0 | Y374: 0 | Z374: 0 | AA374: 0 | AB374: 0 | AC374: 0 | AD374: 0
A375: https://www.tiktok.com/@alugabon/video/7605571201431260417 | B375: alugabon | C375: 12500 | D375: 46064 | E375: 32 | F375: 1045 | G375: 38 | H375: 3 | I375: 6 | J375: 6 | K375: no | L375: On vous accompagne dans vos projets de construction 077595977#flypシ #diy #aluminium #baievitrée #tiktokviral | M375: =IFERROR(I375/F375,0) -> 0.0057416268 | N375: =IFERROR(J375/F375,0) -> 0.0057416268 | O375: 0 | P375: 0 | Q375: 0 | R375: 0 | S375: 0 | T375: 1 | U375: 0 | V375: 0 | W375: 0 | X375: 0 | Y375: 0 | Z375: 0 | AA375: 0 | AB375: 0 | AC375: 0 | AD375: 0
A376: https://www.tiktok.com/@nesturaarchitect.id/video/7606637672022510856 | B376: nesturaarchitect.id | C376: 513 | D376: 46067 | E376: 16 | F376: 1045 | G376: 6 | H376: 0 | I376: 1 | J376: 4 | K376: no | L376: Proyek renovasi fasad buat persiapan Ramadhan dan Lebaran. Desain ini mengusung konsep rumah maroko yang mengadopsi unsur lengkung pada fasadnya. Selaras dengan | M376: =IFERROR(I376/F376,0) -> 0.0009569378 | N376: =IFERROR(J376/F376,0) -> 0.0038277512 | O376: 0 | P376: 0 | Q376: 0 | R376: 0 | S376: 0 | T376: 0 | U376: 0 | V376: 0 | W376: 0 | X376: 0 | Y376: 0 | Z376: 0 | AA376: 0 | AB376: 0 | AC376: 0 | AD376: 0
A377: https://www.tiktok.com/@abderrahimrachdi3/video/7656510994885119252 | B377: abderrahimrachdi3 | C377: 7158 | D377: 46201 | E377: 46 | F377: 1042 | G377: 53 | H377: 1 | I377: 13 | J377: 3 | K377: yes | L377: #aluminium #aluminumwindows #window #slidingdoor Installation fenêtre aluminium | Porte coulissante | Fabrication sur mesure | Maroc #menuiserie | M377: =IFERROR(I377/F377,0) -> 0.012476008 | N377: =IFERROR(J377/F377,0) -> 0.0028790787 | O377: 0 | P377: 0 | Q377: 0 | R377: 0 | S377: 0 | T377: 1 | U377: 0 | V377: 0 | W377: 1 | X377: 1 | Y377: 0 | Z377: 0 | AA377: 0 | AB377: 0 | AC377: 0 | AD377: 0
A378: https://www.tiktok.com/@marchal.fermeture/video/7664646387115576608 | B378: marchal.fermeture | C378: 240 | D378: 46223 | E378: 44 | F378: 1041 | G378: 5 | H378: 0 | I378: 0 | J378: 1 | K378: no | L378: Un chantier d’envergure avec une pièce maîtresse impressionnante : ➡️ une baie vitrée coulissante levant 4 vantaux duo rails + 2 fixes latéraux 😮 ➡️ dimensions | M378: =IFERROR(I378/F378,0) -> 0 | N378: =IFERROR(J378/F378,0) -> 0.00096061479 | O378: 0 | P378: 0 | Q378: 0 | R378: 0 | S378: 0 | T378: 1 | U378: 0 | V378: 0 | W378: 1 | X378: 0 | Y378: 0 | Z378: 0 | AA378: 0 | AB378: 0 | AC378: 0 | AD378: 0
A379: https://www.tiktok.com/@markglassoffciel/video/7697550939586071828 | B379: markglassoffciel | C379: 12800 | D379: 46312 | E379: 22 | F379: 1035 | G379: 5 | H379: 0 | I379: 0 | J379: 1 | K379: yes | L379: MARK GLASS : L’expertise du verre et de l’aluminium au Maroc ! 📞 [tel] MARK GLASS, votre expert en verre et aluminium : pergolas, garde-corps, systèmes accordéo | M379: =IFERROR(I379/F379,0) -> 0 | N379: =IFERROR(J379/F379,0) -> 0.00096618357 | O379: 0 | P379: 0 | Q379: 1 | R379: 0 | S379: 0 | T379: 0 | U379: 1 | V379: 1 | W379: 0 | X379: 0 | Y379: 0 | Z379: 0 | AA379: 0 | AB379: 0 | AC379: 0 | AD379: 0
A380: https://www.tiktok.com/@y.zonephone/video/7697687772584316161 | B380: y.zonephone | C380: 983 | D380: 46312 | E380: 16 | F380: 1025 | G380: 19 | H380: 3 | I380: 8 | J380: 7 | K380: yes | L380: #kindle2026 #maroc🇲🇦 | M380: =IFERROR(I380/F380,0) -> 0.007804878 | N380: =IFERROR(J380/F380,0) -> 0.0068292683 | O380: 0 | P380: 1 | Q380: 0 | R380: 0 | S380: 0 | T380: 0 | U380: 0 | V380: 0 | W380: 0 | X380: 0 | Y380: 0 | Z380: 0 | AA380: 0 | AB380: 0 | AC380: 0 | AD380: 0
A381: https://www.tiktok.com/@cheikhou.aluminium/video/7663252608320048417 | B381: cheikhou.aluminium | C381: 6482 | D381: 46219 | E381: 67 | F381: 1013 | G381: 159 | H381: 13 | I381: 42 | J381: 14 | K381: no | L381: Fenetre coulissant baie vitrée Aluminium,porte cuisine aluminium #senegalaise_tik_tok🇸🇳 #pourtoiii#viralvideos#aluminum #visibilite | M381: =IFERROR(I381/F381,0) -> 0.041461007 | N381: =IFERROR(J381/F381,0) -> 0.013820336 | O381: 0 | P381: 0 | Q381: 0 | R381: 1 | S381: 0 | T381: 1 | U381: 0 | V381: 0 | W381: 1 | X381: 1 | Y381: 0 | Z381: 0 | AA381: 0 | AB381: 0 | AC381: 0 | AD381: 0
... A400: https://www.tiktok.com/@aluminum_profile_factory/video/7688657535561141534 | B400: aluminum_profile_factory | C400: 22200 | D400: 46288 | E400: 26 | F400: 832 | G400: 47 | H400: 4 | I400: 0 | J400: 3 | K400: no | L400: 👏👏A warm welcome to our aluminum profile factory, #aluminumOEM #aluminumODM #aluminumfactory #aluminumprofile #aluminummanufacturer #aluminumdoorsandwindows #ch | M400: =IFERROR(I400/F400,0) -> 0 | N400: =IFERROR(J400/F400,0) -> 0.0036057692 | O400: 0 | P400: 0 | Q400: 0 | R400: 0 | S400: 0 | T400: 0 | U400: 0 | V400: 0 | W400: 1 | X400: 1 | Y400: 0 | Z400: 0 | AA400: 0 | AB400: 0 | AC400: 0 | AD400: 0
A401: https://www.tiktok.com/@yassine.essafi6/video/7697173379069234452 | B401: yassine.essafi6 | C401: 312 | D401: 46311 | E401: 8 | F401: 802 | G401: 26 | H401: 2 | I401: 0 | J401: 2 | K401: no | M401: =IFERROR(I401/F401,0) -> 0 | N401: =IFERROR(J401/F401,0) -> 0.0024937656 | O401: 0 | P401: 1 | Q401: 0 | R401: 0 | S401: 0 | T401: 0 | U401: 0 | V401: 0 | W401: 0 | X401: 0 | Y401: 0 | Z401: 0 | AA401: 0 | AB401: 0 | AC401: 0 | AD401: 0
A402: https://www.tiktok.com/@verre.hafid/video/7697682959675051284 | B402: verre.hafid | C402: 353 | D402: 46312 | E402: 67 | F402: 795 | G402: 12 | H402: 0 | I402: 1 | J402: 0 | K402: yes | L402: 🔥 **ACCORDÉON ALUMINIUM SUR MESURE** 🔥 بغيتي تستغل المساحة كاملة وتجمع بين **الأناقة والعملية؟** ✨ ✅ فتح كامل للمساحة ✅ تصميم عصري وأنيق ✅ صناعة حسب القياس ✅ Al | M402: =IFERROR(I402/F402,0) -> 0.0012578616 | N402: =IFERROR(J402/F402,0) -> 0 | O402: 1 | P402: 0 | Q402: 1 | R402: 0 | S402: 0 | T402: 0 | U402: 0 | V402: 0 | W402: 0 | X402: 0 | Y402: 0 | Z402: 0 | AA402: 0 | AB402: 0 | AC402: 0 | AD402: 1
A403: https://www.tiktok.com/@aluminooo/video/7696938913612582160 | B403: aluminooo | C403: 74500 | D403: 46310 | E403: 48 | F403: 778 | G403: 19 | H403: 0 | I403: 3 | J403: 1 | K403: yes | L403: Garde corps les escaliers Verre trempés #gardecorps #villa #maroc #glass 📍🇲🇦🇲🇦🇲🇦🇲🇦🇲🇦🇲🇦 | M403: =IFERROR(I403/F403,0) -> 0.0038560411 | N403: =IFERROR(J403/F403,0) -> 0.001285347 | O403: 0 | P403: 0 | Q403: 0 | R403: 0 | S403: 0 | T403: 0 | U403: 0 | V403: 1 | W403: 0 | X403: 0 | Y403: 0 | Z403: 0 | AA403: 0 | AB403: 0 | AC403: 0 | AD403: 0
A404: https://www.tiktok.com/@markglassoffciel/video/7698111031024897281 | B404: markglassoffciel | C404: 12800 | D404: 46313 | E404: 28 | F404: 742 | G404: 11 | H404: 3 | I404: 2 | J404: 2 | K404: yes | L404: MARK GLASS : L’expertise du verre et de l’aluminium au Maroc ! 📞 [tel] MARK GLASS, votre expert en verre et aluminium : pergolas, garde-corps, systèmes accordéo | M404: =IFERROR(I404/F404,0) -> 0.0026954178 | N404: =IFERROR(J404/F404,0) -> 0.0026954178 | O404: 0 | P404: 0 | Q404: 1 | R404: 0 | S404: 0 | T404: 0 | U404: 1 | V404: 1 | W404: 0 | X404: 0 | Y404: 0 | Z404: 0 | AA404: 0 | AB404: 0 | AC404: 0 | AD404: 0
A405: https://www.tiktok.com/@aluminum_profile_factory/video/7690885723028868383 | B405: aluminum_profile_factory | C405: 22200 | D405: 46294 | E405: 25 | F405: 731 | G405: 32 | H405: 1 | I405: 0 | J405: 1 | K405: no | L405: 📢📢Looking for a trustworthy Chinese aluminum profile partner? Trial and bulk orders are welcome. #aluminumOEM #aluminumODM #aluminumfactory #aluminumprofile #al | M405: =IFERROR(I405/F405,0) -> 0 | N405: =IFERROR(J405/F405,0) -> 0.0013679891 | O405: 0 | P405: 0 | Q405: 0 | R405: 0 | S405: 0 | T405: 0 | U405: 0 | V405: 0 | W405: 1 | X405: 1 | Y405: 0 | Z405: 0 | AA405: 0 | AB405: 0 | AC405: 0 | AD405: 0
A406: https://www.tiktok.com/@markglassoffciel/video/7696902504306543892 | B406: markglassoffciel | C406: 12800 | D406: 46310 | E406: 17 | F406: 706 | G406: 6 | H406: 1 | I406: 5 | J406: 1 | K406: yes | L406: MARK GLASS : L’expertise du verre et de l’aluminium au Maroc ! 📞 [tel] MARK GLASS, votre expert en verre et aluminium : pergolas, garde-corps, systèmes accordéo | M406: =IFERROR(I406/F406,0) -> 0.007082153 | N406: =IFERROR(J406/F406,0) -> 0.0014164306 | O406: 0 | P406: 0 | Q406: 1 | R406: 0 | S406: 0 | T406: 0 | U406: 1 | V406: 1 | W406: 0 | X406: 0 | Y406: 0 | Z406: 0 | AA406: 0 | AB406: 0 | AC406: 0 | AD406: 0
A407: https://www.tiktok.com/@fouad.dahmani3/video/7698488476139834631 | B407: fouad.dahmani3 | C407: 458 | D407: 46314 | E407: 16 | F407: 665 | G407: 15 | H407: 1 | I407: 0 | J407: 0 | K407: yes | L407: accsesouar_counfor_profel aluminium _stugal_aluminium de maroc | M407: =IFERROR(I407/F407,0) -> 0 | N407: =IFERROR(J407/F407,0) -> 0 | O407: 0 | P407: 0 | Q407: 0 | R407: 0 | S407: 0 | T407: 0 | U407: 0 | V407: 0 | W407: 0 | X407: 0 | Y407: 0 | Z407: 0 | AA407: 0 | AB407: 0 | AC407: 0 | AD407: 0
A408: https://www.tiktok.com/@jlchinadoorfactory/video/7698680202737487137 | B408: jlchinadoorfactory | C408: 3702 | D408: 46315 | E408: 8 | F408: 662 | G408: 0 | H408: 0 | I408: 0 | J408: 0 | K408: no | L408: Custom high‑end aluminium doors & windows ✅ Quotations available for private homeowners and contractors. Message us directly for your offer!#JL #aluminum #Fosha | M408: =IFERROR(I408/F408,0) -> 0 | N408: =IFERROR(J408/F408,0) -> 0 | O408: 0 | P408: 0 | Q408: 0 | R408: 0 | S408: 0 | T408: 0 | U408: 0 | V408: 0 | W408: 1 | X408: 1 | Y408: 0 | Z408: 0 | AA408: 0 | AB408: 0 | AC408: 0 | AD408: 0
A409: https://www.tiktok.com/@ecodom_algerie/video/7649467867284442389 | B409: ecodom_algerie | C409: 1365 | D409: 46182 | E409: 22 | F409: 636 | G409: 22 | H409: 1 | I409: 1 | J409: 3 | K409: no | L409: L'élégance se révèle dans les détails ✨ Pour cette villa d'exception à Alger, nous avons réalisé une installation de garde-corps en verre sur socles en aluminiu | M409: =IFERROR(I409/F409,0) -> 0.001572327 | N409: =IFERROR(J409/F409,0) -> 0.0047169811 | O409: 0 | P409: 0 | Q409: 0 | R409: 0 | S409: 0 | T409: 0 | U409: 0 | V409: 1 | W409: 0 | X409: 0 | Y409: 0 | Z409: 0 | AA409: 0 | AB409: 0 | AC409: 0 | AD409: 0
A410: https://www.tiktok.com/@68designcreation/video/7653922674137107745 | B410: 68designcreation | C410: 1023 | D410: 46194 | E410: 62 | F410: 629 | G410: 18 | H410: 4 | I410: 5 | J410: 3 | K410: no | L410: Escalier avec garde-corps verre #gardecorpssurmesure #construction #escalier #renovation #construction | M410: =IFERROR(I410/F410,0) -> 0.0079491256 | N410: =IFERROR(J410/F410,0) -> 0.0047694754 | O410: 0 | P410: 0 | Q410: 0 | R410: 0 | S410: 0 | T410: 0 | U410: 0 | V410: 1 | W410: 0 | X410: 0 | Y410: 0 | Z410: 0 | AA410: 0 | AB410: 0 | AC410: 0 | AD410: 0
A411: https://www.tiktok.com/@johnnyxcally/video/7698115430862376198 | B411: johnnyxcally | C411: 369 | D411: 46313 | E411: 57 | F411: 605 | G411: 42 | H411: 2 | I411: 4 | J411: 1 | K411: no | M411: =IFERROR(I411/F411,0) -> 0.0066115702 | N411: =IFERROR(J411/F411,0) -> 0.0016528926 | O411: 0 | P411: 1 | Q411: 0 | R411: 0 | S411: 0 | T411: 0 | U411: 0 | V411: 0 | W411: 0 | X411: 0 | Y411: 0 | Z411: 0 | AA411: 0 | AB411: 0 | AC411: 0 | AD411: 0
A412: https://www.tiktok.com/@nawaltechnical/video/7698400608579095828 | B412: nawaltechnical | C412: 5849 | D412: 46314 | E412: 27 | F412: 597 | G412: 17 | H412: 0 | I412: 0 | J412: 4 | K412: no | L412: Aluminium windows and doors with quality finishes and affordable prices | M412: =IFERROR(I412/F412,0) -> 0 | N412: =IFERROR(J412/F412,0) -> 0.0067001675 | O412: 0 | P412: 0 | Q412: 0 | R412: 0 | S412: 0 | T412: 0 | U412: 0 | V412: 0 | W412: 1 | X412: 1 | Y412: 0 | Z412: 0 | AA412: 0 | AB412: 0 | AC412: 0 | AD412: 1
A413: https://www.tiktok.com/@bhattialuminum0/video/7696925002590932246 | B413: bhattialuminum0 | C413: 491 | D413: 46310 | E413: 51 | F413: 580 | G413: 47 | H413: 2 | I413: 0 | J413: 2 | K413: no | L413: Sliding door+fix fream Bismilallah Aluminium and glass work | M413: =IFERROR(I413/F413,0) -> 0 | N413: =IFERROR(J413/F413,0) -> 0.0034482759 | O413: 0 | P413: 0 | Q413: 0 | R413: 0 | S413: 0 | T413: 1 | U413: 0 | V413: 0 | W413: 0 | X413: 1 | Y413: 0 | Z413: 0 | AA413: 0 | AB413: 0 | AC413: 0 | AD413: 0
A414: https://www.tiktok.com/@glasshome.dz/video/7698258481421241621 | B414: glasshome.dz | C414: 14600 | D414: 46314 | E414: 17 | F414: 553 | G414: 32 | H414: 1 | I414: 0 | J414: 1 | K414: no | L414: 🖤 Garde-corps en verre – RAL 7024 ✨ Élégance, modernité et transparence pour une terrasse au style unique ! 🔥 GLASS HOME – Toujours à la hauteur de vos attentes | M414: =IFERROR(I414/F414,0) -> 0 | N414: =IFERROR(J414/F414,0) -> 0.0018083183 | O414: 0 | P414: 0 | Q414: 0 | R414: 0 | S414: 0 | T414: 0 | U414: 1 | V414: 1 | W414: 0 | X414: 0 | Y414: 0 | Z414: 0 | AA414: 0 | AB414: 0 | AC414: 0 | AD414: 0
A415: https://www.tiktok.com/@luminaglassalsace/video/7697742253657165088 | B415: luminaglassalsace | C415: 70 | D415: 46312 | E415: 23 | F415: 548 | G415: 14 | H415: 0 | I415: 3 | J415: 2 | K415: no | L415: #avantapres #gardecorps #verre #escalier #alsace | M415: =IFERROR(I415/F415,0) -> 0.0054744526 | N415: =IFERROR(J415/F415,0) -> 0.003649635 | O415: 0 | P415: 1 | Q415: 0 | R415: 0 | S415: 0 | T415: 0 | U415: 0 | V415: 1 | W415: 0 | X415: 0 | Y415: 0 | Z415: 0 | AA415: 0 | AB415: 0 | AC415: 1 | AD415: 0
A416: https://www.tiktok.com/@nkunadoors/video/7699058062736379156 | B416: nkunadoors | C416: 3420 | D416: 46316 | E416: 25 | F416: 527 | G416: 6 | H416: 4 | I416: 0 | J416: 1 | K416: no | M416: =IFERROR(I416/F416,0) -> 0 | N416: =IFERROR(J416/F416,0) -> 0.0018975332 | O416: 0 | P416: 1 | Q416: 0 | R416: 0 | S416: 0 | T416: 0 | U416: 0 | V416: 0 | W416: 0 | X416: 0 | Y416: 0 | Z416: 0 | AA416: 0 | AB416: 0 | AC416: 0 | AD416: 0
A417: https://www.tiktok.com/@markglassoffciel/video/7698433457751379221 | B417: markglassoffciel | C417: 12800 | D417: 46314 | E417: 14 | F417: 518 | G417: 7 | H417: 0 | I417: 0 | J417: 2 | K417: yes | L417: MARK GLASS : L’expertise du verre et de l’aluminium au Maroc ! 📞 [tel] MARK GLASS, votre expert en verre et aluminium : pergolas, garde-corps, systèmes accordéo | M417: =IFERROR(I417/F417,0) -> 0 | N417: =IFERROR(J417/F417,0) -> 0.0038610039 | O417: 0 | P417: 0 | Q417: 1 | R417: 0 | S417: 0 | T417: 0 | U417: 1 | V417: 1 | W417: 0 | X417: 0 | Y417: 0 | Z417: 0 | AA417: 0 | AB417: 0 | AC417: 0 | AD417: 0
A418: https://www.tiktok.com/@nawaltechnical/video/7698307998703275284 | B418: nawaltechnical | C418: 5849 | D418: 46314 | E418: 35 | F418: 507 | G418: 24 | H418: 0 | I418: 0 | J418: 1 | K418: no | L418: Aluminium windows and doors with quality finishes and | M418: =IFERROR(I418/F418,0) -> 0 | N418: =IFERROR(J418/F418,0) -> 0.0019723866 | O418: 0 | P418: 0 | Q418: 0 | R418: 0 | S418: 0 | T418: 0 | U418: 0 | V418: 0 | W418: 1 | X418: 1 | Y418: 0 | Z418: 0 | AA418: 0 | AB418: 0 | AC418: 0 | AD418: 0
...

Sheet Data Notes
A1: Data notes, method and caveats
A3: Caveats (from the report)
B4: • Instagram: no post data, no competitor data. Section 6F is niche knowledge, not measured.
B5: • Competitor sample is 479 videos from TikTok search pages, so it skews toward visible, popular content. Medians describe this sample, not the whole market. Some comparisons have small groups (the under-10s Moroccan bucket has only 4 videos).
B6: • Correlation, not proof. Arabic captions and hashtag-only captions correlate with higher reach, but those videos are also often kitchen reveals, which is a confound.
B7: • Your last two videos are very new; their views will keep moving.
B8: • Two of your 12 TikTok videos weren't visible to me.
B9: • Competitor figures were read from public pages on 22 Oct 2026. Full list in data/niche-tiktok-videos.csv (third-party phone numbers redacted).
A11: Method
A12: Your TikTok videos | B12: Profile and video pages read on 22 Oct 2026 from public pages. 10 of the 12 videos on the profile were visible.
A13: Niche sample | B13: 480 video links collected from TikTok search ('discover') pages for niche keywords, rendered in a headless browser. Stats read from each public video page. One video returned no data, leaving 479.
A14: Instagram | B14: Only the profile headline numbers (151 followers, 7 following, 15 posts) were readable. No posts, captions or competitor data, so nothing here about Instagram content is measured.
A15: Moroccan flag | B15: 'yes' when the caption or account name matches: maroc, morocco, المغرب, مغرب, fes, fès, casablanca, الدار_البيضاء, tanger, rabat, agadir, marrakech, +212, a 06/07 phone number, bouznika, mohammedia, sefrou, meknes, oujda, kenitra or 🇲🇦.
A16: Caption flags | B16: Arabic = any Arabic letter in the caption. Hashtag-only = nothing left after removing hashtags. Phone = a 06/07 number or +212 in the caption.
A17: Topic flags | B17: Case-insensitive keyword match on the caption (French, English and Arabic terms). A video can match several topics. The patterns are the columns marked 'Flag:' on the Niche Videos sheet.
A18: Medians | B18: Calculated with array formulas (MEDIAN(IF(…))) over the Niche Videos sheet, so they recalculate if you edit or add rows (extend the ranges if you add rows beyond row 480).
A19: Redaction | B19: Phone numbers in third-party captions are replaced by [tel] and captions are cut to 160 characters.
A20: Share and save rates | B20: Per-video shares ÷ views and saves ÷ views, then the median across videos. Rates on videos with very few views are inflated by followers, so use counts as well.
A21: Correlation | B21: Patterns such as Arabic captions or hashtag-only captions correlate with reach but are also linked to the kind of video (for example kitchen reveals).
